Workbook

Sheet 物件データ
A1: 物件データ（入力シートから抽出・売却決済日順）
A2: 青字＝入力シートからの転記値、黒字＝数式。売却決済日が空欄の物件は末尾（未売却）
A4: No | B4: 物件種別 | C4: 物件名 | D4: 仕入決済日 | E4: 売却契約日 | F4: 売却決済日 | G4: 販売価格(円) | H4: 仕入原価(円) | I4: 商品化原価(円) | J4: 期 | K4: 状態 | L4: 集計対象 | M4: 粗利(円) | N4: 粗利率 | O4: 保有日数 | P4: 価格帯 | Q4: 入力シート行 | R4: データ注記
A5: 12 | B5: MSリフォーム再販 | C5: マンション第一多摩川苑 | D5: 44609 | E5: 44823 | F5: 44875 | G5: 25900000 | I5: 0 | J5: =IF(F5="","",IFERROR(INDEX(設定!$A$8:$A$15,MATCH(F5,設定!$B$8:$B$15,1)),"対象外")) -> 10期 | K5: =IF(F5="","未売却",IF(F5<=設定!$B$3,"実績","予定")) -> 実績 | L5: =IF(F5="",0,IF(OR(設定!$B$4="全て",K5="実績"),1,0)) -> 1 | M5: =IF(OR(G5="",H5=""),"",G5-H5-I5) | N5: =IF(M5="","",M5/G5) | O5: =IF(OR(D5="",F5=""),"",F5-D5) -> 266 | P5: =IF(G5="","",IF(INT(G5/設定!$B$5)*設定!$B$5>=100000000,TEXT(INT(G5/設定!$B$5)*設定!$B$5/100000000,"0.0")&"億",TEXT(INT(G5/設定!$B$5)*設定!$B$5/10000,"#,##0")&"万")&"〜") -> 0万〜 | Q5: 16 | R5: 仕入原価未入力→粗利対象外
A6: 19 | B6: 新築戸建 | C6: 東大泉新築Ａ | D6: 44693 | E6: 44819 | F6: 44889 | G6: 59800000 | I6: 13000000 | J6: =IF(F6="","",IFERROR(INDEX(設定!$A$8:$A$15,MATCH(F6,設定!$B$8:$B$15,1)),"対象外")) -> 10期 | K6: =IF(F6="","未売却",IF(F6<=設定!$B$3,"実績","予定")) -> 実績 | L6: =IF(F6="",0,IF(OR(設定!$B$4="全て",K6="実績"),1,0)) -> 1 | M6: =IF(OR(G6="",H6=""),"",G6-H6-I6) | N6: =IF(M6="","",M6/G6) | O6: =IF(OR(D6="",F6=""),"",F6-D6) -> 196 | P6: =IF(G6="","",IF(INT(G6/設定!$B$5)*設定!$B$5>=100000000,TEXT(INT(G6/設定!$B$5)*設定!$B$5/100000000,"0.0")&"億",TEXT(INT(G6/設定!$B$5)*設定!$B$5/10000,"#,##0")&"万")&"〜") -> 5,000万〜 | Q6: 23 | R6: 仕入原価未入力→粗利対象外
A7: 22 | B7: MSリフォーム再販 | C7: コートヒルズ高輪 | D7: 44728 | E7: 44858 | F7: 44910 | G7: 69900000 | I7: 0 | J7: =IF(F7="","",IFERROR(INDEX(設定!$A$8:$A$15,MATCH(F7,設定!$B$8:$B$15,1)),"対象外")) -> 10期 | K7: =IF(F7="","未売却",IF(F7<=設定!$B$3,"実績","予定")) -> 実績 | L7: =IF(F7="",0,IF(OR(設定!$B$4="全て",K7="実績"),1,0)) -> 1 | M7: =IF(OR(G7="",H7=""),"",G7-H7-I7) | N7: =IF(M7="","",M7/G7) | O7: =IF(OR(D7="",F7=""),"",F7-D7) -> 182 | P7: =IF(G7="","",IF(INT(G7/設定!$B$5)*設定!$B$5>=100000000,TEXT(INT(G7/設定!$B$5)*設定!$B$5/100000000,"0.0")&"億",TEXT(INT(G7/設定!$B$5)*設定!$B$5/10000,"#,##0")&"万")&"〜") -> 5,000万〜 | Q7: 26 | R7: 仕入原価未入力→粗利対象外
A8: 29 | B8: 戸建リフォーム再販 | C8: 柿の木坂2丁目中古戸建 | D8: 44799 | E8: 44878 | F8: 44914 | G8: 67800000 | I8: 9000000 | J8: =IF(F8="","",IFERROR(INDEX(設定!$A$8:$A$15,MATCH(F8,設定!$B$8:$B$15,1)),"対象外")) -> 10期 | K8: =IF(F8="","未売却",IF(F8<=設定!$B$3,"実績","予定")) -> 実績 | L8: =IF(F8="",0,IF(OR(設定!$B$4="全て",K8="実績"),1,0)) -> 1 | M8: =IF(OR(G8="",H8=""),"",G8-H8-I8) | N8: =IF(M8="","",M8/G8) | O8: =IF(OR(D8="",F8=""),"",F8-D8) -> 115 | P8: =IF(G8="","",IF(INT(G8/設定!$B$5)*設定!$B$5>=100000000,TEXT(INT(G8/設定!$B$5)*設定!$B$5/100000000,"0.0")&"億",TEXT(INT(G8/設定!$B$5)*設定!$B$5/10000,"#,##0")&"万")&"〜") -> 5,000万〜 | Q8: 33 | R8: 仕入原価未入力→粗利対象外
A9: 39 | B9: MSリフォーム再販 | C9: フィールファイン | D9: 44862 | E9: 44834 | F9: 44915 | G9: 109000000 | I9: 0 | J9: =IF(F9="","",IFERROR(INDEX(設定!$A$8:$A$15,MATCH(F9,設定!$B$8:$B$15,1)),"対象外")) -> 10期 | K9: =IF(F9="","未売却",IF(F9<=設定!$B$3,"実績","予定")) -> 実績 | L9: =IF(F9="",0,IF(OR(設定!$B$4="全て",K9="実績"),1,0)) -> 1 | M9: =IF(OR(G9="",H9=""),"",G9-H9-I9) | N9: =IF(M9="","",M9/G9) | O9: =IF(OR(D9="",F9=""),"",F9-D9) -> 53 | P9: =IF(G9="","",IF(INT(G9/設定!$B$5)*設定!$B$5>=100000000,TEXT(INT(G9/設定!$B$5)*設定!$B$5/100000000,"0.0")&"億",TEXT(INT(G9/設定!$B$5)*設定!$B$5/10000,"#,##0")&"万")&"〜") -> 1.0億〜 | Q9: 43 | R9: 仕入原価未入力→粗利対象外
A10: 20 | B10: 新築戸建 | C10: 東大泉新築Ｂ | D10: 44693 | E10: 44885 | F10: 44921 | G10: 59800000 | I10: 13000000 | J10: =IF(F10="","",IFERROR(INDEX(設定!$A$8:$A$15,MATCH(F10,設定!$B$8:$B$15,1)),"対象外")) -> 10期 | K10: =IF(F10="","未売却",IF(F10<=設定!$B$3,"実績","予定")) -> 実績 | L10: =IF(F10="",0,IF(OR(設定!$B$4="全て",K10="実績"),1,0)) -> 1 | M10: =IF(OR(G10="",H10=""),"",G10-H10-I10) | N10: =IF(M10="","",M10/G10) | O10: =IF(OR(D10="",F10=""),"",F10-D10) -> 228 | P10: =IF(G10="","",IF(INT(G10/設定!$B$5)*設定!$B$5>=100000000,TEXT(INT(G10/設定!$B$5)*設定!$B$5/100000000,"0.0")&"億",TEXT(INT(G10/設定!$B$5)*設定!$B$5/10000,"#,##0")&"万")&"〜") -> 5,000万〜 | Q10: 24 | R10: 仕入原価未入力→粗利対象外
A11: 2 | B11: 新築戸建 | C11: 立野新築Ｂ号棟 | D11: 44413 | E11: 44903 | F11: 44922 | G11: 47800000 | I11: 22000000 | J11: =IF(F11="","",IFERROR(INDEX(設定!$A$8:$A$15,MATCH(F11,設定!$B$8:$B$15,1)),"対象外")) -> 10期 | K11: =IF(F11="","未売却",IF(F11<=設定!$B$3,"実績","予定")) -> 実績 | L11: =IF(F11="",0,IF(OR(設定!$B$4="全て",K11="実績"),1,0)) -> 1 | M11: =IF(OR(G11="",H11=""),"",G11-H11-I11) | N11: =IF(M11="","",M11/G11) | O11: =IF(OR(D11="",F11=""),"",F11-D11) -> 509 | P11: =IF(G11="","",IF(INT(G11/設定!$B$5)*設定!$B$5>=100000000,TEXT(INT(G11/設定!$B$5)*設定!$B$5/100000000,"0.0")&"億",TEXT(INT(G11/設定!$B$5)*設定!$B$5/10000,"#,##0")&"万")&"〜") -> 0万〜 | Q11: 6 | R11: 仕入原価未入力→粗利対象外
A12: 18 | B12: 戸建リフォーム再販 | C12: 墨田区八広中古戸建 | D12: 44620 | E12: 44822 | F12: 44932 | G12: 92800000 | I12: 0 | J12: =IF(F12="","",IFERROR(INDEX(設定!$A$8:$A$15,MATCH(F12,設定!$B$8:$B$15,1)),"対象外")) -> 10期 | K12: =IF(F12="","未売却",IF(F12<=設定!$B$3,"実績","予定")) -> 実績 | L12: =IF(F12="",0,IF(OR(設定!$B$4="全て",K12="実績"),1,0)) -> 1 | M12: =IF(OR(G12="",H12=""),"",G12-H12-I12) | N12: =IF(M12="","",M12/G12) | O12: =IF(OR(D12="",F12=""),"",F12-D12) -> 312 | P12: =IF(G12="","",IF(INT(G12/設定!$B$5)*設定!$B$5>=100000000,TEXT(INT(G12/設定!$B$5)*設定!$B$5/100000000,"0.0")&"億",TEXT(INT(G12/設定!$B$5)*設定!$B$5/10000,"#,##0")&"万")&"〜") -> 5,000万〜 | Q12: 22 | R12: 仕入原価未入力→粗利対象外
A13: 15 | B13: 新築戸建 | C13: 中川新築Ｂ | D13: 44681 | E13: 44794 | F13: 44953 | G13: 39900000 | I13: 14000000 | J13: =IF(F13="","",IFERROR(INDEX(設定!$A$8:$A$15,MATCH(F13,設定!$B$8:$B$15,1)),"対象外")) -> 10期 | K13: =IF(F13="","未売却",IF(F13<=設定!$B$3,"実績","予定")) -> 実績 | L13: =IF(F13="",0,IF(OR(設定!$B$4="全て",K13="実績"),1,0)) -> 1 | M13: =IF(OR(G13="",H13=""),"",G13-H13-I13) | N13: =IF(M13="","",M13/G13) | O13: =IF(OR(D13="",F13=""),"",F13-D13) -> 272 | P13: =IF(G13="","",IF(INT(G13/設定!$B$5)*設定!$B$5>=100000000,TEXT(INT(G13/設定!$B$5)*設定!$B$5/100000000,"0.0")&"億",TEXT(INT(G13/設定!$B$5)*設定!$B$5/10000,"#,##0")&"万")&"〜") -> 0万〜 | Q13: 19 | R13: 仕入原価未入力→粗利対象外
A14: 36 | B14: 戸建リフォーム再販 | C14: 粕谷中古戸建 | D14: 44834 | E14: 44909 | F14: 44963 | G14: 58800000 | I14: 5000000 | J14: =IF(F14="","",IFERROR(INDEX(設定!$A$8:$A$15,MATCH(F14,設定!$B$8:$B$15,1)),"対象外")) -> 10期 | K14: =IF(F14="","未売却",IF(F14<=設定!$B$3,"実績","予定")) -> 実績 | L14: =IF(F14="",0,IF(OR(設定!$B$4="全て",K14="実績"),1,0)) -> 1 | M14: =IF(OR(G14="",H14=""),"",G14-H14-I14) | N14: =IF(M14="","",M14/G14) | O14: =IF(OR(D14="",F14=""),"",F14-D14) -> 129 | P14: =IF(G14="","",IF(INT(G14/設定!$B$5)*設定!$B$5>=100000000,TEXT(INT(G14/設定!$B$5)*設定!$B$5/100000000,"0.0")&"億",TEXT(INT(G14/設定!$B$5)*設定!$B$5/10000,"#,##0")&"万")&"〜") -> 5,000万〜 | Q14: 40 | R14: 仕入原価未入力→粗利対象外
A15: 14 | B15: 新築戸建 | C15: 中川新築Ａ | D15: 44681 | E15: 44915 | F15: 44970 | G15: 39900000 | I15: 14000000 | J15: =IF(F15="","",IFERROR(INDEX(設定!$A$8:$A$15,MATCH(F15,設定!$B$8:$B$15,1)),"対象外")) -> 10期 | K15: =IF(F15="","未売却",IF(F15<=設定!$B$3,"実績","予定")) -> 実績 | L15: =IF(F15="",0,IF(OR(設定!$B$4="全て",K15="実績"),1,0)) -> 1 | M15: =IF(OR(G15="",H15=""),"",G15-H15-I15) | N15: =IF(M15="","",M15/G15) | O15: =IF(OR(D15="",F15=""),"",F15-D15) -> 289 | P15: =IF(G15="","",IF(INT(G15/設定!$B$5)*設定!$B$5>=100000000,TEXT(INT(G15/設定!$B$5)*設定!$B$5/100000000,"0.0")&"億",TEXT(INT(G15/設定!$B$5)*設定!$B$5/10000,"#,##0")&"万")&"〜") -> 0万〜 | Q15: 18 | R15: 仕入原価未入力→粗利対象外
A16: 16 | B16: 新築戸建 | C16: 中川新築Ｃ | D16: 44681 | E16: 44898 | F16: 44970 | G16: 39900000 | I16: 14000000 | J16: =IF(F16="","",IFERROR(INDEX(設定!$A$8:$A$15,MATCH(F16,設定!$B$8:$B$15,1)),"対象外")) -> 10期 | K16: =IF(F16="","未売却",IF(F16<=設定!$B$3,"実績","予定")) -> 実績 | L16: =IF(F16="",0,IF(OR(設定!$B$4="全て",K16="実績"),1,0)) -> 1 | M16: =IF(OR(G16="",H16=""),"",G16-H16-I16) | N16: =IF(M16="","",M16/G16) | O16: =IF(OR(D16="",F16=""),"",F16-D16) -> 289 | P16: =IF(G16="","",IF(INT(G16/設定!$B$5)*設定!$B$5>=100000000,TEXT(INT(G16/設定!$B$5)*設定!$B$5/100000000,"0.0")&"億",TEXT(INT(G16/設定!$B$5)*設定!$B$5/10000,"#,##0")&"万")&"〜") -> 0万〜 | Q16: 20 | R16: 仕入原価未入力→粗利対象外
A17: 7 | B17: 新築戸建 | C17: 世田谷区池尻新築戸建 | D17: 44540 | E17: 44946 | F17: 44985 | G17: 126500000 | I17: 31691326 | J17: =IF(F17="","",IFERROR(INDEX(設定!$A$8:$A$15,MATCH(F17,設定!$B$8:$B$15,1)),"対象外")) -> 10期 | K17: =IF(F17="","未売却",IF(F17<=設定!$B$3,"実績","予定")) -> 実績 | L17: =IF(F17="",0,IF(OR(設定!$B$4="全て",K17="実績"),1,0)) -> 1 | M17: =IF(OR(G17="",H17=""),"",G17-H17-I17) | N17: =IF(M17="","",M17/G17) | O17: =IF(OR(D17="",F17=""),"",F17-D17) -> 445 | P17: =IF(G17="","",IF(INT(G17/設定!$B$5)*設定!$B$5>=100000000,TEXT(INT(G17/設定!$B$5)*設定!$B$5/100000000,"0.0")&"億",TEXT(INT(G17/設定!$B$5)*設定!$B$5/10000,"#,##0")&"万")&"〜") -> 1.0億〜 | Q17: 11 | R17: 仕入原価未入力→粗利対象外
A18: 59 | B18: MSリフォーム再販 | C18: 原宿インペリアルハイツ | E18: 44975 | F18: 44985 | G18: 34800000 | I18: 0 | J18: =IF(F18="","",IFERROR(INDEX(設定!$A$8:$A$15,MATCH(F18,設定!$B$8:$B$15,1)),"対象外")) -> 10期 | K18: =IF(F18="","未売却",IF(F18<=設定!$B$3,"実績","予定")) -> 実績 | L18: =IF(F18="",0,IF(OR(設定!$B$4="全て",K18="実績"),1,0)) -> 1 | M18: =IF(OR(G18="",H18=""),"",G18-H18-I18) | N18: =IF(M18="","",M18/G18) | O18: =IF(OR(D18="",F18=""),"",F18-D18) | P18: =IF(G18="","",IF(INT(G18/設定!$B$5)*設定!$B$5>=100000000,TEXT(INT(G18/設定!$B$5)*設定!$B$5/100000000,"0.0")&"億",TEXT(INT(G18/設定!$B$5)*設定!$B$5/10000,"#,##0")&"万")&"〜") -> 0万〜 | Q18: 63 | R18: 仕入決済日が空欄→保有日数算出不可 / 仕入原価未入力→粗利対象外
A19: 10 | B19: MSリフォーム再販 | C19: クレイシア戸越公園 | D19: 44558 | E19: 44954 | F19: 44991 | G19: 42000000 | I19: 0 | J19: =IF(F19="","",IFERROR(INDEX(設定!$A$8:$A$15,MATCH(F19,設定!$B$8:$B$15,1)),"対象外")) -> 10期 | K19: =IF(F19="","未売却",IF(F19<=設定!$B$3,"実績","予定")) -> 実績 | L19: =IF(F19="",0,IF(OR(設定!$B$4="全て",K19="実績"),1,0)) -> 1 | M19: =IF(OR(G19="",H19=""),"",G19-H19-I19) | N19: =IF(M19="","",M19/G19) | O19: =IF(OR(D19="",F19=""),"",F19-D19) -> 433 | P19: =IF(G19="","",IF(INT(G19/設定!$B$5)*設定!$B$5>=100000000,TEXT(INT(G19/設定!$B$5)*設定!$B$5/100000000,"0.0")&"億",TEXT(INT(G19/設定!$B$5)*設定!$B$5/10000,"#,##0")&"万")&"〜") -> 0万〜 | Q19: 14 | R19: 仕入原価未入力→粗利対象外
A20: 4 | B20: 新築戸建 | C20: 大田区南久が原新築Ａ | D20: 44644 | E20: 44955 | F20: 45008 | G20: 59500000 | I20: 18000000 | J20: =IF(F20="","",IFERROR(INDEX(設定!$A$8:$A$15,MATCH(F20,設定!$B$8:$B$15,1)),"対象外")) -> 10期 | K20: =IF(F20="","未売却",IF(F20<=設定!$B$3,"実績","予定")) -> 実績 | L20: =IF(F20="",0,IF(OR(設定!$B$4="全て",K20="実績"),1,0)) -> 1 | M20: =IF(OR(G20="",H20=""),"",G20-H20-I20) | N20: =IF(M20="","",M20/G20) | O20: =IF(OR(D20="",F20=""),"",F20-D20) -> 364 | P20: =IF(G20="","",IF(INT(G20/設定!$B$5)*設定!$B$5>=100000000,TEXT(INT(G20/設定!$B$5)*設定!$B$5/100000000,"0.0")&"億",TEXT(INT(G20/設定!$B$5)*設定!$B$5/10000,"#,##0")&"万")&"〜") -> 5,000万〜 | Q20: 8 | R20: 仕入原価未入力→粗利対象外
A21: 8 | B21: 新築戸建 | C21: 東雪谷新築戸建A | D21: 44681 | E21: 44834 | F21: 45012 | G21: 48800000 | I21: 13100000 | J21: =IF(F21="","",IFERROR(INDEX(設定!$A$8:$A$15,MATCH(F21,設定!$B$8:$B$15,1)),"対象外")) -> 10期 | K21: =IF(F21="","未売却",IF(F21<=設定!$B$3,"実績","予定")) -> 実績 | L21: =IF(F21="",0,IF(OR(設定!$B$4="全て",K21="実績"),1,0)) -> 1 | M21: =IF(OR(G21="",H21=""),"",G21-H21-I21) | N21: =IF(M21="","",M21/G21) | O21: =IF(OR(D21="",F21=""),"",F21-D21) -> 331 | P21: =IF(G21="","",IF(INT(G21/設定!$B$5)*設定!$B$5>=100000000,TEXT(INT(G21/設定!$B$5)*設定!$B$5/100000000,"0.0")&"億",TEXT(INT(G21/設定!$B$5)*設定!$B$5/10000,"#,##0")&"万")&"〜") -> 0万〜 | Q21: 12 | R21: 仕入原価未入力→粗利対象外
A22: 35 | B22: 条件なし土地 | C22: 中央5丁目ＡＰ用地 | D22: 44830 | E22: 44972 | F22: 45015 | G22: 81000000 | I22: 3000000 | J22: =IF(F22="","",IFERROR(INDEX(設定!$A$8:$A$15,MATCH(F22,設定!$B$8:$B$15,1)),"対象外")) -> 10期 | K22: =IF(F22="","未売却",IF(F22<=設定!$B$3,"実績","予定")) -> 実績 | L22: =IF(F22="",0,IF(OR(設定!$B$4="全て",K22="実績"),1,0)) -> 1 | M22: =IF(OR(G22="",H22=""),"",G22-H22-I22) | N22: =IF(M22="","",M22/G22) | O22: =IF(OR(D22="",F22=""),"",F22-D22) -> 185 | P22: =IF(G22="","",IF(INT(G22/設定!$B$5)*設定!$B$5>=100000000,TEXT(INT(G22/設定!$B$5)*設定!$B$5/100000000,"0.0")&"億",TEXT(INT(G22/設定!$B$5)*設定!$B$5/10000,"#,##0")&"万")&"〜") -> 5,000万〜 | Q22: 39 | R22: 仕入原価未入力→粗利対象外
A23: 44 | B23: 条件なし土地 | C23: 三軒茶屋土地 | D23: 44985 | E23: 45008 | F23: 45058 | G23: 138000000 | H23: 107214000 | I23: 2000000 | J23: =IF(F23="","",IFERROR(INDEX(設定!$A$8:$A$15,MATCH(F23,設定!$B$8:$B$15,1)),"対象外")) -> 10期 | K23: =IF(F23="","未売却",IF(F23<=設定!$B$3,"実績","予定")) -> 実績 | L23: =IF(F23="",0,IF(OR(設定!$B$4="全て",K23="実績"),1,0)) -> 1 | M23: =IF(OR(G23="",H23=""),"",G23-H23-I23) -> 28786000 | N23: =IF(M23="","",M23/G23) -> 0.2085942 | O23: =IF(OR(D23="",F23=""),"",F23-D23) -> 73 | P23: =IF(G23="","",IF(INT(G23/設定!$B$5)*設定!$B$5>=100000000,TEXT(INT(G23/設定!$B$5)*設定!$B$5/100000000,"0.0")&"億",TEXT(INT(G23/設定!$B$5)*設定!$B$5/10000,"#,##0")&"万")&"〜") -> 1.0億〜 | Q23: 48
A24: 43 | B24: 戸建リフォーム再販 | C24: 奥沢中古戸建 | D24: 44921 | E24: 44980 | F24: 45072 | G24: 83800000 | H24: 64458000 | I24: 9000000 | J24: =IF(F24="","",IFERROR(INDEX(設定!$A$8:$A$15,MATCH(F24,設定!$B$8:$B$15,1)),"対象外")) -> 10期 | K24: =IF(F24="","未売却",IF(F24<=設定!$B$3,"実績","予定")) -> 実績 | L24: =IF(F24="",0,IF(OR(設定!$B$4="全て",K24="実績"),1,0)) -> 1 | M24: =IF(OR(G24="",H24=""),"",G24-H24-I24) -> 10342000 | N24: =IF(M24="","",M24/G24) -> 0.12341289 | O24: =IF(OR(D24="",F24=""),"",F24-D24) -> 151 | P24: =IF(G24="","",IF(INT(G24/設定!$B$5)*設定!$B$5>=100000000,TEXT(INT(G24/設定!$B$5)*設定!$B$5/100000000,"0.0")&"億",TEXT(INT(G24/設定!$B$5)*設定!$B$5/10000,"#,##0")&"万")&"〜") -> 5,000万〜 | Q24: 47
A25: 24 | B25: 新築戸建 | C25: 荏原6丁目Ｂ | D25: 44736 | E25: 45018 | F25: 45075 | G25: 64800000 | I25: 0 | J25: =IF(F25="","",IFERROR(INDEX(設定!$A$8:$A$15,MATCH(F25,設定!$B$8:$B$15,1)),"対象外")) -> 10期 | K25: =IF(F25="","未売却",IF(F25<=設定!$B$3,"実績","予定")) -> 実績 | L25: =IF(F25="",0,IF(OR(設定!$B$4="全て",K25="実績"),1,0)) -> 1 | M25: =IF(OR(G25="",H25=""),"",G25-H25-I25) | N25: =IF(M25="","",M25/G25) | O25: =IF(OR(D25="",F25=""),"",F25-D25) -> 339 | P25: =IF(G25="","",IF(INT(G25/設定!$B$5)*設定!$B$5>=100000000,TEXT(INT(G25/設定!$B$5)*設定!$B$5/100000000,"0.0")&"億",TEXT(INT(G25/設定!$B$5)*設定!$B$5/10000,"#,##0")&"万")&"〜") -> 5,000万〜 | Q25: 28 | R25: 仕入原価未入力→粗利対象外
A26: 25 | B26: 新築戸建 | C26: 上小田中1丁目新築Ａ | D26: 44782 | E26: 44905 | F26: 45075 | G26: 48800000 | I26: 16000000 | J26: =IF(F26="","",IFERROR(INDEX(設定!$A$8:$A$15,MATCH(F26,設定!$B$8:$B$15,1)),"対象外")) -> 10期 | K26: =IF(F26="","未売却",IF(F26<=設定!$B$3,"実績","予定")) -> 実績 | L26: =IF(F26="",0,IF(OR(設定!$B$4="全て",K26="実績"),1,0)) -> 1 | M26: =IF(OR(G26="",H26=""),"",G26-H26-I26) | N26: =IF(M26="","",M26/G26) | O26: =IF(OR(D26="",F26=""),"",F26-D26) -> 293 | P26: =IF(G26="","",IF(INT(G26/設定!$B$5)*設定!$B$5>=100000000,TEXT(INT(G26/設定!$B$5)*設定!$B$5/100000000,"0.0")&"億",TEXT(INT(G26/設定!$B$5)*設定!$B$5/10000,"#,##0")&"万")&"〜") -> 0万〜 | Q26: 29 | R26: 仕入原価未入力→粗利対象外
A27: 23 | B27: 新築戸建 | C27: 荏原6丁目Ａ | D27: 44736 | E27: 45031 | F27: 45076 | G27: 64800000 | I27: 0 | J27: =IF(F27="","",IFERROR(INDEX(設定!$A$8:$A$15,MATCH(F27,設定!$B$8:$B$15,1)),"対象外")) -> 10期 | K27: =IF(F27="","未売却",IF(F27<=設定!$B$3,"実績","予定")) -> 実績 | L27: =IF(F27="",0,IF(OR(設定!$B$4="全て",K27="実績"),1,0)) -> 1 | M27: =IF(OR(G27="",H27=""),"",G27-H27-I27) | N27: =IF(M27="","",M27/G27) | O27: =IF(OR(D27="",F27=""),"",F27-D27) -> 340 | P27: =IF(G27="","",IF(INT(G27/設定!$B$5)*設定!$B$5>=100000000,TEXT(INT(G27/設定!$B$5)*設定!$B$5/100000000,"0.0")&"億",TEXT(INT(G27/設定!$B$5)*設定!$B$5/10000,"#,##0")&"万")&"〜") -> 5,000万〜 | Q27: 27 | R27: 仕入原価未入力→粗利対象外
A28: 26 | B28: 新築戸建 | C28: 上小田中1丁目新築戸建Ｂ | D28: 44782 | E28: 44870 | F28: 45082 | G28: 51800000 | I28: 16250000 | J28: =IF(F28="","",IFERROR(INDEX(設定!$A$8:$A$15,MATCH(F28,設定!$B$8:$B$15,1)),"対象外")) -> 10期 | K28: =IF(F28="","未売却",IF(F28<=設定!$B$3,"実績","予定")) -> 実績 | L28: =IF(F28="",0,IF(OR(設定!$B$4="全て",K28="実績"),1,0)) -> 1 | M28: =IF(OR(G28="",H28=""),"",G28-H28-I28) | N28: =IF(M28="","",M28/G28) | O28: =IF(OR(D28="",F28=""),"",F28-D28) -> 300 | P28: =IF(G28="","",IF(INT(G28/設定!$B$5)*設定!$B$5>=100000000,TEXT(INT(G28/設定!$B$5)*設定!$B$5/100000000,"0.0")&"億",TEXT(INT(G28/設定!$B$5)*設定!$B$5/10000,"#,##0")&"万")&"〜") -> 5,000万〜 | Q28: 30 | R28: 仕入原価未入力→粗利対象外
A29: 31 | B29: 条件付き土地 | C29: 若林4丁目条件付土地 | D29: 44819 | E29: 45046 | F29: 45097 | G29: 47800000 | I29: 0 | J29: =IF(F29="","",IFERROR(INDEX(設定!$A$8:$A$15,MATCH(F29,設定!$B$8:$B$15,1)),"対象外")) -> 10期 | K29: =IF(F29="","未売却",IF(F29<=設定!$B$3,"実績","予定")) -> 実績 | L29: =IF(F29="",0,IF(OR(設定!$B$4="全て",K29="実績"),1,0)) -> 1 | M29: =IF(OR(G29="",H29=""),"",G29-H29-I29) | N29: =IF(M29="","",M29/G29) | O29: =IF(OR(D29="",F29=""),"",F29-D29) -> 278 | P29: =IF(G29="","",IF(INT(G29/設定!$B$5)*設定!$B$5>=100000000,TEXT(INT(G29/設定!$B$5)*設定!$B$5/100000000,"0.0")&"億",TEXT(INT(G29/設定!$B$5)*設定!$B$5/10000,"#,##0")&"万")&"〜") -> 0万〜 | Q29: 35 | R29: 仕入原価未入力→粗利対象外
A30: 11 | B30: 新築戸建 | C30: 苅宿新築戸建 | D30: 44830 | E30: 44940 | F30: 45107 | G30: 64900000 | I30: 20000000 | J30: =IF(F30="","",IFERROR(INDEX(設定!$A$8:$A$15,MATCH(F30,設定!$B$8:$B$15,1)),"対象外")) -> 10期 | K30: =IF(F30="","未売却",IF(F30<=設定!$B$3,"実績","予定")) -> 実績 | L30: =IF(F30="",0,IF(OR(設定!$B$4="全て",K30="実績"),1,0)) -> 1 | M30: =IF(OR(G30="",H30=""),"",G30-H30-I30) | N30: =IF(M30="","",M30/G30) | O30: =IF(OR(D30="",F30=""),"",F30-D30) -> 277 | P30: =IF(G30="","",IF(INT(G30/設定!$B$5)*設定!$B$5>=100000000,TEXT(INT(G30/設定!$B$5)*設定!$B$5/100000000,"0.0")&"億",TEXT(INT(G30/設定!$B$5)*設定!$B$5/10000,"#,##0")&"万")&"〜") -> 5,000万〜 | Q30: 15 | R30: 仕入原価未入力→粗利対象外
A31: 32 | B31: 新築戸建 | C31: 宮内3丁目新築戸建Ａ | D31: 44830 | E31: 44998 | F31: 45107 | G31: 46800000 | I31: 16750000 | J31: =IF(F31="","",IFERROR(INDEX(設定!$A$8:$A$15,MATCH(F31,設定!$B$8:$B$15,1)),"対象外")) -> 10期 | K31: =IF(F31="","未売却",IF(F31<=設定!$B$3,"実績","予定")) -> 実績 | L31: =IF(F31="",0,IF(OR(設定!$B$4="全て",K31="実績"),1,0)) -> 1 | M31: =IF(OR(G31="",H31=""),"",G31-H31-I31) | N31: =IF(M31="","",M31/G31) | O31: =IF(OR(D31="",F31=""),"",F31-D31) -> 277 | P31: =IF(G31="","",IF(INT(G31/設定!$B$5)*設定!$B$5>=100000000,TEXT(INT(G31/設定!$B$5)*設定!$B$5/100000000,"0.0")&"億",TEXT(INT(G31/設定!$B$5)*設定!$B$5/10000,"#,##0")&"万")&"〜") -> 0万〜 | Q31: 36 | R31: 仕入原価未入力→粗利対象外
A32: 33 | B32: 新築戸建 | C32: 宮内3丁目新築戸建Ｂ | D32: 44830 | E32: 44988 | F32: 45107 | G32: 45400000 | I32: 16750000 | J32: =IF(F32="","",IFERROR(INDEX(設定!$A$8:$A$15,MATCH(F32,設定!$B$8:$B$15,1)),"対象外")) -> 10期 | K32: =IF(F32="","未売却",IF(F32<=設定!$B$3,"実績","予定")) -> 実績 | L32: =IF(F32="",0,IF(OR(設定!$B$4="全て",K32="実績"),1,0)) -> 1 | M32: =IF(OR(G32="",H32=""),"",G32-H32-I32) | N32: =IF(M32="","",M32/G32) | O32: =IF(OR(D32="",F32=""),"",F32-D32) -> 277 | P32: =IF(G32="","",IF(INT(G32/設定!$B$5)*設定!$B$5>=100000000,TEXT(INT(G32/設定!$B$5)*設定!$B$5/100000000,"0.0")&"億",TEXT(INT(G32/設定!$B$5)*設定!$B$5/10000,"#,##0")&"万")&"〜") -> 0万〜 | Q32: 37 | R32: 仕入原価未入力→粗利対象外
A33: 34 | B33: 新築戸建 | C33: 宮内3丁目新築戸建Ｃ | D33: 44830 | E33: 44920 | F33: 45107 | G33: 48800000 | I33: 16750000 | J33: =IF(F33="","",IFERROR(INDEX(設定!$A$8:$A$15,MATCH(F33,設定!$B$8:$B$15,1)),"対象外")) -> 10期 | K33: =IF(F33="","未売却",IF(F33<=設定!$B$3,"実績","予定")) -> 実績 | L33: =IF(F33="",0,IF(OR(設定!$B$4="全て",K33="実績"),1,0)) -> 1 | M33: =IF(OR(G33="",H33=""),"",G33-H33-I33) | N33: =IF(M33="","",M33/G33) | O33: =IF(OR(D33="",F33=""),"",F33-D33) -> 277 | P33: =IF(G33="","",IF(INT(G33/設定!$B$5)*設定!$B$5>=100000000,TEXT(INT(G33/設定!$B$5)*設定!$B$5/100000000,"0.0")&"億",TEXT(INT(G33/設定!$B$5)*設定!$B$5/10000,"#,##0")&"万")&"〜") -> 0万〜 | Q33: 38 | R33: 仕入原価未入力→粗利対象外
A34: 42 | B34: 条件付き土地 | C34: 目黒本町5丁目条件付き土地 | D34: 44957 | E34: 45077 | F34: 45107 | G34: 59900000 | H34: 50366400 | I34: 500000 | J34: =IF(F34="","",IFERROR(INDEX(設定!$A$8:$A$15,MATCH(F34,設定!$B$8:$B$15,1)),"対象外")) -> 10期 | K34: =IF(F34="","未売却",IF(F34<=設定!$B$3,"実績","予定")) -> 実績 | L34: =IF(F34="",0,IF(OR(設定!$B$4="全て",K34="実績"),1,0)) -> 1 | M34: =IF(OR(G34="",H34=""),"",G34-H34-I34) -> 9033600 | N34: =IF(M34="","",M34/G34) -> 0.15081135 | O34: =IF(OR(D34="",F34=""),"",F34-D34) -> 150 | P34: =IF(G34="","",IF(INT(G34/設定!$B$5)*設定!$B$5>=100000000,TEXT(INT(G34/設定!$B$5)*設定!$B$5/100000000,"0.0")&"億",TEXT(INT(G34/設定!$B$5)*設定!$B$5/10000,"#,##0")&"万")&"〜") -> 5,000万〜 | Q34: 46
A35: 62 | B35: MSリフォーム再販 | C35: 上馬マンション | D35: 45082 | E35: 45079 | F35: 45114 | G35: 21000000 | H35: 16000000 | I35: 0 | J35: =IF(F35="","",IFERROR(INDEX(設定!$A$8:$A$15,MATCH(F35,設定!$B$8:$B$15,1)),"対象外")) -> 11期 | K35: =IF(F35="","未売却",IF(F35<=設定!$B$3,"実績","予定")) -> 実績 | L35: =IF(F35="",0,IF(OR(設定!$B$4="全て",K35="実績"),1,0)) -> 1 | M35: =IF(OR(G35="",H35=""),"",G35-H35-I35) -> 5000000 | N35: =IF(M35="","",M35/G35) -> 0.23809524 | O35: =IF(OR(D35="",F35=""),"",F35-D35) -> 32 | P35: =IF(G35="","",IF(INT(G35/設定!$B$5)*設定!$B$5>=100000000,TEXT(INT(G35/設定!$B$5)*設定!$B$5/100000000,"0.0")&"億",TEXT(INT(G35/設定!$B$5)*設定!$B$5/10000,"#,##0")&"万")&"〜") -> 0万〜 | Q35: 66
A36: 21 | B36: OC転売 | C36: サンパルムOC転売 | D36: 44694 | E36: 45166 | F36: 45166 | G36: 39000000 | I36: 0 | J36: =IF(F36="","",IFERROR(INDEX(設定!$A$8:$A$15,MATCH(F36,設定!$B$8:$B$15,1)),"対象外")) -> 11期 | K36: =IF(F36="","未売却",IF(F36<=設定!$B$3,"実績","予定")) -> 実績 | L36: =IF(F36="",0,IF(OR(設定!$B$4="全て",K36="実績"),1,0)) -> 1 | M36: =IF(OR(G36="",H36=""),"",G36-H36-I36) | N36: =IF(M36="","",M36/G36) | O36: =IF(OR(D36="",F36=""),"",F36-D36) -> 472 | P36: =IF(G36="","",IF(INT(G36/設定!$B$5)*設定!$B$5>=100000000,TEXT(INT(G36/設定!$B$5)*設定!$B$5/100000000,"0.0")&"億",TEXT(INT(G36/設定!$B$5)*設定!$B$5/10000,"#,##0")&"万")&"〜") -> 0万〜 | Q36: 25 | R36: 仕入原価未入力→粗利対象外
A37: 37 | B37: 条件なし土地 | C37: 東山MS土地売り | D37: 44865 | E37: 45022 | F37: 45169 | G37: 400000000 | I37: 50000000 | J37: =IF(F37="","",IFERROR(INDEX(設定!$A$8:$A$15,MATCH(F37,設定!$B$8:$B$15,1)),"対象外")) -> 11期 | K37: =IF(F37="","未売却",IF(F37<=設定!$B$3,"実績","予定")) -> 実績 | L37: =IF(F37="",0,IF(OR(設定!$B$4="全て",K37="実績"),1,0)) -> 1 | M37: =IF(OR(G37="",H37=""),"",G37-H37-I37) | N37: =IF(M37="","",M37/G37) | O37: =IF(OR(D37="",F37=""),"",F37-D37) -> 304 | P37: =IF(G37="","",IF(INT(G37/設定!$B$5)*設定!$B$5>=100000000,TEXT(INT(G37/設定!$B$5)*設定!$B$5/100000000,"0.0")&"億",TEXT(INT(G37/設定!$B$5)*設定!$B$5/10000,"#,##0")&"万")&"〜") -> 4.0億〜 | Q37: 41 | R37: 仕入原価未入力→粗利対象外
A38: 27 | B38: 新築戸建 | C38: 北寺尾2丁目新築戸建Ａ | D38: 44798 | F38: 45194 | G38: 52800000 | I38: 15000000 | J38: =IF(F38="","",IFERROR(INDEX(設定!$A$8:$A$15,MATCH(F38,設定!$B$8:$B$15,1)),"対象外")) -> 11期 | K38: =IF(F38="","未売却",IF(F38<=設定!$B$3,"実績","予定")) -> 実績 | L38: =IF(F38="",0,IF(OR(設定!$B$4="全て",K38="実績"),1,0)) -> 1 | M38: =IF(OR(G38="",H38=""),"",G38-H38-I38) | N38: =IF(M38="","",M38/G38) | O38: =IF(OR(D38="",F38=""),"",F38-D38) -> 396 | P38: =IF(G38="","",IF(INT(G38/設定!$B$5)*設定!$B$5>=100000000,TEXT(INT(G38/設定!$B$5)*設定!$B$5/100000000,"0.0")&"億",TEXT(INT(G38/設定!$B$5)*設定!$B$5/10000,"#,##0")&"万")&"〜") -> 5,000万〜 | Q38: 31 | R38: 仕入原価未入力→粗利対象外
A39: 28 | B39: 新築戸建 | C39: 北寺尾2丁目新築戸建Ｂ | D39: 44798 | F39: 45194 | G39: 54800000 | I39: 15000000 | J39: =IF(F39="","",IFERROR(INDEX(設定!$A$8:$A$15,MATCH(F39,設定!$B$8:$B$15,1)),"対象外")) -> 11期 | K39: =IF(F39="","未売却",IF(F39<=設定!$B$3,"実績","予定")) -> 実績 | L39: =IF(F39="",0,IF(OR(設定!$B$4="全て",K39="実績"),1,0)) -> 1 | M39: =IF(OR(G39="",H39=""),"",G39-H39-I39) | N39: =IF(M39="","",M39/G39) | O39: =IF(OR(D39="",F39=""),"",F39-D39) -> 396 | P39: =IF(G39="","",IF(INT(G39/設定!$B$5)*設定!$B$5>=100000000,TEXT(INT(G39/設定!$B$5)*設定!$B$5/100000000,"0.0")&"億",TEXT(INT(G39/設定!$B$5)*設定!$B$5/10000,"#,##0")&"万")&"〜") -> 5,000万〜 | Q39: 32 | R39: 仕入原価未入力→粗利対象外
A40: 56 | B40: MSリフォーム再販 | C40: ｼﾘｳｽｺｰﾄ川崎南 | D40: 45015 | E40: 45219 | F40: 45260 | G40: 27650000 | H40: 28550000 | I40: 7150000 | J40: =IF(F40="","",IFERROR(INDEX(設定!$A$8:$A$15,MATCH(F40,設定!$B$8:$B$15,1)),"対象外")) -> 11期 | K40: =IF(F40="","未売却",IF(F40<=設定!$B$3,"実績","予定")) -> 実績 | L40: =IF(F40="",0,IF(OR(設定!$B$4="全て",K40="実績"),1,0)) -> 1 | M40: =IF(OR(G40="",H40=""),"",G40-H40-I40) -> -8050000 | N40: =IF(M40="","",M40/G40) -> -0.29113924 | O40: =IF(OR(D40="",F40=""),"",F40-D40) -> 245 | P40: =IF(G40="","",IF(INT(G40/設定!$B$5)*設定!$B$5>=100000000,TEXT(INT(G40/設定!$B$5)*設定!$B$5/100000000,"0.0")&"億",TEXT(INT(G40/設定!$B$5)*設定!$B$5/10000,"#,##0")&"万")&"〜") -> 0万〜 | Q40: 60 | R40: 原価が売価を上回る
A41: 82 | B41: MSリフォーム再販 | C41: ｼｬﾝﾎﾞｰﾙ互恵ビル | D41: 45194 | E41: 45234 | F41: 45270 | G41: 19500000 | H41: 15600000 | I41: 0 | J41: =IF(F41="","",IFERROR(INDEX(設定!$A$8:$A$15,MATCH(F41,設定!$B$8:$B$15,1)),"対象外")) -> 11期 | K41: =IF(F41="","未売却",IF(F41<=設定!$B$3,"実績","予定")) -> 実績 | L41: =IF(F41="",0,IF(OR(設定!$B$4="全て",K41="実績"),1,0)) -> 1 | M41: =IF(OR(G41="",H41=""),"",G41-H41-I41) -> 3900000 | N41: =IF(M41="","",M41/G41) -> 0.2 | O41: =IF(OR(D41="",F41=""),"",F41-D41) -> 76 | P41: =IF(G41="","",IF(INT(G41/設定!$B$5)*設定!$B$5>=100000000,TEXT(INT(G41/設定!$B$5)*設定!$B$5/100000000,"0.0")&"億",TEXT(INT(G41/設定!$B$5)*設定!$B$5/10000,"#,##0")&"万")&"〜") -> 0万〜 | Q41: 86
A42: 53 | B42: 新築戸建 | C42: 幸区古市場新築Ｂ | D42: 44995 | E42: 45148 | F42: 45281 | G42: 53400000 | H42: 28750000 | I42: 18250000 | J42: =IF(F42="","",IFERROR(INDEX(設定!$A$8:$A$15,MATCH(F42,設定!$B$8:$B$15,1)),"対象外")) -> 11期 | K42: =IF(F42="","未売却",IF(F42<=設定!$B$3,"実績","予定")) -> 実績 | L42: =IF(F42="",0,IF(OR(設定!$B$4="全て",K42="実績"),1,0)) -> 1 | M42: =IF(OR(G42="",H42=""),"",G42-H42-I42) -> 6400000 | N42: =IF(M42="","",M42/G42) -> 0.11985019 | O42: =IF(OR(D42="",F42=""),"",F42-D42) -> 286 | P42: =IF(G42="","",IF(INT(G42/設定!$B$5)*設定!$B$5>=100000000,TEXT(INT(G42/設定!$B$5)*設定!$B$5/100000000,"0.0")&"億",TEXT(INT(G42/設定!$B$5)*設定!$B$5/10000,"#,##0")&"万")&"〜") -> 5,000万〜 | Q42: 57
A43: 58 | B43: 戸建リフォーム再販 | C43: 上池台３丁目中古戸建 | D43: 45076 | E43: 45262 | F43: 45286 | G43: 82800000 | H43: 60800000 | I43: 5300000 | J43: =IF(F43="","",IFERROR(INDEX(設定!$A$8:$A$15,MATCH(F43,設定!$B$8:$B$15,1)),"対象外")) -> 11期 | K43: =IF(F43="","未売却",IF(F43<=設定!$B$3,"実績","予定")) -> 実績 | L43: =IF(F43="",0,IF(OR(設定!$B$4="全て",K43="実績"),1,0)) -> 1 | M43: =IF(OR(G43="",H43=""),"",G43-H43-I43) -> 16700000 | N43: =IF(M43="","",M43/G43) -> 0.20169082 | O43: =IF(OR(D43="",F43=""),"",F43-D43) -> 210 | P43: =IF(G43="","",IF(INT(G43/設定!$B$5)*設定!$B$5>=100000000,TEXT(INT(G43/設定!$B$5)*設定!$B$5/100000000,"0.0")&"億",TEXT(INT(G43/設定!$B$5)*設定!$B$5/10000,"#,##0")&"万")&"〜") -> 5,000万〜 | Q43: 62
A44: 77 | B44: 戸建リフォーム再販 | C44: 生田中古戸建 | D44: 45134 | E44: 45249 | F44: 45286 | G44: 42800000 | H44: 31000000 | I44: 7950000 | J44: =IF(F44="","",IFERROR(INDEX(設定!$A$8:$A$15,MATCH(F44,設定!$B$8:$B$15,1)),"対象外")) -> 11期 | K44: =IF(F44="","未売却",IF(F44<=設定!$B$3,"実績","予定")) -> 実績 | L44: =IF(F44="",0,IF(OR(設定!$B$4="全て",K44="実績"),1,0)) -> 1 | M44: =IF(OR(G44="",H44=""),"",G44-H44-I44) -> 3850000 | N44: =IF(M44="","",M44/G44) -> 0.089953271 | O44: =IF(OR(D44="",F44=""),"",F44-D44) -> 152 | P44: =IF(G44="","",IF(INT(G44/設定!$B$5)*設定!$B$5>=100000000,TEXT(INT(G44/設定!$B$5)*設定!$B$5/100000000,"0.0")&"億",TEXT(INT(G44/設定!$B$5)*設定!$B$5/10000,"#,##0")&"万")&"〜") -> 0万〜 | Q44: 81
A45: 67 | B45: 一棟収益天端 | C45: 五井中央西一棟マンション | D45: 45076 | E45: 45278 | F45: 45313 | G45: 56500000 | H45: 34400000 | I45: 7000000 | J45: =IF(F45="","",IFERROR(INDEX(設定!$A$8:$A$15,MATCH(F45,設定!$B$8:$B$15,1)),"対象外")) -> 11期 | K45: =IF(F45="","未売却",IF(F45<=設定!$B$3,"実績","予定")) -> 実績 | L45: =IF(F45="",0,IF(OR(設定!$B$4="全て",K45="実績"),1,0)) -> 1 | M45: =IF(OR(G45="",H45=""),"",G45-H45-I45) -> 15100000 | N45: =IF(M45="","",M45/G45) -> 0.26725664 | O45: =IF(OR(D45="",F45=""),"",F45-D45) -> 237 | P45: =IF(G45="","",IF(INT(G45/設定!$B$5)*設定!$B$5>=100000000,TEXT(INT(G45/設定!$B$5)*設定!$B$5/100000000,"0.0")&"億",TEXT(INT(G45/設定!$B$5)*設定!$B$5/10000,"#,##0")&"万")&"〜") -> 5,000万〜 | Q45: 71
A46: 52 | B46: 新築戸建 | C46: 幸区古市場新築Ａ | D46: 44995 | E46: 45278 | F46: 45322 | G46: 50000000 | H46: 28750000 | I46: 18250000 | J46: =IF(F46="","",IFERROR(INDEX(設定!$A$8:$A$15,MATCH(F46,設定!$B$8:$B$15,1)),"対象外")) -> 11期 | K46: =IF(F46="","未売却",IF(F46<=設定!$B$3,"実績","予定")) -> 実績 | L46: =IF(F46="",0,IF(OR(設定!$B$4="全て",K46="実績"),1,0)) -> 1 | M46: =IF(OR(G46="",H46=""),"",G46-H46-I46) -> 3000000 | N46: =IF(M46="","",M46/G46) -> 0.06 | O46: =IF(OR(D46="",F46=""),"",F46-D46) -> 327 | P46: =IF(G46="","",IF(INT(G46/設定!$B$5)*設定!$B$5>=100000000,TEXT(INT(G46/設定!$B$5)*設定!$B$5/100000000,"0.0")&"億",TEXT(INT(G46/設定!$B$5)*設定!$B$5/10000,"#,##0")&"万")&"〜") -> 5,000万〜 | Q46: 56
A47: 55 | B47: 新築戸建 | C47: 幸区古市場新築Ｄ | D47: 44995 | E47: 45304 | F47: 45337 | G47: 52900000 | H47: 28750000 | I47: 18250000 | J47: =IF(F47="","",IFERROR(INDEX(設定!$A$8:$A$15,MATCH(F47,設定!$B$8:$B$15,1)),"対象外")) -> 11期 | K47: =IF(F47="","未売却",IF(F47<=設定!$B$3,"実績","予定")) -> 実績 | L47: =IF(F47="",0,IF(OR(設定!$B$4="全て",K47="実績"),1,0)) -> 1 | M47: =IF(OR(G47="",H47=""),"",G47-H47-I47) -> 5900000 | N47: =IF(M47="","",M47/G47) -> 0.11153119 | O47: =IF(OR(D47="",F47=""),"",F47-D47) -> 342 | P47: =IF(G47="","",IF(INT(G47/設定!$B$5)*設定!$B$5>=100000000,TEXT(INT(G47/設定!$B$5)*設定!$B$5/100000000,"0.0")&"億",TEXT(INT(G47/設定!$B$5)*設定!$B$5/10000,"#,##0")&"万")&"〜") -> 5,000万〜 | Q47: 59
A48: 54 | B48: 新築戸建 | C48: 幸区古市場新築Ｃ | D48: 44995 | E48: 45303 | F48: 45340 | G48: 49900000 | H48: 28750000 | I48: 18250000 | J48: =IF(F48="","",IFERROR(INDEX(設定!$A$8:$A$15,MATCH(F48,設定!$B$8:$B$15,1)),"対象外")) -> 11期 | K48: =IF(F48="","未売却",IF(F48<=設定!$B$3,"実績","予定")) -> 実績 | L48: =IF(F48="",0,IF(OR(設定!$B$4="全て",K48="実績"),1,0)) -> 1 | M48: =IF(OR(G48="",H48=""),"",G48-H48-I48) -> 2900000 | N48: =IF(M48="","",M48/G48) -> 0.058116232 | O48: =IF(OR(D48="",F48=""),"",F48-D48) -> 345 | P48: =IF(G48="","",IF(INT(G48/設定!$B$5)*設定!$B$5>=100000000,TEXT(INT(G48/設定!$B$5)*設定!$B$5/100000000,"0.0")&"億",TEXT(INT(G48/設定!$B$5)*設定!$B$5/10000,"#,##0")&"万")&"〜") -> 0万〜 | Q48: 58
A49: 57 | B49: MSリフォーム再販 | C49: ドミール南青山 | D49: 45026 | E49: 45309 | F49: 45350 | G49: 91400000 | H49: 75600000 | I49: 10200000 | J49: =IF(F49="","",IFERROR(INDEX(設定!$A$8:$A$15,MATCH(F49,設定!$B$8:$B$15,1)),"対象外")) -> 11期 | K49: =IF(F49="","未売却",IF(F49<=設定!$B$3,"実績","予定")) -> 実績 | L49: =IF(F49="",0,IF(OR(設定!$B$4="全て",K49="実績"),1,0)) -> 1 | M49: =IF(OR(G49="",H49=""),"",G49-H49-I49) -> 5600000 | N49: =IF(M49="","",M49/G49) -> 0.061269147 | O49: =IF(OR(D49="",F49=""),"",F49-D49) -> 324 | P49: =IF(G49="","",IF(INT(G49/設定!$B$5)*設定!$B$5>=100000000,TEXT(INT(G49/設定!$B$5)*設定!$B$5/100000000,"0.0")&"億",TEXT(INT(G49/設定!$B$5)*設定!$B$5/10000,"#,##0")&"万")&"〜") -> 5,000万〜 | Q49: 61
A50: 63 | B50: 新築戸建 | C50: 荏原5丁目新築A | D50: 45104 | E50: 45283 | F50: 45350 | G50: 49800000 | H50: 35866666 | I50: 5100000 | J50: =IF(F50="","",IFERROR(INDEX(設定!$A$8:$A$15,MATCH(F50,設定!$B$8:$B$15,1)),"対象外")) -> 11期 | K50: =IF(F50="","未売却",IF(F50<=設定!$B$3,"実績","予定")) -> 実績 | L50: =IF(F50="",0,IF(OR(設定!$B$4="全て",K50="実績"),1,0)) -> 1 | M50: =IF(OR(G50="",H50=""),"",G50-H50-I50) -> 8833334 | N50: =IF(M50="","",M50/G50) -> 0.17737618 | O50: =IF(OR(D50="",F50=""),"",F50-D50) -> 246 | P50: =IF(G50="","",IF(INT(G50/設定!$B$5)*設定!$B$5>=100000000,TEXT(INT(G50/設定!$B$5)*設定!$B$5/100000000,"0.0")&"億",TEXT(INT(G50/設定!$B$5)*設定!$B$5/10000,"#,##0")&"万")&"〜") -> 0万〜 | Q50: 67
A51: 65 | B51: 新築戸建 | C51: 荏原5丁目新築C | D51: 45104 | E51: 45270 | F51: 45350 | G51: 49800000 | H51: 35866668 | I51: 5100000 | J51: =IF(F51="","",IFERROR(INDEX(設定!$A$8:$A$15,MATCH(F51,設定!$B$8:$B$15,1)),"対象外")) -> 11期 | K51: =IF(F51="","未売却",IF(F51<=設定!$B$3,"実績","予定")) -> 実績 | L51: =IF(F51="",0,IF(OR(設定!$B$4="全て",K51="実績"),1,0)) -> 1 | M51: =IF(OR(G51="",H51=""),"",G51-H51-I51) -> 8833332 | N51: =IF(M51="","",M51/G51) -> 0.17737614 | O51: =IF(OR(D51="",F51=""),"",F51-D51) -> 246 | P51: =IF(G51="","",IF(INT(G51/設定!$B$5)*設定!$B$5>=100000000,TEXT(INT(G51/設定!$B$5)*設定!$B$5/100000000,"0.0")&"億",TEXT(INT(G51/設定!$B$5)*設定!$B$5/10000,"#,##0")&"万")&"〜") -> 0万〜 | Q51: 69
A52: 66 | B52: 一棟収益天端 | C52: 中幸一棟収益 | D52: 45107 | E52: 45230 | F52: 45350 | G52: 117000000 | H52: 74600000 | I52: 24000000 | J52: =IF(F52="","",IFERROR(INDEX(設定!$A$8:$A$15,MATCH(F52,設定!$B$8:$B$15,1)),"対象外")) -> 11期 | K52: =IF(F52="","未売却",IF(F52<=設定!$B$3,"実績","予定")) -> 実績 | L52: =IF(F52="",0,IF(OR(設定!$B$4="全て",K52="実績"),1,0)) -> 1 | M52: =IF(OR(G52="",H52=""),"",G52-H52-I52) -> 18400000 | N52: =IF(M52="","",M52/G52) -> 0.15726496 | O52: =IF(OR(D52="",F52=""),"",F52-D52) -> 243 | P52: =IF(G52="","",IF(INT(G52/設定!$B$5)*設定!$B$5>=100000000,TEXT(INT(G52/設定!$B$5)*設定!$B$5/100000000,"0.0")&"億",TEXT(INT(G52/設定!$B$5)*設定!$B$5/10000,"#,##0")&"万")&"〜") -> 1.0億〜 | Q52: 70
... A73: 85 | B73: 新築戸建 | C73: 板橋区坂下新築 | D73: 45503 | E73: 45537 | F73: 45596 | G73: 30900000 | H73: 20900000 | I73: 4300000 | J73: =IF(F73="","",IFERROR(INDEX(設定!$A$8:$A$15,MATCH(F73,設定!$B$8:$B$15,1)),"対象外")) -> 13期 | K73: =IF(F73="","未売却",IF(F73<=設定!$B$3,"実績","予定")) -> 実績 | L73: =IF(F73="",0,IF(OR(設定!$B$4="全て",K73="実績"),1,0)) -> 1 | M73: =IF(OR(G73="",H73=""),"",G73-H73-I73) -> 5700000 | N73: =IF(M73="","",M73/G73) -> 0.18446602 | O73: =IF(OR(D73="",F73=""),"",F73-D73) -> 93 | P73: =IF(G73="","",IF(INT(G73/設定!$B$5)*設定!$B$5>=100000000,TEXT(INT(G73/設定!$B$5)*設定!$B$5/100000000,"0.0")&"億",TEXT(INT(G73/設定!$B$5)*設定!$B$5/10000,"#,##0")&"万")&"〜") -> 0万〜 | Q73: 89
A74: 38 | B74: 新築戸建 | C74: 小山6丁目新築戸建 | D74: 45230 | E74: 45577 | F74: 45619 | G74: 109000000 | I74: 26800000 | J74: =IF(F74="","",IFERROR(INDEX(設定!$A$8:$A$15,MATCH(F74,設定!$B$8:$B$15,1)),"対象外")) -> 13期 | K74: =IF(F74="","未売却",IF(F74<=設定!$B$3,"実績","予定")) -> 実績 | L74: =IF(F74="",0,IF(OR(設定!$B$4="全て",K74="実績"),1,0)) -> 1 | M74: =IF(OR(G74="",H74=""),"",G74-H74-I74) | N74: =IF(M74="","",M74/G74) | O74: =IF(OR(D74="",F74=""),"",F74-D74) -> 389 | P74: =IF(G74="","",IF(INT(G74/設定!$B$5)*設定!$B$5>=100000000,TEXT(INT(G74/設定!$B$5)*設定!$B$5/100000000,"0.0")&"億",TEXT(INT(G74/設定!$B$5)*設定!$B$5/10000,"#,##0")&"万")&"〜") -> 1.0億〜 | Q74: 42 | R74: 仕入原価未入力→粗利対象外
A75: 95 | B75: MSリフォーム再販 | C75: ステラレジデンス横濱 | D75: 45380 | E75: 45594 | F75: 45636 | G75: 43800000 | H75: 32400000 | I75: 6000000 | J75: =IF(F75="","",IFERROR(INDEX(設定!$A$8:$A$15,MATCH(F75,設定!$B$8:$B$15,1)),"対象外")) -> 13期 | K75: =IF(F75="","未売却",IF(F75<=設定!$B$3,"実績","予定")) -> 実績 | L75: =IF(F75="",0,IF(OR(設定!$B$4="全て",K75="実績"),1,0)) -> 1 | M75: =IF(OR(G75="",H75=""),"",G75-H75-I75) -> 5400000 | N75: =IF(M75="","",M75/G75) -> 0.12328767 | O75: =IF(OR(D75="",F75=""),"",F75-D75) -> 256 | P75: =IF(G75="","",IF(INT(G75/設定!$B$5)*設定!$B$5>=100000000,TEXT(INT(G75/設定!$B$5)*設定!$B$5/100000000,"0.0")&"億",TEXT(INT(G75/設定!$B$5)*設定!$B$5/10000,"#,##0")&"万")&"〜") -> 0万〜 | Q75: 99
A76: 90 | B76: 新築戸建 | C76: 矢向借地権B | D76: 45313 | E76: 45607 | F76: 45645 | G76: 42800000 | H76: 14500000 | I76: 17690000 | J76: =IF(F76="","",IFERROR(INDEX(設定!$A$8:$A$15,MATCH(F76,設定!$B$8:$B$15,1)),"対象外")) -> 13期 | K76: =IF(F76="","未売却",IF(F76<=設定!$B$3,"実績","予定")) -> 実績 | L76: =IF(F76="",0,IF(OR(設定!$B$4="全て",K76="実績"),1,0)) -> 1 | M76: =IF(OR(G76="",H76=""),"",G76-H76-I76) -> 10610000 | N76: =IF(M76="","",M76/G76) -> 0.2478972 | O76: =IF(OR(D76="",F76=""),"",F76-D76) -> 332 | P76: =IF(G76="","",IF(INT(G76/設定!$B$5)*設定!$B$5>=100000000,TEXT(INT(G76/設定!$B$5)*設定!$B$5/100000000,"0.0")&"億",TEXT(INT(G76/設定!$B$5)*設定!$B$5/10000,"#,##0")&"万")&"〜") -> 0万〜 | Q76: 94
A77: 75 | B77: MSリフォーム再販 | C77: 東海経堂マンション | D77: 45137 | E77: 45616 | F77: 45646 | G77: 29000000 | H77: 34800000 | I77: 7300000 | J77: =IF(F77="","",IFERROR(INDEX(設定!$A$8:$A$15,MATCH(F77,設定!$B$8:$B$15,1)),"対象外")) -> 13期 | K77: =IF(F77="","未売却",IF(F77<=設定!$B$3,"実績","予定")) -> 実績 | L77: =IF(F77="",0,IF(OR(設定!$B$4="全て",K77="実績"),1,0)) -> 1 | M77: =IF(OR(G77="",H77=""),"",G77-H77-I77) -> -13100000 | N77: =IF(M77="","",M77/G77) -> -0.45172414 | O77: =IF(OR(D77="",F77=""),"",F77-D77) -> 509 | P77: =IF(G77="","",IF(INT(G77/設定!$B$5)*設定!$B$5>=100000000,TEXT(INT(G77/設定!$B$5)*設定!$B$5/100000000,"0.0")&"億",TEXT(INT(G77/設定!$B$5)*設定!$B$5/10000,"#,##0")&"万")&"〜") -> 0万〜 | Q77: 79 | R77: 原価が売価を上回る
A78: 105 | B78: 戸建リフォーム再販 | C78: 江戸川区松島4丁目中古戸建 | D78: 45626 | E78: 45619 | F78: 45651 | G78: 46800000 | H78: 30500000 | I78: 10500000 | J78: =IF(F78="","",IFERROR(INDEX(設定!$A$8:$A$15,MATCH(F78,設定!$B$8:$B$15,1)),"対象外")) -> 13期 | K78: =IF(F78="","未売却",IF(F78<=設定!$B$3,"実績","予定")) -> 実績 | L78: =IF(F78="",0,IF(OR(設定!$B$4="全て",K78="実績"),1,0)) -> 1 | M78: =IF(OR(G78="",H78=""),"",G78-H78-I78) -> 5800000 | N78: =IF(M78="","",M78/G78) -> 0.12393162 | O78: =IF(OR(D78="",F78=""),"",F78-D78) -> 25 | P78: =IF(G78="","",IF(INT(G78/設定!$B$5)*設定!$B$5>=100000000,TEXT(INT(G78/設定!$B$5)*設定!$B$5/100000000,"0.0")&"億",TEXT(INT(G78/設定!$B$5)*設定!$B$5/10000,"#,##0")&"万")&"〜") -> 0万〜 | Q78: 109
A79: 99 | B79: 戸建リフォーム再販 | C79: 亀戸中古戸建て | D79: 45513 | E79: 45613 | F79: 45677 | G79: 47800000 | H79: 34600000 | I79: 8000000 | J79: =IF(F79="","",IFERROR(INDEX(設定!$A$8:$A$15,MATCH(F79,設定!$B$8:$B$15,1)),"対象外")) -> 13期 | K79: =IF(F79="","未売却",IF(F79<=設定!$B$3,"実績","予定")) -> 実績 | L79: =IF(F79="",0,IF(OR(設定!$B$4="全て",K79="実績"),1,0)) -> 1 | M79: =IF(OR(G79="",H79=""),"",G79-H79-I79) -> 5200000 | N79: =IF(M79="","",M79/G79) -> 0.10878661 | O79: =IF(OR(D79="",F79=""),"",F79-D79) -> 164 | P79: =IF(G79="","",IF(INT(G79/設定!$B$5)*設定!$B$5>=100000000,TEXT(INT(G79/設定!$B$5)*設定!$B$5/100000000,"0.0")&"億",TEXT(INT(G79/設定!$B$5)*設定!$B$5/10000,"#,##0")&"万")&"〜") -> 0万〜 | Q79: 103
A80: 101 | B80: 条件付き土地 | C80: 南馬込1丁目条件付土地A | D80: 45534 | E80: 45642 | F80: 45702 | G80: 48800000 | H80: 30000000 | I80: 3180000 | J80: =IF(F80="","",IFERROR(INDEX(設定!$A$8:$A$15,MATCH(F80,設定!$B$8:$B$15,1)),"対象外")) -> 13期 | K80: =IF(F80="","未売却",IF(F80<=設定!$B$3,"実績","予定")) -> 実績 | L80: =IF(F80="",0,IF(OR(設定!$B$4="全て",K80="実績"),1,0)) -> 1 | M80: =IF(OR(G80="",H80=""),"",G80-H80-I80) -> 15620000 | N80: =IF(M80="","",M80/G80) -> 0.32008197 | O80: =IF(OR(D80="",F80=""),"",F80-D80) -> 168 | P80: =IF(G80="","",IF(INT(G80/設定!$B$5)*設定!$B$5>=100000000,TEXT(INT(G80/設定!$B$5)*設定!$B$5/100000000,"0.0")&"億",TEXT(INT(G80/設定!$B$5)*設定!$B$5/10000,"#,##0")&"万")&"〜") -> 0万〜 | Q80: 105
A81: 88 | B81: 新築戸建 | C81: 鵜の木借地権新築 | D81: 45350 | E81: 45675 | F81: 45716 | G81: 28900000 | H81: 13900000 | I81: 10000000 | J81: =IF(F81="","",IFERROR(INDEX(設定!$A$8:$A$15,MATCH(F81,設定!$B$8:$B$15,1)),"対象外")) -> 13期 | K81: =IF(F81="","未売却",IF(F81<=設定!$B$3,"実績","予定")) -> 実績 | L81: =IF(F81="",0,IF(OR(設定!$B$4="全て",K81="実績"),1,0)) -> 1 | M81: =IF(OR(G81="",H81=""),"",G81-H81-I81) -> 5000000 | N81: =IF(M81="","",M81/G81) -> 0.17301038 | O81: =IF(OR(D81="",F81=""),"",F81-D81) -> 366 | P81: =IF(G81="","",IF(INT(G81/設定!$B$5)*設定!$B$5>=100000000,TEXT(INT(G81/設定!$B$5)*設定!$B$5/100000000,"0.0")&"億",TEXT(INT(G81/設定!$B$5)*設定!$B$5/10000,"#,##0")&"万")&"〜") -> 0万〜 | Q81: 92
A82: 78 | B82: MSリフォーム再販 | C82: クレイシア北千束 | D82: 45204 | E82: 45683 | F82: 45744 | G82: 54000000 | I82: 6600000 | J82: =IF(F82="","",IFERROR(INDEX(設定!$A$8:$A$15,MATCH(F82,設定!$B$8:$B$15,1)),"対象外")) -> 13期 | K82: =IF(F82="","未売却",IF(F82<=設定!$B$3,"実績","予定")) -> 実績 | L82: =IF(F82="",0,IF(OR(設定!$B$4="全て",K82="実績"),1,0)) -> 1 | M82: =IF(OR(G82="",H82=""),"",G82-H82-I82) | N82: =IF(M82="","",M82/G82) | O82: =IF(OR(D82="",F82=""),"",F82-D82) -> 540 | P82: =IF(G82="","",IF(INT(G82/設定!$B$5)*設定!$B$5>=100000000,TEXT(INT(G82/設定!$B$5)*設定!$B$5/100000000,"0.0")&"億",TEXT(INT(G82/設定!$B$5)*設定!$B$5/10000,"#,##0")&"万")&"〜") -> 5,000万〜 | Q82: 82 | R82: 仕入原価未入力→粗利対象外
A83: 119 | B83: OC転売 | C83: 文京区千石1丁目中古戸建OC | D83: 45719 | E83: 45677 | F83: 45747 | G83: 102000000 | H83: 88700000 | I83: 0 | J83: =IF(F83="","",IFERROR(INDEX(設定!$A$8:$A$15,MATCH(F83,設定!$B$8:$B$15,1)),"対象外")) -> 13期 | K83: =IF(F83="","未売却",IF(F83<=設定!$B$3,"実績","予定")) -> 実績 | L83: =IF(F83="",0,IF(OR(設定!$B$4="全て",K83="実績"),1,0)) -> 1 | M83: =IF(OR(G83="",H83=""),"",G83-H83-I83) -> 13300000 | N83: =IF(M83="","",M83/G83) -> 0.13039216 | O83: =IF(OR(D83="",F83=""),"",F83-D83) -> 28 | P83: =IF(G83="","",IF(INT(G83/設定!$B$5)*設定!$B$5>=100000000,TEXT(INT(G83/設定!$B$5)*設定!$B$5/100000000,"0.0")&"億",TEXT(INT(G83/設定!$B$5)*設定!$B$5/10000,"#,##0")&"万")&"〜") -> 1.0億〜 | Q83: 123
A84: 114 | B84: 戸建リフォーム再販 | C84: 赤塚4丁目中古戸建 | D84: 45641 | E84: 45716 | F84: 45775 | G84: 44800000 | H84: 24200000 | I84: 13000000 | J84: =IF(F84="","",IFERROR(INDEX(設定!$A$8:$A$15,MATCH(F84,設定!$B$8:$B$15,1)),"対象外")) -> 13期 | K84: =IF(F84="","未売却",IF(F84<=設定!$B$3,"実績","予定")) -> 実績 | L84: =IF(F84="",0,IF(OR(設定!$B$4="全て",K84="実績"),1,0)) -> 1 | M84: =IF(OR(G84="",H84=""),"",G84-H84-I84) -> 7600000 | N84: =IF(M84="","",M84/G84) -> 0.16964286 | O84: =IF(OR(D84="",F84=""),"",F84-D84) -> 134 | P84: =IF(G84="","",IF(INT(G84/設定!$B$5)*設定!$B$5>=100000000,TEXT(INT(G84/設定!$B$5)*設定!$B$5/100000000,"0.0")&"億",TEXT(INT(G84/設定!$B$5)*設定!$B$5/10000,"#,##0")&"万")&"〜") -> 0万〜 | Q84: 118
A85: 92 | B85: 新築戸建 | C85: 南長崎A号棟 | D85: 45366 | E85: 45736 | F85: 45803 | G85: 41000000 | H85: 32000000 | I85: 6000000 | J85: =IF(F85="","",IFERROR(INDEX(設定!$A$8:$A$15,MATCH(F85,設定!$B$8:$B$15,1)),"対象外")) -> 13期 | K85: =IF(F85="","未売却",IF(F85<=設定!$B$3,"実績","予定")) -> 実績 | L85: =IF(F85="",0,IF(OR(設定!$B$4="全て",K85="実績"),1,0)) -> 1 | M85: =IF(OR(G85="",H85=""),"",G85-H85-I85) -> 3000000 | N85: =IF(M85="","",M85/G85) -> 0.073170732 | O85: =IF(OR(D85="",F85=""),"",F85-D85) -> 437 | P85: =IF(G85="","",IF(INT(G85/設定!$B$5)*設定!$B$5>=100000000,TEXT(INT(G85/設定!$B$5)*設定!$B$5/100000000,"0.0")&"億",TEXT(INT(G85/設定!$B$5)*設定!$B$5/10000,"#,##0")&"万")&"〜") -> 0万〜 | Q85: 96
A86: 93 | B86: 新築戸建 | C86: 南長崎B号棟 | D86: 45366 | E86: 45736 | F86: 45803 | G86: 41000000 | H86: 32000000 | I86: 0 | J86: =IF(F86="","",IFERROR(INDEX(設定!$A$8:$A$15,MATCH(F86,設定!$B$8:$B$15,1)),"対象外")) -> 13期 | K86: =IF(F86="","未売却",IF(F86<=設定!$B$3,"実績","予定")) -> 実績 | L86: =IF(F86="",0,IF(OR(設定!$B$4="全て",K86="実績"),1,0)) -> 1 | M86: =IF(OR(G86="",H86=""),"",G86-H86-I86) -> 9000000 | N86: =IF(M86="","",M86/G86) -> 0.2195122 | O86: =IF(OR(D86="",F86=""),"",F86-D86) -> 437 | P86: =IF(G86="","",IF(INT(G86/設定!$B$5)*設定!$B$5>=100000000,TEXT(INT(G86/設定!$B$5)*設定!$B$5/100000000,"0.0")&"億",TEXT(INT(G86/設定!$B$5)*設定!$B$5/10000,"#,##0")&"万")&"〜") -> 0万〜 | Q86: 97
A87: 117 | B87: 条件なし土地 | C87: 東浪見解体土地売り2区画A | D87: 45629 | E87: 45745 | F87: 45806 | G87: 6800000 | H87: 2800000 | I87: 8349000 | J87: =IF(F87="","",IFERROR(INDEX(設定!$A$8:$A$15,MATCH(F87,設定!$B$8:$B$15,1)),"対象外")) -> 13期 | K87: =IF(F87="","未売却",IF(F87<=設定!$B$3,"実績","予定")) -> 実績 | L87: =IF(F87="",0,IF(OR(設定!$B$4="全て",K87="実績"),1,0)) -> 1 | M87: =IF(OR(G87="",H87=""),"",G87-H87-I87) -> -4349000 | N87: =IF(M87="","",M87/G87) -> -0.63955882 | O87: =IF(OR(D87="",F87=""),"",F87-D87) -> 177 | P87: =IF(G87="","",IF(INT(G87/設定!$B$5)*設定!$B$5>=100000000,TEXT(INT(G87/設定!$B$5)*設定!$B$5/100000000,"0.0")&"億",TEXT(INT(G87/設定!$B$5)*設定!$B$5/10000,"#,##0")&"万")&"〜") -> 0万〜 | Q87: 121 | R87: 原価が売価を上回る
A88: 106 | B88: 立ち退き後転売土地 | C88: 井田杉山町立ち退きA棟 | D88: 45535 | E88: 45704 | F88: 45808 | G88: 43900000 | H88: 28500000 | I88: 14370000 | J88: =IF(F88="","",IFERROR(INDEX(設定!$A$8:$A$15,MATCH(F88,設定!$B$8:$B$15,1)),"対象外")) -> 13期 | K88: =IF(F88="","未売却",IF(F88<=設定!$B$3,"実績","予定")) -> 実績 | L88: =IF(F88="",0,IF(OR(設定!$B$4="全て",K88="実績"),1,0)) -> 1 | M88: =IF(OR(G88="",H88=""),"",G88-H88-I88) -> 1030000 | N88: =IF(M88="","",M88/G88) -> 0.023462415 | O88: =IF(OR(D88="",F88=""),"",F88-D88) -> 273 | P88: =IF(G88="","",IF(INT(G88/設定!$B$5)*設定!$B$5>=100000000,TEXT(INT(G88/設定!$B$5)*設定!$B$5/100000000,"0.0")&"億",TEXT(INT(G88/設定!$B$5)*設定!$B$5/10000,"#,##0")&"万")&"〜") -> 0万〜 | Q88: 110
A89: 122 | B89: 条件なし土地 | C89: 世田谷区池尻3丁目土地A区画 | D89: 45744 | E89: 45790 | F89: 45818 | G89: 140000000 | H89: 114100000 | I89: 700000 | J89: =IF(F89="","",IFERROR(INDEX(設定!$A$8:$A$15,MATCH(F89,設定!$B$8:$B$15,1)),"対象外")) -> 13期 | K89: =IF(F89="","未売却",IF(F89<=設定!$B$3,"実績","予定")) -> 実績 | L89: =IF(F89="",0,IF(OR(設定!$B$4="全て",K89="実績"),1,0)) -> 1 | M89: =IF(OR(G89="",H89=""),"",G89-H89-I89) -> 25200000 | N89: =IF(M89="","",M89/G89) -> 0.18 | O89: =IF(OR(D89="",F89=""),"",F89-D89) -> 74 | P89: =IF(G89="","",IF(INT(G89/設定!$B$5)*設定!$B$5>=100000000,TEXT(INT(G89/設定!$B$5)*設定!$B$5/100000000,"0.0")&"億",TEXT(INT(G89/設定!$B$5)*設定!$B$5/10000,"#,##0")&"万")&"〜") -> 1.0億〜 | Q89: 126
A90: 123 | B90: 条件なし土地 | C90: 世田谷区池尻3丁目土地B区画 | D90: 45744 | E90: 45790 | F90: 45818 | G90: 103500000 | H90: 78100000 | I90: 0 | J90: =IF(F90="","",IFERROR(INDEX(設定!$A$8:$A$15,MATCH(F90,設定!$B$8:$B$15,1)),"対象外")) -> 13期 | K90: =IF(F90="","未売却",IF(F90<=設定!$B$3,"実績","予定")) -> 実績 | L90: =IF(F90="",0,IF(OR(設定!$B$4="全て",K90="実績"),1,0)) -> 1 | M90: =IF(OR(G90="",H90=""),"",G90-H90-I90) -> 25400000 | N90: =IF(M90="","",M90/G90) -> 0.24541063 | O90: =IF(OR(D90="",F90=""),"",F90-D90) -> 74 | P90: =IF(G90="","",IF(INT(G90/設定!$B$5)*設定!$B$5>=100000000,TEXT(INT(G90/設定!$B$5)*設定!$B$5/100000000,"0.0")&"億",TEXT(INT(G90/設定!$B$5)*設定!$B$5/10000,"#,##0")&"万")&"〜") -> 1.0億〜 | Q90: 127
A91: 91 | B91: 新築戸建 | C91: 矢向借地権C | D91: 45313 | E91: 45802 | F91: 45838 | G91: 43900000 | H91: 14100000 | I91: 23110000 | J91: =IF(F91="","",IFERROR(INDEX(設定!$A$8:$A$15,MATCH(F91,設定!$B$8:$B$15,1)),"対象外")) -> 13期 | K91: =IF(F91="","未売却",IF(F91<=設定!$B$3,"実績","予定")) -> 実績 | L91: =IF(F91="",0,IF(OR(設定!$B$4="全て",K91="実績"),1,0)) -> 1 | M91: =IF(OR(G91="",H91=""),"",G91-H91-I91) -> 6690000 | N91: =IF(M91="","",M91/G91) -> 0.1523918 | O91: =IF(OR(D91="",F91=""),"",F91-D91) -> 525 | P91: =IF(G91="","",IF(INT(G91/設定!$B$5)*設定!$B$5>=100000000,TEXT(INT(G91/設定!$B$5)*設定!$B$5/100000000,"0.0")&"億",TEXT(INT(G91/設定!$B$5)*設定!$B$5/10000,"#,##0")&"万")&"〜") -> 0万〜 | Q91: 95
A92: 128 | B92: 一棟収益天端 | C92: 太子堂5丁目収益MS | D92: 45838 | E92: 45786 | F92: 45838 | G92: 110000000 | H92: 94700000 | I92: 5500000 | J92: =IF(F92="","",IFERROR(INDEX(設定!$A$8:$A$15,MATCH(F92,設定!$B$8:$B$15,1)),"対象外")) -> 13期 | K92: =IF(F92="","未売却",IF(F92<=設定!$B$3,"実績","予定")) -> 実績 | L92: =IF(F92="",0,IF(OR(設定!$B$4="全て",K92="実績"),1,0)) -> 1 | M92: =IF(OR(G92="",H92=""),"",G92-H92-I92) -> 9800000 | N92: =IF(M92="","",M92/G92) -> 0.089090909 | O92: =IF(OR(D92="",F92=""),"",F92-D92) -> 0 | P92: =IF(G92="","",IF(INT(G92/設定!$B$5)*設定!$B$5>=100000000,TEXT(INT(G92/設定!$B$5)*設定!$B$5/100000000,"0.0")&"億",TEXT(INT(G92/設定!$B$5)*設定!$B$5/10000,"#,##0")&"万")&"〜") -> 1.0億〜 | Q92: 132
A93: 120 | B93: 条件付き土地 | C93: 大田区仲六郷条件付き土地 | D93: 45777 | E93: 45794 | F93: 45845 | G93: 41800000 | H93: 30500000 | I93: 8390000 | J93: =IF(F93="","",IFERROR(INDEX(設定!$A$8:$A$15,MATCH(F93,設定!$B$8:$B$15,1)),"対象外")) -> 13期 | K93: =IF(F93="","未売却",IF(F93<=設定!$B$3,"実績","予定")) -> 実績 | L93: =IF(F93="",0,IF(OR(設定!$B$4="全て",K93="実績"),1,0)) -> 1 | M93: =IF(OR(G93="",H93=""),"",G93-H93-I93) -> 2910000 | N93: =IF(M93="","",M93/G93) -> 0.069617225 | O93: =IF(OR(D93="",F93=""),"",F93-D93) -> 68 | P93: =IF(G93="","",IF(INT(G93/設定!$B$5)*設定!$B$5>=100000000,TEXT(INT(G93/設定!$B$5)*設定!$B$5/100000000,"0.0")&"億",TEXT(INT(G93/設定!$B$5)*設定!$B$5/10000,"#,##0")&"万")&"〜") -> 0万〜 | Q93: 124
A94: 125 | B94: 立ち退き後転売土地 | C94: 井田杉山町立ち退きB棟 | D94: 45535 | E94: 45823 | F94: 45866 | G94: 41000000 | H94: 28500000 | I94: 0 | J94: =IF(F94="","",IFERROR(INDEX(設定!$A$8:$A$15,MATCH(F94,設定!$B$8:$B$15,1)),"対象外")) -> 13期 | K94: =IF(F94="","未売却",IF(F94<=設定!$B$3,"実績","予定")) -> 実績 | L94: =IF(F94="",0,IF(OR(設定!$B$4="全て",K94="実績"),1,0)) -> 1 | M94: =IF(OR(G94="",H94=""),"",G94-H94-I94) -> 12500000 | N94: =IF(M94="","",M94/G94) -> 0.30487805 | O94: =IF(OR(D94="",F94=""),"",F94-D94) -> 331 | P94: =IF(G94="","",IF(INT(G94/設定!$B$5)*設定!$B$5>=100000000,TEXT(INT(G94/設定!$B$5)*設定!$B$5/100000000,"0.0")&"億",TEXT(INT(G94/設定!$B$5)*設定!$B$5/10000,"#,##0")&"万")&"〜") -> 0万〜 | Q94: 129
A95: 126 | B95: 条件付き土地 | C95: 品川区荏原2丁目条件付き土地 | D95: 45828 | E95: 45806 | F95: 45867 | G95: 97800000 | H95: 73980000 | I95: 500000 | J95: =IF(F95="","",IFERROR(INDEX(設定!$A$8:$A$15,MATCH(F95,設定!$B$8:$B$15,1)),"対象外")) -> 13期 | K95: =IF(F95="","未売却",IF(F95<=設定!$B$3,"実績","予定")) -> 実績 | L95: =IF(F95="",0,IF(OR(設定!$B$4="全て",K95="実績"),1,0)) -> 1 | M95: =IF(OR(G95="",H95=""),"",G95-H95-I95) -> 23320000 | N95: =IF(M95="","",M95/G95) -> 0.23844581 | O95: =IF(OR(D95="",F95=""),"",F95-D95) -> 39 | P95: =IF(G95="","",IF(INT(G95/設定!$B$5)*設定!$B$5>=100000000,TEXT(INT(G95/設定!$B$5)*設定!$B$5/100000000,"0.0")&"億",TEXT(INT(G95/設定!$B$5)*設定!$B$5/10000,"#,##0")&"万")&"〜") -> 5,000万〜 | Q95: 130
A96: 97 | B96: JT | C96: 上目黒4丁目コンセプト住宅 | D96: 45427 | E96: 45836 | F96: 45873 | G96: 320000000 | H96: 158000000 | I96: 84250000 | J96: =IF(F96="","",IFERROR(INDEX(設定!$A$8:$A$15,MATCH(F96,設定!$B$8:$B$15,1)),"対象外")) -> 13期 | K96: =IF(F96="","未売却",IF(F96<=設定!$B$3,"実績","予定")) -> 実績 | L96: =IF(F96="",0,IF(OR(設定!$B$4="全て",K96="実績"),1,0)) -> 1 | M96: =IF(OR(G96="",H96=""),"",G96-H96-I96) -> 77750000 | N96: =IF(M96="","",M96/G96) -> 0.24296875 | O96: =IF(OR(D96="",F96=""),"",F96-D96) -> 446 | P96: =IF(G96="","",IF(INT(G96/設定!$B$5)*設定!$B$5>=100000000,TEXT(INT(G96/設定!$B$5)*設定!$B$5/100000000,"0.0")&"億",TEXT(INT(G96/設定!$B$5)*設定!$B$5/10000,"#,##0")&"万")&"〜") -> 3.0億〜 | Q96: 101
A97: 103 | B97: 新築戸建 | C97: 南馬込1丁目新築C | D97: 45565 | E97: 45796 | F97: 45894 | G97: 56000000 | H97: 29100000 | I97: 22000000 | J97: =IF(F97="","",IFERROR(INDEX(設定!$A$8:$A$15,MATCH(F97,設定!$B$8:$B$15,1)),"対象外")) -> 13期 | K97: =IF(F97="","未売却",IF(F97<=設定!$B$3,"実績","予定")) -> 実績 | L97: =IF(F97="",0,IF(OR(設定!$B$4="全て",K97="実績"),1,0)) -> 1 | M97: =IF(OR(G97="",H97=""),"",G97-H97-I97) -> 4900000 | N97: =IF(M97="","",M97/G97) -> 0.0875 | O97: =IF(OR(D97="",F97=""),"",F97-D97) -> 329 | P97: =IF(G97="","",IF(INT(G97/設定!$B$5)*設定!$B$5>=100000000,TEXT(INT(G97/設定!$B$5)*設定!$B$5/100000000,"0.0")&"億",TEXT(INT(G97/設定!$B$5)*設定!$B$5/10000,"#,##0")&"万")&"〜") -> 5,000万〜 | Q97: 107
A98: 118 | B98: 立ち退き後転売土地 | C98: 品川区大井立ち退き戸建 | D98: 45653 | E98: 45836 | F98: 45894 | G98: 42800000 | H98: 37100000 | I98: 0 | J98: =IF(F98="","",IFERROR(INDEX(設定!$A$8:$A$15,MATCH(F98,設定!$B$8:$B$15,1)),"対象外")) -> 13期 | K98: =IF(F98="","未売却",IF(F98<=設定!$B$3,"実績","予定")) -> 実績 | L98: =IF(F98="",0,IF(OR(設定!$B$4="全て",K98="実績"),1,0)) -> 1 | M98: =IF(OR(G98="",H98=""),"",G98-H98-I98) -> 5700000 | N98: =IF(M98="","",M98/G98) -> 0.13317757 | O98: =IF(OR(D98="",F98=""),"",F98-D98) -> 241 | P98: =IF(G98="","",IF(INT(G98/設定!$B$5)*設定!$B$5>=100000000,TEXT(INT(G98/設定!$B$5)*設定!$B$5/100000000,"0.0")&"億",TEXT(INT(G98/設定!$B$5)*設定!$B$5/10000,"#,##0")&"万")&"〜") -> 0万〜 | Q98: 122
A99: 86 | B99: 新築戸建 | C99: 井田中ノ町新築A号棟 | D99: 45306 | E99: 45828 | F99: 45911 | G99: 65800000 | H99: 25400000 | I99: 34100000 | J99: =IF(F99="","",IFERROR(INDEX(設定!$A$8:$A$15,MATCH(F99,設定!$B$8:$B$15,1)),"対象外")) -> 13期 | K99: =IF(F99="","未売却",IF(F99<=設定!$B$3,"実績","予定")) -> 実績 | L99: =IF(F99="",0,IF(OR(設定!$B$4="全て",K99="実績"),1,0)) -> 1 | M99: =IF(OR(G99="",H99=""),"",G99-H99-I99) -> 6300000 | N99: =IF(M99="","",M99/G99) -> 0.095744681 | O99: =IF(OR(D99="",F99=""),"",F99-D99) -> 605 | P99: =IF(G99="","",IF(INT(G99/設定!$B$5)*設定!$B$5>=100000000,TEXT(INT(G99/設定!$B$5)*設定!$B$5/100000000,"0.0")&"億",TEXT(INT(G99/設定!$B$5)*設定!$B$5/10000,"#,##0")&"万")&"〜") -> 5,000万〜 | Q99: 90
... A104: 127 | B104: 条件なし土地 | C104: 東浪見解体土地売り2区画B | D104: 45629 | E104: 45892 | F104: 45926 | G104: 10500000 | H104: 3300000 | I104: 990000 | J104: =IF(F104="","",IFERROR(INDEX(設定!$A$8:$A$15,MATCH(F104,設定!$B$8:$B$15,1)),"対象外")) -> 13期 | K104: =IF(F104="","未売却",IF(F104<=設定!$B$3,"実績","予定")) -> 実績 | L104: =IF(F104="",0,IF(OR(設定!$B$4="全て",K104="実績"),1,0)) -> 1 | M104: =IF(OR(G104="",H104=""),"",G104-H104-I104) -> 6210000 | N104: =IF(M104="","",M104/G104) -> 0.59142857 | O104: =IF(OR(D104="",F104=""),"",F104-D104) -> 297 | P104: =IF(G104="","",IF(INT(G104/設定!$B$5)*設定!$B$5>=100000000,TEXT(INT(G104/設定!$B$5)*設定!$B$5/100000000,"0.0")&"億",TEXT(INT(G104/設定!$B$5)*設定!$B$5/10000,"#,##0")&"万")&"〜") -> 0万〜 | Q104: 131
A105: 112 | B105: MSリフォーム再販 | C105: ワールドパレス第二戸越 | D105: 45611 | E105: 45912 | F105: 45930 | G105: 16000000 | H105: 15800000 | I105: 1250000 | J105: =IF(F105="","",IFERROR(INDEX(設定!$A$8:$A$15,MATCH(F105,設定!$B$8:$B$15,1)),"対象外")) -> 13期 | K105: =IF(F105="","未売却",IF(F105<=設定!$B$3,"実績","予定")) -> 実績 | L105: =IF(F105="",0,IF(OR(設定!$B$4="全て",K105="実績"),1,0)) -> 1 | M105: =IF(OR(G105="",H105=""),"",G105-H105-I105) -> -1050000 | N105: =IF(M105="","",M105/G105) -> -0.065625 | O105: =IF(OR(D105="",F105=""),"",F105-D105) -> 319 | P105: =IF(G105="","",IF(INT(G105/設定!$B$5)*設定!$B$5>=100000000,TEXT(INT(G105/設定!$B$5)*設定!$B$5/100000000,"0.0")&"億",TEXT(INT(G105/設定!$B$5)*設定!$B$5/10000,"#,##0")&"万")&"〜") -> 0万〜 | Q105: 116 | R105: 原価が売価を上回る
A106: 124 | B106: 戸建リフォーム再販 | C106: 世田谷区奥沢2丁目中古戸建 | D106: 45730 | E106: 45927 | F106: 45960 | G106: 136900000 | H106: 126700000 | I106: 800000 | J106: =IF(F106="","",IFERROR(INDEX(設定!$A$8:$A$15,MATCH(F106,設定!$B$8:$B$15,1)),"対象外")) -> 14期 | K106: =IF(F106="","未売却",IF(F106<=設定!$B$3,"実績","予定")) -> 実績 | L106: =IF(F106="",0,IF(OR(設定!$B$4="全て",K106="実績"),1,0)) -> 1 | M106: =IF(OR(G106="",H106=""),"",G106-H106-I106) -> 9400000 | N106: =IF(M106="","",M106/G106) -> 0.068663258 | O106: =IF(OR(D106="",F106=""),"",F106-D106) -> 230 | P106: =IF(G106="","",IF(INT(G106/設定!$B$5)*設定!$B$5>=100000000,TEXT(INT(G106/設定!$B$5)*設定!$B$5/100000000,"0.0")&"億",TEXT(INT(G106/設定!$B$5)*設定!$B$5/10000,"#,##0")&"万")&"〜") -> 1.0億〜 | Q106: 128
A107: 80 | B107: 立ち退き後転売土地 | C107: 田園調布１丁目立ち退き土地B | D107: 45230 | E107: 45930 | F107: 45982 | G107: 128000000 | H107: 66500000 | I107: 47893910 | J107: =IF(F107="","",IFERROR(INDEX(設定!$A$8:$A$15,MATCH(F107,設定!$B$8:$B$15,1)),"対象外")) -> 14期 | K107: =IF(F107="","未売却",IF(F107<=設定!$B$3,"実績","予定")) -> 実績 | L107: =IF(F107="",0,IF(OR(設定!$B$4="全て",K107="実績"),1,0)) -> 1 | M107: =IF(OR(G107="",H107=""),"",G107-H107-I107) -> 13606090 | N107: =IF(M107="","",M107/G107) -> 0.10629758 | O107: =IF(OR(D107="",F107=""),"",F107-D107) -> 752 | P107: =IF(G107="","",IF(INT(G107/設定!$B$5)*設定!$B$5>=100000000,TEXT(INT(G107/設定!$B$5)*設定!$B$5/100000000,"0.0")&"億",TEXT(INT(G107/設定!$B$5)*設定!$B$5/10000,"#,##0")&"万")&"〜") -> 1.0億〜 | Q107: 84
A108: 113 | B108: 新築戸建 | C108: 池上5丁目借地権付き新築戸建 | D108: 45640 | E108: 45950 | F108: 45991 | G108: 64900000 | H108: 28600000 | I108: 29500000 | J108: =IF(F108="","",IFERROR(INDEX(設定!$A$8:$A$15,MATCH(F108,設定!$B$8:$B$15,1)),"対象外")) -> 14期 | K108: =IF(F108="","未売却",IF(F108<=設定!$B$3,"実績","予定")) -> 実績 | L108: =IF(F108="",0,IF(OR(設定!$B$4="全て",K108="実績"),1,0)) -> 1 | M108: =IF(OR(G108="",H108=""),"",G108-H108-I108) -> 6800000 | N108: =IF(M108="","",M108/G108) -> 0.10477658 | O108: =IF(OR(D108="",F108=""),"",F108-D108) -> 351 | P108: =IF(G108="","",IF(INT(G108/設定!$B$5)*設定!$B$5>=100000000,TEXT(INT(G108/設定!$B$5)*設定!$B$5/100000000,"0.0")&"億",TEXT(INT(G108/設定!$B$5)*設定!$B$5/10000,"#,##0")&"万")&"〜") -> 5,000万〜 | Q108: 117
A109: 116 | B109: 戸建リフォーム再販 | C109: 砧 中古戸建 | D109: 45646 | E109: 45940 | F109: 45991 | G109: 81000000 | H109: 61800000 | I109: 10000000 | J109: =IF(F109="","",IFERROR(INDEX(設定!$A$8:$A$15,MATCH(F109,設定!$B$8:$B$15,1)),"対象外")) -> 14期 | K109: =IF(F109="","未売却",IF(F109<=設定!$B$3,"実績","予定")) -> 実績 | L109: =IF(F109="",0,IF(OR(設定!$B$4="全て",K109="実績"),1,0)) -> 1 | M109: =IF(OR(G109="",H109=""),"",G109-H109-I109) -> 9200000 | N109: =IF(M109="","",M109/G109) -> 0.11358025 | O109: =IF(OR(D109="",F109=""),"",F109-D109) -> 345 | P109: =IF(G109="","",IF(INT(G109/設定!$B$5)*設定!$B$5>=100000000,TEXT(INT(G109/設定!$B$5)*設定!$B$5/100000000,"0.0")&"億",TEXT(INT(G109/設定!$B$5)*設定!$B$5/10000,"#,##0")&"万")&"〜") -> 5,000万〜 | Q109: 120
A110: 107 | B110: 新築戸建 | C110: 大田区南久が原1丁目新築A | D110: 45583 | E110: 45858 | F110: 46011 | G110: 77000000 | H110: 37100000 | I110: 26000000 | J110: =IF(F110="","",IFERROR(INDEX(設定!$A$8:$A$15,MATCH(F110,設定!$B$8:$B$15,1)),"対象外")) -> 14期 | K110: =IF(F110="","未売却",IF(F110<=設定!$B$3,"実績","予定")) -> 実績 | L110: =IF(F110="",0,IF(OR(設定!$B$4="全て",K110="実績"),1,0)) -> 1 | M110: =IF(OR(G110="",H110=""),"",G110-H110-I110) -> 13900000 | N110: =IF(M110="","",M110/G110) -> 0.18051948 | O110: =IF(OR(D110="",F110=""),"",F110-D110) -> 428 | P110: =IF(G110="","",IF(INT(G110/設定!$B$5)*設定!$B$5>=100000000,TEXT(INT(G110/設定!$B$5)*設定!$B$5/100000000,"0.0")&"億",TEXT(INT(G110/設定!$B$5)*設定!$B$5/10000,"#,##0")&"万")&"〜") -> 5,000万〜 | Q110: 111
A111: 145 | B111: MSリフォーム再販 | C111: シャンボール第二都立大 | E111: 45981 | F111: 46011 | G111: 33000000 | I111: 0 | J111: =IF(F111="","",IFERROR(INDEX(設定!$A$8:$A$15,MATCH(F111,設定!$B$8:$B$15,1)),"対象外")) -> 14期 | K111: =IF(F111="","未売却",IF(F111<=設定!$B$3,"実績","予定")) -> 実績 | L111: =IF(F111="",0,IF(OR(設定!$B$4="全て",K111="実績"),1,0)) -> 1 | M111: =IF(OR(G111="",H111=""),"",G111-H111-I111) | N111: =IF(M111="","",M111/G111) | O111: =IF(OR(D111="",F111=""),"",F111-D111) | P111: =IF(G111="","",IF(INT(G111/設定!$B$5)*設定!$B$5>=100000000,TEXT(INT(G111/設定!$B$5)*設定!$B$5/100000000,"0.0")&"億",TEXT(INT(G111/設定!$B$5)*設定!$B$5/10000,"#,##0")&"万")&"〜") -> 0万〜 | Q111: 149 | R111: 仕入決済日が空欄→保有日数算出不可 / 仕入原価未入力→粗利対象外
A112: 104 | B112: 一棟収益天端 | C112: 昭島市東町3丁目1棟収益 | D112: 45595 | E112: 45796 | F112: 46017 | G112: 230000000 | H112: 143000000 | I112: 70000000 | J112: =IF(F112="","",IFERROR(INDEX(設定!$A$8:$A$15,MATCH(F112,設定!$B$8:$B$15,1)),"対象外")) -> 14期 | K112: =IF(F112="","未売却",IF(F112<=設定!$B$3,"実績","予定")) -> 実績 | L112: =IF(F112="",0,IF(OR(設定!$B$4="全て",K112="実績"),1,0)) -> 1 | M112: =IF(OR(G112="",H112=""),"",G112-H112-I112) -> 17000000 | N112: =IF(M112="","",M112/G112) -> 0.073913043 | O112: =IF(OR(D112="",F112=""),"",F112-D112) -> 422 | P112: =IF(G112="","",IF(INT(G112/設定!$B$5)*設定!$B$5>=100000000,TEXT(INT(G112/設定!$B$5)*設定!$B$5/100000000,"0.0")&"億",TEXT(INT(G112/設定!$B$5)*設定!$B$5/10000,"#,##0")&"万")&"〜") -> 2.0億〜 | Q112: 108
A113: 108 | B113: 新築戸建 | C113: 大田区南久が原2丁目新築B | D113: 45583 | E113: 45920 | F113: 46017 | G113: 77900000 | H113: 37100000 | I113: 26000000 | J113: =IF(F113="","",IFERROR(INDEX(設定!$A$8:$A$15,MATCH(F113,設定!$B$8:$B$15,1)),"対象外")) -> 14期 | K113: =IF(F113="","未売却",IF(F113<=設定!$B$3,"実績","予定")) -> 実績 | L113: =IF(F113="",0,IF(OR(設定!$B$4="全て",K113="実績"),1,0)) -> 1 | M113: =IF(OR(G113="",H113=""),"",G113-H113-I113) -> 14800000 | N113: =IF(M113="","",M113/G113) -> 0.18998716 | O113: =IF(OR(D113="",F113=""),"",F113-D113) -> 434 | P113: =IF(G113="","",IF(INT(G113/設定!$B$5)*設定!$B$5>=100000000,TEXT(INT(G113/設定!$B$5)*設定!$B$5/100000000,"0.0")&"億",TEXT(INT(G113/設定!$B$5)*設定!$B$5/10000,"#,##0")&"万")&"〜") -> 5,000万〜 | Q113: 112
A114: 136 | B114: 条件なし土地 | C114: 目黒区八雲2丁目土地 | D114: 45968 | E114: 45981 | F114: 46052 | G114: 177000000 | H114: 130000000 | I114: 5600000 | J114: =IF(F114="","",IFERROR(INDEX(設定!$A$8:$A$15,MATCH(F114,設定!$B$8:$B$15,1)),"対象外")) -> 14期 | K114: =IF(F114="","未売却",IF(F114<=設定!$B$3,"実績","予定")) -> 実績 | L114: =IF(F114="",0,IF(OR(設定!$B$4="全て",K114="実績"),1,0)) -> 1 | M114: =IF(OR(G114="",H114=""),"",G114-H114-I114) -> 41400000 | N114: =IF(M114="","",M114/G114) -> 0.23389831 | O114: =IF(OR(D114="",F114=""),"",F114-D114) -> 84 | P114: =IF(G114="","",IF(INT(G114/設定!$B$5)*設定!$B$5>=100000000,TEXT(INT(G114/設定!$B$5)*設定!$B$5/100000000,"0.0")&"億",TEXT(INT(G114/設定!$B$5)*設定!$B$5/10000,"#,##0")&"万")&"〜") -> 1.5億〜 | Q114: 140
A115: 121 | B115: 新築戸建 | C115: 荒川区南千住新築戸建 | D115: 45726 | E115: 45879 | F115: 46063 | G115: 42800000 | H115: 8000000 | I115: 21715000 | J115: =IF(F115="","",IFERROR(INDEX(設定!$A$8:$A$15,MATCH(F115,設定!$B$8:$B$15,1)),"対象外")) -> 14期 | K115: =IF(F115="","未売却",IF(F115<=設定!$B$3,"実績","予定")) -> 実績 | L115: =IF(F115="",0,IF(OR(設定!$B$4="全て",K115="実績"),1,0)) -> 1 | M115: =IF(OR(G115="",H115=""),"",G115-H115-I115) -> 13085000 | N115: =IF(M115="","",M115/G115) -> 0.3057243 | O115: =IF(OR(D115="",F115=""),"",F115-D115) -> 337 | P115: =IF(G115="","",IF(INT(G115/設定!$B$5)*設定!$B$5>=100000000,TEXT(INT(G115/設定!$B$5)*設定!$B$5/100000000,"0.0")&"億",TEXT(INT(G115/設定!$B$5)*設定!$B$5/10000,"#,##0")&"万")&"〜") -> 0万〜 | Q115: 125
A116: 115 | B116: 新築戸建 | C116: 世田谷区代沢4丁目新築 | D116: 45617 | E116: 45823 | F116: 46068 | G116: 288000000 | H116: 149200000 | I116: 81500000 | J116: =IF(F116="","",IFERROR(INDEX(設定!$A$8:$A$15,MATCH(F116,設定!$B$8:$B$15,1)),"対象外")) -> 14期 | K116: =IF(F116="","未売却",IF(F116<=設定!$B$3,"実績","予定")) -> 実績 | L116: =IF(F116="",0,IF(OR(設定!$B$4="全て",K116="実績"),1,0)) -> 1 | M116: =IF(OR(G116="",H116=""),"",G116-H116-I116) -> 57300000 | N116: =IF(M116="","",M116/G116) -> 0.19895833 | O116: =IF(OR(D116="",F116=""),"",F116-D116) -> 451 | P116: =IF(G116="","",IF(INT(G116/設定!$B$5)*設定!$B$5>=100000000,TEXT(INT(G116/設定!$B$5)*設定!$B$5/100000000,"0.0")&"億",TEXT(INT(G116/設定!$B$5)*設定!$B$5/10000,"#,##0")&"万")&"〜") -> 2.5億〜 | Q116: 119
A117: 148 | B117: 条件なし土地 | C117: 練馬区桜台5丁目土地 | D117: 46073 | E117: 46019 | F117: 46073 | G117: 122000000 | H117: 105400000 | I117: 1200000 | J117: =IF(F117="","",IFERROR(INDEX(設定!$A$8:$A$15,MATCH(F117,設定!$B$8:$B$15,1)),"対象外")) -> 14期 | K117: =IF(F117="","未売却",IF(F117<=設定!$B$3,"実績","予定")) -> 実績 | L117: =IF(F117="",0,IF(OR(設定!$B$4="全て",K117="実績"),1,0)) -> 1 | M117: =IF(OR(G117="",H117=""),"",G117-H117-I117) -> 15400000 | N117: =IF(M117="","",M117/G117) -> 0.12622951 | O117: =IF(OR(D117="",F117=""),"",F117-D117) -> 0 | P117: =IF(G117="","",IF(INT(G117/設定!$B$5)*設定!$B$5>=100000000,TEXT(INT(G117/設定!$B$5)*設定!$B$5/100000000,"0.0")&"億",TEXT(INT(G117/設定!$B$5)*設定!$B$5/10000,"#,##0")&"万")&"〜") -> 1.0億〜 | Q117: 152
A118: 129 | B118: MSリフォーム再販 | C118: メゾン三鷹 | D118: 45848 | E118: 46073 | F118: 46077 | G118: 38400000 | H118: 22400000 | I118: 11000000 | J118: =IF(F118="","",IFERROR(INDEX(設定!$A$8:$A$15,MATCH(F118,設定!$B$8:$B$15,1)),"対象外")) -> 14期 | K118: =IF(F118="","未売却",IF(F118<=設定!$B$3,"実績","予定")) -> 実績 | L118: =IF(F118="",0,IF(OR(設定!$B$4="全て",K118="実績"),1,0)) -> 1 | M118: =IF(OR(G118="",H118=""),"",G118-H118-I118) -> 5000000 | N118: =IF(M118="","",M118/G118) -> 0.13020833 | O118: =IF(OR(D118="",F118=""),"",F118-D118) -> 229 | P118: =IF(G118="","",IF(INT(G118/設定!$B$5)*設定!$B$5>=100000000,TEXT(INT(G118/設定!$B$5)*設定!$B$5/100000000,"0.0")&"億",TEXT(INT(G118/設定!$B$5)*設定!$B$5/10000,"#,##0")&"万")&"〜") -> 0万〜 | Q118: 133
A119: 142 | B119: MSリフォーム再販 | C119: コーポ高幡 | D119: 45991 | E119: 46032 | F119: 46081 | G119: 27800000 | H119: 12700000 | I119: 9000000 | J119: =IF(F119="","",IFERROR(INDEX(設定!$A$8:$A$15,MATCH(F119,設定!$B$8:$B$15,1)),"対象外")) -> 14期 | K119: =IF(F119="","未売却",IF(F119<=設定!$B$3,"実績","予定")) -> 実績 | L119: =IF(F119="",0,IF(OR(設定!$B$4="全て",K119="実績"),1,0)) -> 1 | M119: =IF(OR(G119="",H119=""),"",G119-H119-I119) -> 6100000 | N119: =IF(M119="","",M119/G119) -> 0.21942446 | O119: =IF(OR(D119="",F119=""),"",F119-D119) -> 90 | P119: =IF(G119="","",IF(INT(G119/設定!$B$5)*設定!$B$5>=100000000,TEXT(INT(G119/設定!$B$5)*設定!$B$5/100000000,"0.0")&"億",TEXT(INT(G119/設定!$B$5)*設定!$B$5/10000,"#,##0")&"万")&"〜") -> 0万〜 | Q119: 146
A120: 109 | B120: 新築戸建 | C120: 大田区南久が原3丁目新築C | D120: 45575 | E120: 46052 | F120: 46096 | G120: 77900000 | H120: 36000000 | I120: 26000000 | J120: =IF(F120="","",IFERROR(INDEX(設定!$A$8:$A$15,MATCH(F120,設定!$B$8:$B$15,1)),"対象外")) -> 14期 | K120: =IF(F120="","未売却",IF(F120<=設定!$B$3,"実績","予定")) -> 実績 | L120: =IF(F120="",0,IF(OR(設定!$B$4="全て",K120="実績"),1,0)) -> 1 | M120: =IF(OR(G120="",H120=""),"",G120-H120-I120) -> 15900000 | N120: =IF(M120="","",M120/G120) -> 0.20410783 | O120: =IF(OR(D120="",F120=""),"",F120-D120) -> 521 | P120: =IF(G120="","",IF(INT(G120/設定!$B$5)*設定!$B$5>=100000000,TEXT(INT(G120/設定!$B$5)*設定!$B$5/100000000,"0.0")&"億",TEXT(INT(G120/設定!$B$5)*設定!$B$5/10000,"#,##0")&"万")&"〜") -> 5,000万〜 | Q120: 113
A121: 139 | B121: 条件なし土地 | C121: 川崎大師駅2丁目土地A | D121: 46081 | E121: 46081 | F121: 46142 | G121: 99000000 | H121: 82200000 | I121: 5900000 | J121: =IF(F121="","",IFERROR(INDEX(設定!$A$8:$A$15,MATCH(F121,設定!$B$8:$B$15,1)),"対象外")) -> 14期 | K121: =IF(F121="","未売却",IF(F121<=設定!$B$3,"実績","予定")) -> 実績 | L121: =IF(F121="",0,IF(OR(設定!$B$4="全て",K121="実績"),1,0)) -> 1 | M121: =IF(OR(G121="",H121=""),"",G121-H121-I121) -> 10900000 | N121: =IF(M121="","",M121/G121) -> 0.11010101 | O121: =IF(OR(D121="",F121=""),"",F121-D121) -> 61 | P121: =IF(G121="","",IF(INT(G121/設定!$B$5)*設定!$B$5>=100000000,TEXT(INT(G121/設定!$B$5)*設定!$B$5/100000000,"0.0")&"億",TEXT(INT(G121/設定!$B$5)*設定!$B$5/10000,"#,##0")&"万")&"〜") -> 5,000万〜 | Q121: 143
A122: 140 | B122: 条件なし土地 | C122: 川崎大師駅3丁目土地A | D122: 46081 | E122: 46081 | F122: 46142 | G122: 98000000 | H122: 75000000 | I122: 0 | J122: =IF(F122="","",IFERROR(INDEX(設定!$A$8:$A$15,MATCH(F122,設定!$B$8:$B$15,1)),"対象外")) -> 14期 | K122: =IF(F122="","未売却",IF(F122<=設定!$B$3,"実績","予定")) -> 実績 | L122: =IF(F122="",0,IF(OR(設定!$B$4="全て",K122="実績"),1,0)) -> 1 | M122: =IF(OR(G122="",H122=""),"",G122-H122-I122) -> 23000000 | N122: =IF(M122="","",M122/G122) -> 0.23469388 | O122: =IF(OR(D122="",F122=""),"",F122-D122) -> 61 | P122: =IF(G122="","",IF(INT(G122/設定!$B$5)*設定!$B$5>=100000000,TEXT(INT(G122/設定!$B$5)*設定!$B$5/100000000,"0.0")&"億",TEXT(INT(G122/設定!$B$5)*設定!$B$5/10000,"#,##0")&"万")&"〜") -> 5,000万〜 | Q122: 144
A123: 134 | B123: 条件なし土地 | C123: 大田区西馬込1丁目土地 | D123: 46006 | E123: 45989 | F123: 46237 | G123: 300000000 | H123: 238000000 | I123: 23300000 | J123: =IF(F123="","",IFERROR(INDEX(設定!$A$8:$A$15,MATCH(F123,設定!$B$8:$B$15,1)),"対象外")) -> 14期 | K123: =IF(F123="","未売却",IF(F123<=設定!$B$3,"実績","予定")) -> 実績 | L123: =IF(F123="",0,IF(OR(設定!$B$4="全て",K123="実績"),1,0)) -> 1 | M123: =IF(OR(G123="",H123=""),"",G123-H123-I123) -> 38700000 | N123: =IF(M123="","",M123/G123) -> 0.129 | O123: =IF(OR(D123="",F123=""),"",F123-D123) -> 231 | P123: =IF(G123="","",IF(INT(G123/設定!$B$5)*設定!$B$5>=100000000,TEXT(INT(G123/設定!$B$5)*設定!$B$5/100000000,"0.0")&"億",TEXT(INT(G123/設定!$B$5)*設定!$B$5/10000,"#,##0")&"万")&"〜") -> 3.0億〜 | Q123: 138
... A130: 156 | B130: 条件なし土地 | C130: 上小田中1丁目住宅用地Ｃ | D130: 46203 | E130: 46244 | F130: 46295 | G130: 76000000 | H130: 26250000 | I130: 1600000 | J130: =IF(F130="","",IFERROR(INDEX(設定!$A$8:$A$15,MATCH(F130,設定!$B$8:$B$15,1)),"対象外")) -> 14期 | K130: =IF(F130="","未売却",IF(F130<=設定!$B$3,"実績","予定")) -> 予定 | L130: =IF(F130="",0,IF(OR(設定!$B$4="全て",K130="実績"),1,0)) -> 1 | M130: =IF(OR(G130="",H130=""),"",G130-H130-I130) -> 48150000 | N130: =IF(M130="","",M130/G130) -> 0.63355263 | O130: =IF(OR(D130="",F130=""),"",F130-D130) -> 92 | P130: =IF(G130="","",IF(INT(G130/設定!$B$5)*設定!$B$5>=100000000,TEXT(INT(G130/設定!$B$5)*設定!$B$5/100000000,"0.0")&"億",TEXT(INT(G130/設定!$B$5)*設定!$B$5/10000,"#,##0")&"万")&"〜") -> 5,000万〜 | Q130: 160
A131: 157 | B131: 条件なし土地 | C131: 上小田中1丁目住宅用地Ｄ | D131: 46203 | E131: 46244 | F131: 46295 | H131: 26250000 | I131: 1600000 | J131: =IF(F131="","",IFERROR(INDEX(設定!$A$8:$A$15,MATCH(F131,設定!$B$8:$B$15,1)),"対象外")) -> 14期 | K131: =IF(F131="","未売却",IF(F131<=設定!$B$3,"実績","予定")) -> 予定 | L131: =IF(F131="",0,IF(OR(設定!$B$4="全て",K131="実績"),1,0)) -> 1 | M131: =IF(OR(G131="",H131=""),"",G131-H131-I131) | N131: =IF(M131="","",M131/G131) | O131: =IF(OR(D131="",F131=""),"",F131-D131) -> 92 | P131: =IF(G131="","",IF(INT(G131/設定!$B$5)*設定!$B$5>=100000000,TEXT(INT(G131/設定!$B$5)*設定!$B$5/100000000,"0.0")&"億",TEXT(INT(G131/設定!$B$5)*設定!$B$5/10000,"#,##0")&"万")&"〜") | Q131: 161 | R131: 売却決済日ありだが販売価格が空欄
...

Sheet ①期別×種別
A1: ① 期ごとの物件種別（売却決済ベース 棟数）
A2: =" 集計対象："&設定!B4&"／基準日："&TEXT(設定!B3,"yyyy/mm/dd") -> 集計対象：全て／基準日：2026/09/29
A4: 物件種別 | B4: 10期 | C4: 11期 | D4: 12期 | E4: 13期 | F4: 14期 | G4: 15期 | H4: 合計
A5: 新築戸建 | B5: =COUNTIFS(物件データ!$B$5:$B$180,$A5,物件データ!$J$5:$J$180,B$4,物件データ!$L$5:$L$180,1) -> 17 | C5: =COUNTIFS(物件データ!$B$5:$B$180,$A5,物件データ!$J$5:$J$180,C$4,物件データ!$L$5:$L$180,1) -> 17 | D5: =COUNTIFS(物件データ!$B$5:$B$180,$A5,物件データ!$J$5:$J$180,D$4,物件データ!$L$5:$L$180,1) -> 4 | E5: =COUNTIFS(物件データ!$B$5:$B$180,$A5,物件データ!$J$5:$J$180,E$4,物件データ!$L$5:$L$180,1) -> 13 | F5: =COUNTIFS(物件データ!$B$5:$B$180,$A5,物件データ!$J$5:$J$180,F$4,物件データ!$L$5:$L$180,1) -> 7 | G5: =COUNTIFS(物件データ!$B$5:$B$180,$A5,物件データ!$J$5:$J$180,G$4,物件データ!$L$5:$L$180,1) -> 3 | H5: =SUM(B5:G5) -> 61
A6: 条件なし土地 | B6: =COUNTIFS(物件データ!$B$5:$B$180,$A6,物件データ!$J$5:$J$180,B$4,物件データ!$L$5:$L$180,1) -> 2 | C6: =COUNTIFS(物件データ!$B$5:$B$180,$A6,物件データ!$J$5:$J$180,C$4,物件データ!$L$5:$L$180,1) -> 3 | D6: =COUNTIFS(物件データ!$B$5:$B$180,$A6,物件データ!$J$5:$J$180,D$4,物件データ!$L$5:$L$180,1) -> 0 | E6: =COUNTIFS(物件データ!$B$5:$B$180,$A6,物件データ!$J$5:$J$180,E$4,物件データ!$L$5:$L$180,1) -> 4 | F6: =COUNTIFS(物件データ!$B$5:$B$180,$A6,物件データ!$J$5:$J$180,F$4,物件データ!$L$5:$L$180,1) -> 10 | G6: =COUNTIFS(物件データ!$B$5:$B$180,$A6,物件データ!$J$5:$J$180,G$4,物件データ!$L$5:$L$180,1) -> 2 | H6: =SUM(B6:G6) -> 21
A7: MSリフォーム再販 | B7: =COUNTIFS(物件データ!$B$5:$B$180,$A7,物件データ!$J$5:$J$180,B$4,物件データ!$L$5:$L$180,1) -> 5 | C7: =COUNTIFS(物件データ!$B$5:$B$180,$A7,物件データ!$J$5:$J$180,C$4,物件データ!$L$5:$L$180,1) -> 5 | D7: =COUNTIFS(物件データ!$B$5:$B$180,$A7,物件データ!$J$5:$J$180,D$4,物件データ!$L$5:$L$180,1) -> 0 | E7: =COUNTIFS(物件データ!$B$5:$B$180,$A7,物件データ!$J$5:$J$180,E$4,物件データ!$L$5:$L$180,1) -> 4 | F7: =COUNTIFS(物件データ!$B$5:$B$180,$A7,物件データ!$J$5:$J$180,F$4,物件データ!$L$5:$L$180,1) -> 5 | G7: =COUNTIFS(物件データ!$B$5:$B$180,$A7,物件データ!$J$5:$J$180,G$4,物件データ!$L$5:$L$180,1) -> 1 | H7: =SUM(B7:G7) -> 20
A8: 戸建リフォーム再販 | B8: =COUNTIFS(物件データ!$B$5:$B$180,$A8,物件データ!$J$5:$J$180,B$4,物件データ!$L$5:$L$180,1) -> 4 | C8: =COUNTIFS(物件データ!$B$5:$B$180,$A8,物件データ!$J$5:$J$180,C$4,物件データ!$L$5:$L$180,1) -> 3 | D8: =COUNTIFS(物件データ!$B$5:$B$180,$A8,物件データ!$J$5:$J$180,D$4,物件データ!$L$5:$L$180,1) -> 1 | E8: =COUNTIFS(物件データ!$B$5:$B$180,$A8,物件データ!$J$5:$J$180,E$4,物件データ!$L$5:$L$180,1) -> 3 | F8: =COUNTIFS(物件データ!$B$5:$B$180,$A8,物件データ!$J$5:$J$180,F$4,物件データ!$L$5:$L$180,1) -> 3 | G8: =COUNTIFS(物件データ!$B$5:$B$180,$A8,物件データ!$J$5:$J$180,G$4,物件データ!$L$5:$L$180,1) -> 0 | H8: =SUM(B8:G8) -> 14
A9: 条件付き土地 | B9: =COUNTIFS(物件データ!$B$5:$B$180,$A9,物件データ!$J$5:$J$180,B$4,物件データ!$L$5:$L$180,1) -> 2 | C9: =COUNTIFS(物件データ!$B$5:$B$180,$A9,物件データ!$J$5:$J$180,C$4,物件データ!$L$5:$L$180,1) -> 1 | D9: =COUNTIFS(物件データ!$B$5:$B$180,$A9,物件データ!$J$5:$J$180,D$4,物件データ!$L$5:$L$180,1) -> 0 | E9: =COUNTIFS(物件データ!$B$5:$B$180,$A9,物件データ!$J$5:$J$180,E$4,物件データ!$L$5:$L$180,1) -> 3 | F9: =COUNTIFS(物件データ!$B$5:$B$180,$A9,物件データ!$J$5:$J$180,F$4,物件データ!$L$5:$L$180,1) -> 0 | G9: =COUNTIFS(物件データ!$B$5:$B$180,$A9,物件データ!$J$5:$J$180,G$4,物件データ!$L$5:$L$180,1) -> 0 | H9: =SUM(B9:G9) -> 6
A10: 立ち退き後転売土地 | B10: =COUNTIFS(物件データ!$B$5:$B$180,$A10,物件データ!$J$5:$J$180,B$4,物件データ!$L$5:$L$180,1) -> 0 | C10: =COUNTIFS(物件データ!$B$5:$B$180,$A10,物件データ!$J$5:$J$180,C$4,物件データ!$L$5:$L$180,1) -> 0 | D10: =COUNTIFS(物件データ!$B$5:$B$180,$A10,物件データ!$J$5:$J$180,D$4,物件データ!$L$5:$L$180,1) -> 1 | E10: =COUNTIFS(物件データ!$B$5:$B$180,$A10,物件データ!$J$5:$J$180,E$4,物件データ!$L$5:$L$180,1) -> 3 | F10: =COUNTIFS(物件データ!$B$5:$B$180,$A10,物件データ!$J$5:$J$180,F$4,物件データ!$L$5:$L$180,1) -> 1 | G10: =COUNTIFS(物件データ!$B$5:$B$180,$A10,物件データ!$J$5:$J$180,G$4,物件データ!$L$5:$L$180,1) -> 0 | H10: =SUM(B10:G10) -> 5
A11: 一棟収益天端 | B11: =COUNTIFS(物件データ!$B$5:$B$180,$A11,物件データ!$J$5:$J$180,B$4,物件データ!$L$5:$L$180,1) -> 0 | C11: =COUNTIFS(物件データ!$B$5:$B$180,$A11,物件データ!$J$5:$J$180,C$4,物件データ!$L$5:$L$180,1) -> 2 | D11: =COUNTIFS(物件データ!$B$5:$B$180,$A11,物件データ!$J$5:$J$180,D$4,物件データ!$L$5:$L$180,1) -> 0 | E11: =COUNTIFS(物件データ!$B$5:$B$180,$A11,物件データ!$J$5:$J$180,E$4,物件データ!$L$5:$L$180,1) -> 1 | F11: =COUNTIFS(物件データ!$B$5:$B$180,$A11,物件データ!$J$5:$J$180,F$4,物件データ!$L$5:$L$180,1) -> 1 | G11: =COUNTIFS(物件データ!$B$5:$B$180,$A11,物件データ!$J$5:$J$180,G$4,物件データ!$L$5:$L$180,1) -> 0 | H11: =SUM(B11:G11) -> 4
A12: OC転売 | B12: =COUNTIFS(物件データ!$B$5:$B$180,$A12,物件データ!$J$5:$J$180,B$4,物件データ!$L$5:$L$180,1) -> 0 | C12: =COUNTIFS(物件データ!$B$5:$B$180,$A12,物件データ!$J$5:$J$180,C$4,物件データ!$L$5:$L$180,1) -> 1 | D12: =COUNTIFS(物件データ!$B$5:$B$180,$A12,物件データ!$J$5:$J$180,D$4,物件データ!$L$5:$L$180,1) -> 0 | E12: =COUNTIFS(物件データ!$B$5:$B$180,$A12,物件データ!$J$5:$J$180,E$4,物件データ!$L$5:$L$180,1) -> 1 | F12: =COUNTIFS(物件データ!$B$5:$B$180,$A12,物件データ!$J$5:$J$180,F$4,物件データ!$L$5:$L$180,1) -> 0 | G12: =COUNTIFS(物件データ!$B$5:$B$180,$A12,物件データ!$J$5:$J$180,G$4,物件データ!$L$5:$L$180,1) -> 0 | H12: =SUM(B12:G12) -> 2
A13: JT | B13: =COUNTIFS(物件データ!$B$5:$B$180,$A13,物件データ!$J$5:$J$180,B$4,物件データ!$L$5:$L$180,1) -> 0 | C13: =COUNTIFS(物件データ!$B$5:$B$180,$A13,物件データ!$J$5:$J$180,C$4,物件データ!$L$5:$L$180,1) -> 0 | D13: =COUNTIFS(物件データ!$B$5:$B$180,$A13,物件データ!$J$5:$J$180,D$4,物件データ!$L$5:$L$180,1) -> 0 | E13: =COUNTIFS(物件データ!$B$5:$B$180,$A13,物件データ!$J$5:$J$180,E$4,物件データ!$L$5:$L$180,1) -> 1 | F13: =COUNTIFS(物件データ!$B$5:$B$180,$A13,物件データ!$J$5:$J$180,F$4,物件データ!$L$5:$L$180,1) -> 0 | G13: =COUNTIFS(物件データ!$B$5:$B$180,$A13,物件データ!$J$5:$J$180,G$4,物件データ!$L$5:$L$180,1) -> 0 | H13: =SUM(B13:G13) -> 1
A14: たちのき後転売MS | B14: =COUNTIFS(物件データ!$B$5:$B$180,$A14,物件データ!$J$5:$J$180,B$4,物件データ!$L$5:$L$180,1) -> 0 | C14: =COUNTIFS(物件データ!$B$5:$B$180,$A14,物件データ!$J$5:$J$180,C$4,物件データ!$L$5:$L$180,1) -> 0 | D14: =COUNTIFS(物件データ!$B$5:$B$180,$A14,物件データ!$J$5:$J$180,D$4,物件データ!$L$5:$L$180,1) -> 0 | E14: =COUNTIFS(物件データ!$B$5:$B$180,$A14,物件データ!$J$5:$J$180,E$4,物件データ!$L$5:$L$180,1) -> 0 | F14: =COUNTIFS(物件データ!$B$5:$B$180,$A14,物件データ!$J$5:$J$180,F$4,物件データ!$L$5:$L$180,1) -> 1 | G14: =COUNTIFS(物件データ!$B$5:$B$180,$A14,物件データ!$J$5:$J$180,G$4,物件データ!$L$5:$L$180,1) -> 0 | H14: =SUM(B14:G14) -> 1
A15: 合計 | B15: =SUM(B5:B14) -> 30 | C15: =SUM(C5:C14) -> 32 | D15: =SUM(D5:D14) -> 6 | E15: =SUM(E5:E14) -> 33 | F15: =SUM(F5:F14) -> 28 | G15: =SUM(G5:G14) -> 6 | H15: =SUM(H5:H14) -> 135
A17: 種別構成比（棟数）
A18: 物件種別 | B18: 10期 | C18: 11期 | D18: 12期 | E18: 13期 | F18: 14期 | G18: 15期 | H18: 合計
A19: 新築戸建 | B19: =IF(B$15=0,"",B5/B$15) -> 0.56666667 | C19: =IF(C$15=0,"",C5/C$15) -> 0.53125 | D19: =IF(D$15=0,"",D5/D$15) -> 0.66666667 | E19: =IF(E$15=0,"",E5/E$15) -> 0.39393939 | F19: =IF(F$15=0,"",F5/F$15) -> 0.25 | G19: =IF(G$15=0,"",G5/G$15) -> 0.5 | H19: =IF(H$15=0,"",H5/H$15) -> 0.45185185
A20: 条件なし土地 | B20: =IF(B$15=0,"",B6/B$15) -> 0.066666667 | C20: =IF(C$15=0,"",C6/C$15) -> 0.09375 | D20: =IF(D$15=0,"",D6/D$15) -> 0 | E20: =IF(E$15=0,"",E6/E$15) -> 0.12121212 | F20: =IF(F$15=0,"",F6/F$15) -> 0.35714286 | G20: =IF(G$15=0,"",G6/G$15) -> 0.33333333 | H20: =IF(H$15=0,"",H6/H$15) -> 0.15555556
A21: MSリフォーム再販 | B21: =IF(B$15=0,"",B7/B$15) -> 0.16666667 | C21: =IF(C$15=0,"",C7/C$15) -> 0.15625 | D21: =IF(D$15=0,"",D7/D$15) -> 0 | E21: =IF(E$15=0,"",E7/E$15) -> 0.12121212 | F21: =IF(F$15=0,"",F7/F$15) -> 0.17857143 | G21: =IF(G$15=0,"",G7/G$15) -> 0.16666667 | H21: =IF(H$15=0,"",H7/H$15) -> 0.14814815
A22: 戸建リフォーム再販 | B22: =IF(B$15=0,"",B8/B$15) -> 0.13333333 | C22: =IF(C$15=0,"",C8/C$15) -> 0.09375 | D22: =IF(D$15=0,"",D8/D$15) -> 0.16666667 | E22: =IF(E$15=0,"",E8/E$15) -> 0.090909091 | F22: =IF(F$15=0,"",F8/F$15) -> 0.10714286 | G22: =IF(G$15=0,"",G8/G$15) -> 0 | H22: =IF(H$15=0,"",H8/H$15) -> 0.1037037
A23: 条件付き土地 | B23: =IF(B$15=0,"",B9/B$15) -> 0.066666667 | C23: =IF(C$15=0,"",C9/C$15) -> 0.03125 | D23: =IF(D$15=0,"",D9/D$15) -> 0 | E23: =IF(E$15=0,"",E9/E$15) -> 0.090909091 | F23: =IF(F$15=0,"",F9/F$15) -> 0 | G23: =IF(G$15=0,"",G9/G$15) -> 0 | H23: =IF(H$15=0,"",H9/H$15) -> 0.044444444
A24: 立ち退き後転売土地 | B24: =IF(B$15=0,"",B10/B$15) -> 0 | C24: =IF(C$15=0,"",C10/C$15) -> 0 | D24: =IF(D$15=0,"",D10/D$15) -> 0.16666667 | E24: =IF(E$15=0,"",E10/E$15) -> 0.090909091 | F24: =IF(F$15=0,"",F10/F$15) -> 0.035714286 | G24: =IF(G$15=0,"",G10/G$15) -> 0 | H24: =IF(H$15=0,"",H10/H$15) -> 0.037037037
A25: 一棟収益天端 | B25: =IF(B$15=0,"",B11/B$15) -> 0 | C25: =IF(C$15=0,"",C11/C$15) -> 0.0625 | D25: =IF(D$15=0,"",D11/D$15) -> 0 | E25: =IF(E$15=0,"",E11/E$15) -> 0.03030303 | F25: =IF(F$15=0,"",F11/F$15) -> 0.035714286 | G25: =IF(G$15=0,"",G11/G$15) -> 0 | H25: =IF(H$15=0,"",H11/H$15) -> 0.02962963
A26: OC転売 | B26: =IF(B$15=0,"",B12/B$15) -> 0 | C26: =IF(C$15=0,"",C12/C$15) -> 0.03125 | D26: =IF(D$15=0,"",D12/D$15) -> 0 | E26: =IF(E$15=0,"",E12/E$15) -> 0.03030303 | F26: =IF(F$15=0,"",F12/F$15) -> 0 | G26: =IF(G$15=0,"",G12/G$15) -> 0 | H26: =IF(H$15=0,"",H12/H$15) -> 0.014814815
A27: JT | B27: =IF(B$15=0,"",B13/B$15) -> 0 | C27: =IF(C$15=0,"",C13/C$15) -> 0 | D27: =IF(D$15=0,"",D13/D$15) -> 0 | E27: =IF(E$15=0,"",E13/E$15) -> 0.03030303 | F27: =IF(F$15=0,"",F13/F$15) -> 0 | G27: =IF(G$15=0,"",G13/G$15) -> 0 | H27: =IF(H$15=0,"",H13/H$15) -> 0.0074074074
A28: たちのき後転売MS | B28: =IF(B$15=0,"",B14/B$15) -> 0 | C28: =IF(C$15=0,"",C14/C$15) -> 0 | D28: =IF(D$15=0,"",D14/D$15) -> 0 | E28: =IF(E$15=0,"",E14/E$15) -> 0 | F28: =IF(F$15=0,"",F14/F$15) -> 0.035714286 | G28: =IF(G$15=0,"",G14/G$15) -> 0 | H28: =IF(H$15=0,"",H14/H$15) -> 0.0074074074

Sheet ②種別別KPI
A1: ② 種別ごと・期ごとの売上高／粗利／保有日数／棟数
A2: =" 集計対象："&設定!B4&"／粗利・粗利率は仕入原価入力済の物件のみ" -> 集計対象：全て／粗利・粗利率は仕入原価入力済の物件のみ
A4: 棟数
A5: 物件種別 | B5: 10期 | C5: 11期 | D5: 12期 | E5: 13期 | F5: 14期 | G5: 15期 | H5: 合計
A6: 新築戸建 | B6: =COUNTIFS(物件データ!$L$5:$L$180,1,物件データ!$B$5:$B$180,$A6,物件データ!$J$5:$J$180,B$5) -> 17 | C6: =COUNTIFS(物件データ!$L$5:$L$180,1,物件データ!$B$5:$B$180,$A6,物件データ!$J$5:$J$180,C$5) -> 17 | D6: =COUNTIFS(物件データ!$L$5:$L$180,1,物件データ!$B$5:$B$180,$A6,物件データ!$J$5:$J$180,D$5) -> 4 | E6: =COUNTIFS(物件データ!$L$5:$L$180,1,物件データ!$B$5:$B$180,$A6,物件データ!$J$5:$J$180,E$5) -> 13 | F6: =COUNTIFS(物件データ!$L$5:$L$180,1,物件データ!$B$5:$B$180,$A6,物件データ!$J$5:$J$180,F$5) -> 7 | G6: =COUNTIFS(物件データ!$L$5:$L$180,1,物件データ!$B$5:$B$180,$A6,物件データ!$J$5:$J$180,G$5) -> 3 | H6: =COUNTIFS(物件データ!$L$5:$L$180,1,物件データ!$B$5:$B$180,$A6,物件データ!$J$5:$J$180,"?*") -> 61
A7: 条件なし土地 | B7: =COUNTIFS(物件データ!$L$5:$L$180,1,物件データ!$B$5:$B$180,$A7,物件データ!$J$5:$J$180,B$5) -> 2 | C7: =COUNTIFS(物件データ!$L$5:$L$180,1,物件データ!$B$5:$B$180,$A7,物件データ!$J$5:$J$180,C$5) -> 3 | D7: =COUNTIFS(物件データ!$L$5:$L$180,1,物件データ!$B$5:$B$180,$A7,物件データ!$J$5:$J$180,D$5) -> 0 | E7: =COUNTIFS(物件データ!$L$5:$L$180,1,物件データ!$B$5:$B$180,$A7,物件データ!$J$5:$J$180,E$5) -> 4 | F7: =COUNTIFS(物件データ!$L$5:$L$180,1,物件データ!$B$5:$B$180,$A7,物件データ!$J$5:$J$180,F$5) -> 10 | G7: =COUNTIFS(物件データ!$L$5:$L$180,1,物件データ!$B$5:$B$180,$A7,物件データ!$J$5:$J$180,G$5) -> 2 | H7: =COUNTIFS(物件データ!$L$5:$L$180,1,物件データ!$B$5:$B$180,$A7,物件データ!$J$5:$J$180,"?*") -> 21
A8: MSリフォーム再販 | B8: =COUNTIFS(物件データ!$L$5:$L$180,1,物件データ!$B$5:$B$180,$A8,物件データ!$J$5:$J$180,B$5) -> 5 | C8: =COUNTIFS(物件データ!$L$5:$L$180,1,物件データ!$B$5:$B$180,$A8,物件データ!$J$5:$J$180,C$5) -> 5 | D8: =COUNTIFS(物件データ!$L$5:$L$180,1,物件データ!$B$5:$B$180,$A8,物件データ!$J$5:$J$180,D$5) -> 0 | E8: =COUNTIFS(物件データ!$L$5:$L$180,1,物件データ!$B$5:$B$180,$A8,物件データ!$J$5:$J$180,E$5) -> 4 | F8: =COUNTIFS(物件データ!$L$5:$L$180,1,物件データ!$B$5:$B$180,$A8,物件データ!$J$5:$J$180,F$5) -> 5 | G8: =COUNTIFS(物件データ!$L$5:$L$180,1,物件データ!$B$5:$B$180,$A8,物件データ!$J$5:$J$180,G$5) -> 1 | H8: =COUNTIFS(物件データ!$L$5:$L$180,1,物件データ!$B$5:$B$180,$A8,物件データ!$J$5:$J$180,"?*") -> 20
A9: 戸建リフォーム再販 | B9: =COUNTIFS(物件データ!$L$5:$L$180,1,物件データ!$B$5:$B$180,$A9,物件データ!$J$5:$J$180,B$5) -> 4 | C9: =COUNTIFS(物件データ!$L$5:$L$180,1,物件データ!$B$5:$B$180,$A9,物件データ!$J$5:$J$180,C$5) -> 3 | D9: =COUNTIFS(物件データ!$L$5:$L$180,1,物件データ!$B$5:$B$180,$A9,物件データ!$J$5:$J$180,D$5) -> 1 | E9: =COUNTIFS(物件データ!$L$5:$L$180,1,物件データ!$B$5:$B$180,$A9,物件データ!$J$5:$J$180,E$5) -> 3 | F9: =COUNTIFS(物件データ!$L$5:$L$180,1,物件データ!$B$5:$B$180,$A9,物件データ!$J$5:$J$180,F$5) -> 3 | G9: =COUNTIFS(物件データ!$L$5:$L$180,1,物件データ!$B$5:$B$180,$A9,物件データ!$J$5:$J$180,G$5) -> 0 | H9: =COUNTIFS(物件データ!$L$5:$L$180,1,物件データ!$B$5:$B$180,$A9,物件データ!$J$5:$J$180,"?*") -> 14
A10: 条件付き土地 | B10: =COUNTIFS(物件データ!$L$5:$L$180,1,物件データ!$B$5:$B$180,$A10,物件データ!$J$5:$J$180,B$5) -> 2 | C10: =COUNTIFS(物件データ!$L$5:$L$180,1,物件データ!$B$5:$B$180,$A10,物件データ!$J$5:$J$180,C$5) -> 1 | D10: =COUNTIFS(物件データ!$L$5:$L$180,1,物件データ!$B$5:$B$180,$A10,物件データ!$J$5:$J$180,D$5) -> 0 | E10: =COUNTIFS(物件データ!$L$5:$L$180,1,物件データ!$B$5:$B$180,$A10,物件データ!$J$5:$J$180,E$5) -> 3 | F10: =COUNTIFS(物件データ!$L$5:$L$180,1,物件データ!$B$5:$B$180,$A10,物件データ!$J$5:$J$180,F$5) -> 0 | G10: =COUNTIFS(物件データ!$L$5:$L$180,1,物件データ!$B$5:$B$180,$A10,物件データ!$J$5:$J$180,G$5) -> 0 | H10: =COUNTIFS(物件データ!$L$5:$L$180,1,物件データ!$B$5:$B$180,$A10,物件データ!$J$5:$J$180,"?*") -> 6
A11: 立ち退き後転売土地 | B11: =COUNTIFS(物件データ!$L$5:$L$180,1,物件データ!$B$5:$B$180,$A11,物件データ!$J$5:$J$180,B$5) -> 0 | C11: =COUNTIFS(物件データ!$L$5:$L$180,1,物件データ!$B$5:$B$180,$A11,物件データ!$J$5:$J$180,C$5) -> 0 | D11: =COUNTIFS(物件データ!$L$5:$L$180,1,物件データ!$B$5:$B$180,$A11,物件データ!$J$5:$J$180,D$5) -> 1 | E11: =COUNTIFS(物件データ!$L$5:$L$180,1,物件データ!$B$5:$B$180,$A11,物件データ!$J$5:$J$180,E$5) -> 3 | F11: =COUNTIFS(物件データ!$L$5:$L$180,1,物件データ!$B$5:$B$180,$A11,物件データ!$J$5:$J$180,F$5) -> 1 | G11: =COUNTIFS(物件データ!$L$5:$L$180,1,物件データ!$B$5:$B$180,$A11,物件データ!$J$5:$J$180,G$5) -> 0 | H11: =COUNTIFS(物件データ!$L$5:$L$180,1,物件データ!$B$5:$B$180,$A11,物件データ!$J$5:$J$180,"?*") -> 5
A12: 一棟収益天端 | B12: =COUNTIFS(物件データ!$L$5:$L$180,1,物件データ!$B$5:$B$180,$A12,物件データ!$J$5:$J$180,B$5) -> 0 | C12: =COUNTIFS(物件データ!$L$5:$L$180,1,物件データ!$B$5:$B$180,$A12,物件データ!$J$5:$J$180,C$5) -> 2 | D12: =COUNTIFS(物件データ!$L$5:$L$180,1,物件データ!$B$5:$B$180,$A12,物件データ!$J$5:$J$180,D$5) -> 0 | E12: =COUNTIFS(物件データ!$L$5:$L$180,1,物件データ!$B$5:$B$180,$A12,物件データ!$J$5:$J$180,E$5) -> 1 | F12: =COUNTIFS(物件データ!$L$5:$L$180,1,物件データ!$B$5:$B$180,$A12,物件データ!$J$5:$J$180,F$5) -> 1 | G12: =COUNTIFS(物件データ!$L$5:$L$180,1,物件データ!$B$5:$B$180,$A12,物件データ!$J$5:$J$180,G$5) -> 0 | H12: =COUNTIFS(物件データ!$L$5:$L$180,1,物件データ!$B$5:$B$180,$A12,物件データ!$J$5:$J$180,"?*") -> 4
A13: OC転売 | B13: =COUNTIFS(物件データ!$L$5:$L$180,1,物件データ!$B$5:$B$180,$A13,物件データ!$J$5:$J$180,B$5) -> 0 | C13: =COUNTIFS(物件データ!$L$5:$L$180,1,物件データ!$B$5:$B$180,$A13,物件データ!$J$5:$J$180,C$5) -> 1 | D13: =COUNTIFS(物件データ!$L$5:$L$180,1,物件データ!$B$5:$B$180,$A13,物件データ!$J$5:$J$180,D$5) -> 0 | E13: =COUNTIFS(物件データ!$L$5:$L$180,1,物件データ!$B$5:$B$180,$A13,物件データ!$J$5:$J$180,E$5) -> 1 | F13: =COUNTIFS(物件データ!$L$5:$L$180,1,物件データ!$B$5:$B$180,$A13,物件データ!$J$5:$J$180,F$5) -> 0 | G13: =COUNTIFS(物件データ!$L$5:$L$180,1,物件データ!$B$5:$B$180,$A13,物件データ!$J$5:$J$180,G$5) -> 0 | H13: =COUNTIFS(物件データ!$L$5:$L$180,1,物件データ!$B$5:$B$180,$A13,物件データ!$J$5:$J$180,"?*") -> 2
A14: JT | B14: =COUNTIFS(物件データ!$L$5:$L$180,1,物件データ!$B$5:$B$180,$A14,物件データ!$J$5:$J$180,B$5) -> 0 | C14: =COUNTIFS(物件データ!$L$5:$L$180,1,物件データ!$B$5:$B$180,$A14,物件データ!$J$5:$J$180,C$5) -> 0 | D14: =COUNTIFS(物件データ!$L$5:$L$180,1,物件データ!$B$5:$B$180,$A14,物件データ!$J$5:$J$180,D$5) -> 0 | E14: =COUNTIFS(物件データ!$L$5:$L$180,1,物件データ!$B$5:$B$180,$A14,物件データ!$J$5:$J$180,E$5) -> 1 | F14: =COUNTIFS(物件データ!$L$5:$L$180,1,物件データ!$B$5:$B$180,$A14,物件データ!$J$5:$J$180,F$5) -> 0 | G14: =COUNTIFS(物件データ!$L$5:$L$180,1,物件データ!$B$5:$B$180,$A14,物件データ!$J$5:$J$180,G$5) -> 0 | H14: =COUNTIFS(物件データ!$L$5:$L$180,1,物件データ!$B$5:$B$180,$A14,物件データ!$J$5:$J$180,"?*") -> 1
A15: たちのき後転売MS | B15: =COUNTIFS(物件データ!$L$5:$L$180,1,物件データ!$B$5:$B$180,$A15,物件データ!$J$5:$J$180,B$5) -> 0 | C15: =COUNTIFS(物件データ!$L$5:$L$180,1,物件データ!$B$5:$B$180,$A15,物件データ!$J$5:$J$180,C$5) -> 0 | D15: =COUNTIFS(物件データ!$L$5:$L$180,1,物件データ!$B$5:$B$180,$A15,物件データ!$J$5:$J$180,D$5) -> 0 | E15: =COUNTIFS(物件データ!$L$5:$L$180,1,物件データ!$B$5:$B$180,$A15,物件データ!$J$5:$J$180,E$5) -> 0 | F15: =COUNTIFS(物件データ!$L$5:$L$180,1,物件データ!$B$5:$B$180,$A15,物件データ!$J$5:$J$180,F$5) -> 1 | G15: =COUNTIFS(物件データ!$L$5:$L$180,1,物件データ!$B$5:$B$180,$A15,物件データ!$J$5:$J$180,G$5) -> 0 | H15: =COUNTIFS(物件データ!$L$5:$L$180,1,物件データ!$B$5:$B$180,$A15,物件データ!$J$5:$J$180,"?*") -> 1
A16: 合計 | B16: =SUM(B6:B15) -> 30 | C16: =SUM(C6:C15) -> 32 | D16: =SUM(D6:D15) -> 6 | E16: =SUM(E6:E15) -> 33 | F16: =SUM(F6:F15) -> 28 | G16: =SUM(G6:G15) -> 6 | H16: =SUM(H6:H15) -> 135
A18: 売上高（円）
A19: 物件種別 | B19: 10期 | C19: 11期 | D19: 12期 | E19: 13期 | F19: 14期 | G19: 15期 | H19: 合計
A20: 新築戸建 | B20: =SUMIFS(物件データ!$G$5:$G$180,物件データ!$L$5:$L$180,1,物件データ!$B$5:$B$180,$A20,物件データ!$J$5:$J$180,B$19) -> 958000000 | C20: =SUMIFS(物件データ!$G$5:$G$180,物件データ!$L$5:$L$180,1,物件データ!$B$5:$B$180,$A20,物件データ!$J$5:$J$180,C$19) -> 1268600000 | D20: =SUMIFS(物件データ!$G$5:$G$180,物件データ!$L$5:$L$180,1,物件データ!$B$5:$B$180,$A20,物件データ!$J$5:$J$180,D$19) -> 248500000 | E20: =SUMIFS(物件データ!$G$5:$G$180,物件データ!$L$5:$L$180,1,物件データ!$B$5:$B$180,$A20,物件データ!$J$5:$J$180,E$19) -> 714500000 | F20: =SUMIFS(物件データ!$G$5:$G$180,物件データ!$L$5:$L$180,1,物件データ!$B$5:$B$180,$A20,物件データ!$J$5:$J$180,F$19) -> 793500000 | G20: =SUMIFS(物件データ!$G$5:$G$180,物件データ!$L$5:$L$180,1,物件データ!$B$5:$B$180,$A20,物件データ!$J$5:$J$180,G$19) -> 150300000 | H20: =SUMIFS(物件データ!$G$5:$G$180,物件データ!$L$5:$L$180,1,物件データ!$B$5:$B$180,$A20,物件データ!$J$5:$J$180,"?*") -> 4133400000
A21: 条件なし土地 | B21: =SUMIFS(物件データ!$G$5:$G$180,物件データ!$L$5:$L$180,1,物件データ!$B$5:$B$180,$A21,物件データ!$J$5:$J$180,B$19) -> 219000000 | C21: =SUMIFS(物件データ!$G$5:$G$180,物件データ!$L$5:$L$180,1,物件データ!$B$5:$B$180,$A21,物件データ!$J$5:$J$180,C$19) -> 529400000 | D21: =SUMIFS(物件データ!$G$5:$G$180,物件データ!$L$5:$L$180,1,物件データ!$B$5:$B$180,$A21,物件データ!$J$5:$J$180,D$19) -> 0 | E21: =SUMIFS(物件データ!$G$5:$G$180,物件データ!$L$5:$L$180,1,物件データ!$B$5:$B$180,$A21,物件データ!$J$5:$J$180,E$19) -> 260800000 | F21: =SUMIFS(物件データ!$G$5:$G$180,物件データ!$L$5:$L$180,1,物件データ!$B$5:$B$180,$A21,物件データ!$J$5:$J$180,F$19) -> 1212000000 | G21: =SUMIFS(物件データ!$G$5:$G$180,物件データ!$L$5:$L$180,1,物件データ!$B$5:$B$180,$A21,物件データ!$J$5:$J$180,G$19) -> 249800000 | H21: =SUMIFS(物件データ!$G$5:$G$180,物件データ!$L$5:$L$180,1,物件データ!$B$5:$B$180,$A21,物件データ!$J$5:$J$180,"?*") -> 2471000000
A22: MSリフォーム再販 | B22: =SUMIFS(物件データ!$G$5:$G$180,物件データ!$L$5:$L$180,1,物件データ!$B$5:$B$180,$A22,物件データ!$J$5:$J$180,B$19) -> 281600000 | C22: =SUMIFS(物件データ!$G$5:$G$180,物件データ!$L$5:$L$180,1,物件データ!$B$5:$B$180,$A22,物件データ!$J$5:$J$180,C$19) -> 196850000 | D22: =SUMIFS(物件データ!$G$5:$G$180,物件データ!$L$5:$L$180,1,物件データ!$B$5:$B$180,$A22,物件データ!$J$5:$J$180,D$19) -> 0 | E22: =SUMIFS(物件データ!$G$5:$G$180,物件データ!$L$5:$L$180,1,物件データ!$B$5:$B$180,$A22,物件データ!$J$5:$J$180,E$19) -> 142800000 | F22: =SUMIFS(物件データ!$G$5:$G$180,物件データ!$L$5:$L$180,1,物件データ!$B$5:$B$180,$A22,物件データ!$J$5:$J$180,F$19) -> 164000000 | G22: =SUMIFS(物件データ!$G$5:$G$180,物件データ!$L$5:$L$180,1,物件データ!$B$5:$B$180,$A22,物件データ!$J$5:$J$180,G$19) -> 29800000 | H22: =SUMIFS(物件データ!$G$5:$G$180,物件データ!$L$5:$L$180,1,物件データ!$B$5:$B$180,$A22,物件データ!$J$5:$J$180,"?*") -> 815050000
A23: 戸建リフォーム再販 | B23: =SUMIFS(物件データ!$G$5:$G$180,物件データ!$L$5:$L$180,1,物件データ!$B$5:$B$180,$A23,物件データ!$J$5:$J$180,B$19) -> 303200000 | C23: =SUMIFS(物件データ!$G$5:$G$180,物件データ!$L$5:$L$180,1,物件データ!$B$5:$B$180,$A23,物件データ!$J$5:$J$180,C$19) -> 162800000 | D23: =SUMIFS(物件データ!$G$5:$G$180,物件データ!$L$5:$L$180,1,物件データ!$B$5:$B$180,$A23,物件データ!$J$5:$J$180,D$19) -> 74800000 | E23: =SUMIFS(物件データ!$G$5:$G$180,物件データ!$L$5:$L$180,1,物件データ!$B$5:$B$180,$A23,物件データ!$J$5:$J$180,E$19) -> 139400000 | F23: =SUMIFS(物件データ!$G$5:$G$180,物件データ!$L$5:$L$180,1,物件データ!$B$5:$B$180,$A23,物件データ!$J$5:$J$180,F$19) -> 310700000 | G23: =SUMIFS(物件データ!$G$5:$G$180,物件データ!$L$5:$L$180,1,物件データ!$B$5:$B$180,$A23,物件データ!$J$5:$J$180,G$19) -> 0 | H23: =SUMIFS(物件データ!$G$5:$G$180,物件データ!$L$5:$L$180,1,物件データ!$B$5:$B$180,$A23,物件データ!$J$5:$J$180,"?*") -> 990900000
A24: 条件付き土地 | B24: =SUMIFS(物件データ!$G$5:$G$180,物件データ!$L$5:$L$180,1,物件データ!$B$5:$B$180,$A24,物件データ!$J$5:$J$180,B$19) -> 107700000 | C24: =SUMIFS(物件データ!$G$5:$G$180,物件データ!$L$5:$L$180,1,物件データ!$B$5:$B$180,$A24,物件データ!$J$5:$J$180,C$19) -> 41500000 | D24: =SUMIFS(物件データ!$G$5:$G$180,物件データ!$L$5:$L$180,1,物件データ!$B$5:$B$180,$A24,物件データ!$J$5:$J$180,D$19) -> 0 | E24: =SUMIFS(物件データ!$G$5:$G$180,物件データ!$L$5:$L$180,1,物件データ!$B$5:$B$180,$A24,物件データ!$J$5:$J$180,E$19) -> 188400000 | F24: =SUMIFS(物件データ!$G$5:$G$180,物件データ!$L$5:$L$180,1,物件データ!$B$5:$B$180,$A24,物件データ!$J$5:$J$180,F$19) -> 0 | G24: =SUMIFS(物件データ!$G$5:$G$180,物件データ!$L$5:$L$180,1,物件データ!$B$5:$B$180,$A24,物件データ!$J$5:$J$180,G$19) -> 0 | H24: =SUMIFS(物件データ!$G$5:$G$180,物件データ!$L$5:$L$180,1,物件データ!$B$5:$B$180,$A24,物件データ!$J$5:$J$180,"?*") -> 337600000
A25: 立ち退き後転売土地 | B25: =SUMIFS(物件データ!$G$5:$G$180,物件データ!$L$5:$L$180,1,物件データ!$B$5:$B$180,$A25,物件データ!$J$5:$J$180,B$19) -> 0 | C25: =SUMIFS(物件データ!$G$5:$G$180,物件データ!$L$5:$L$180,1,物件データ!$B$5:$B$180,$A25,物件データ!$J$5:$J$180,C$19) -> 0 | D25: =SUMIFS(物件データ!$G$5:$G$180,物件データ!$L$5:$L$180,1,物件データ!$B$5:$B$180,$A25,物件データ!$J$5:$J$180,D$19) -> 99800000 | E25: =SUMIFS(物件データ!$G$5:$G$180,物件データ!$L$5:$L$180,1,物件データ!$B$5:$B$180,$A25,物件データ!$J$5:$J$180,E$19) -> 127700000 | F25: =SUMIFS(物件データ!$G$5:$G$180,物件データ!$L$5:$L$180,1,物件データ!$B$5:$B$180,$A25,物件データ!$J$5:$J$180,F$19) -> 128000000 | G25: =SUMIFS(物件データ!$G$5:$G$180,物件データ!$L$5:$L$180,1,物件データ!$B$5:$B$180,$A25,物件データ!$J$5:$J$180,G$19) -> 0 | H25: =SUMIFS(物件データ!$G$5:$G$180,物件データ!$L$5:$L$180,1,物件データ!$B$5:$B$180,$A25,物件データ!$J$5:$J$180,"?*") -> 355500000
A26: 一棟収益天端 | B26: =SUMIFS(物件データ!$G$5:$G$180,物件データ!$L$5:$L$180,1,物件データ!$B$5:$B$180,$A26,物件データ!$J$5:$J$180,B$19) -> 0 | C26: =SUMIFS(物件データ!$G$5:$G$180,物件データ!$L$5:$L$180,1,物件データ!$B$5:$B$180,$A26,物件データ!$J$5:$J$180,C$19) -> 173500000 | D26: =SUMIFS(物件データ!$G$5:$G$180,物件データ!$L$5:$L$180,1,物件データ!$B$5:$B$180,$A26,物件データ!$J$5:$J$180,D$19) -> 0 | E26: =SUMIFS(物件データ!$G$5:$G$180,物件データ!$L$5:$L$180,1,物件データ!$B$5:$B$180,$A26,物件データ!$J$5:$J$180,E$19) -> 110000000 | F26: =SUMIFS(物件データ!$G$5:$G$180,物件データ!$L$5:$L$180,1,物件データ!$B$5:$B$180,$A26,物件データ!$J$5:$J$180,F$19) -> 230000000 | G26: =SUMIFS(物件データ!$G$5:$G$180,物件データ!$L$5:$L$180,1,物件データ!$B$5:$B$180,$A26,物件データ!$J$5:$J$180,G$19) -> 0 | H26: =SUMIFS(物件データ!$G$5:$G$180,物件データ!$L$5:$L$180,1,物件データ!$B$5:$B$180,$A26,物件データ!$J$5:$J$180,"?*") -> 513500000
A27: OC転売 | B27: =SUMIFS(物件データ!$G$5:$G$180,物件データ!$L$5:$L$180,1,物件データ!$B$5:$B$180,$A27,物件データ!$J$5:$J$180,B$19) -> 0 | C27: =SUMIFS(物件データ!$G$5:$G$180,物件データ!$L$5:$L$180,1,物件データ!$B$5:$B$180,$A27,物件データ!$J$5:$J$180,C$19) -> 39000000 | D27: =SUMIFS(物件データ!$G$5:$G$180,物件データ!$L$5:$L$180,1,物件データ!$B$5:$B$180,$A27,物件データ!$J$5:$J$180,D$19) -> 0 | E27: =SUMIFS(物件データ!$G$5:$G$180,物件データ!$L$5:$L$180,1,物件データ!$B$5:$B$180,$A27,物件データ!$J$5:$J$180,E$19) -> 102000000 | F27: =SUMIFS(物件データ!$G$5:$G$180,物件データ!$L$5:$L$180,1,物件データ!$B$5:$B$180,$A27,物件データ!$J$5:$J$180,F$19) -> 0 | G27: =SUMIFS(物件データ!$G$5:$G$180,物件データ!$L$5:$L$180,1,物件データ!$B$5:$B$180,$A27,物件データ!$J$5:$J$180,G$19) -> 0 | H27: =SUMIFS(物件データ!$G$5:$G$180,物件データ!$L$5:$L$180,1,物件データ!$B$5:$B$180,$A27,物件データ!$J$5:$J$180,"?*") -> 141000000
A28: JT | B28: =SUMIFS(物件データ!$G$5:$G$180,物件データ!$L$5:$L$180,1,物件データ!$B$5:$B$180,$A28,物件データ!$J$5:$J$180,B$19) -> 0 | C28: =SUMIFS(物件データ!$G$5:$G$180,物件データ!$L$5:$L$180,1,物件データ!$B$5:$B$180,$A28,物件データ!$J$5:$J$180,C$19) -> 0 | D28: =SUMIFS(物件データ!$G$5:$G$180,物件データ!$L$5:$L$180,1,物件データ!$B$5:$B$180,$A28,物件データ!$J$5:$J$180,D$19) -> 0 | E28: =SUMIFS(物件データ!$G$5:$G$180,物件データ!$L$5:$L$180,1,物件データ!$B$5:$B$180,$A28,物件データ!$J$5:$J$180,E$19) -> 320000000 | F28: =SUMIFS(物件データ!$G$5:$G$180,物件データ!$L$5:$L$180,1,物件データ!$B$5:$B$180,$A28,物件データ!$J$5:$J$180,F$19) -> 0 | G28: =SUMIFS(物件データ!$G$5:$G$180,物件データ!$L$5:$L$180,1,物件データ!$B$5:$B$180,$A28,物件データ!$J$5:$J$180,G$19) -> 0 | H28: =SUMIFS(物件データ!$G$5:$G$180,物件データ!$L$5:$L$180,1,物件データ!$B$5:$B$180,$A28,物件データ!$J$5:$J$180,"?*") -> 320000000
A29: たちのき後転売MS | B29: =SUMIFS(物件データ!$G$5:$G$180,物件データ!$L$5:$L$180,1,物件データ!$B$5:$B$180,$A29,物件データ!$J$5:$J$180,B$19) -> 0 | C29: =SUMIFS(物件データ!$G$5:$G$180,物件データ!$L$5:$L$180,1,物件データ!$B$5:$B$180,$A29,物件データ!$J$5:$J$180,C$19) -> 0 | D29: =SUMIFS(物件データ!$G$5:$G$180,物件データ!$L$5:$L$180,1,物件データ!$B$5:$B$180,$A29,物件データ!$J$5:$J$180,D$19) -> 0 | E29: =SUMIFS(物件データ!$G$5:$G$180,物件データ!$L$5:$L$180,1,物件データ!$B$5:$B$180,$A29,物件データ!$J$5:$J$180,E$19) -> 0 | F29: =SUMIFS(物件データ!$G$5:$G$180,物件データ!$L$5:$L$180,1,物件データ!$B$5:$B$180,$A29,物件データ!$J$5:$J$180,F$19) -> 37000000 | G29: =SUMIFS(物件データ!$G$5:$G$180,物件データ!$L$5:$L$180,1,物件データ!$B$5:$B$180,$A29,物件データ!$J$5:$J$180,G$19) -> 0 | H29: =SUMIFS(物件データ!$G$5:$G$180,物件データ!$L$5:$L$180,1,物件データ!$B$5:$B$180,$A29,物件データ!$J$5:$J$180,"?*") -> 37000000
A30: 合計 | B30: =SUM(B20:B29) -> 1869500000 | C30: =SUM(C20:C29) -> 2411650000 | D30: =SUM(D20:D29) -> 423100000 | E30: =SUM(E20:E29) -> 2105600000 | F30: =SUM(F20:F29) -> 2875200000 | G30: =SUM(G20:G29) -> 429900000 | H30: =SUM(H20:H29) -> 10114950000
A32: 粗利（円）※原価入力済のみ
A33: 物件種別 | B33: 10期 | C33: 11期 | D33: 12期 | E33: 13期 | F33: 14期 | G33: 15期 | H33: 合計
A34: 新築戸建 | B34: =SUMIFS(物件データ!$M$5:$M$180,物件データ!$L$5:$L$180,1,物件データ!$B$5:$B$180,$A34,物件データ!$J$5:$J$180,B$33) -> 0 | C34: =SUMIFS(物件データ!$M$5:$M$180,物件データ!$L$5:$L$180,1,物件データ!$B$5:$B$180,$A34,物件データ!$J$5:$J$180,C$33) -> 183010000 | D34: =SUMIFS(物件データ!$M$5:$M$180,物件データ!$L$5:$L$180,1,物件データ!$B$5:$B$180,$A34,物件データ!$J$5:$J$180,D$33) -> 33670000 | E34: =SUMIFS(物件データ!$M$5:$M$180,物件データ!$L$5:$L$180,1,物件データ!$B$5:$B$180,$A34,物件データ!$J$5:$J$180,E$33) -> 75200000 | F34: =SUMIFS(物件データ!$M$5:$M$180,物件データ!$L$5:$L$180,1,物件データ!$B$5:$B$180,$A34,物件データ!$J$5:$J$180,F$33) -> 158785000 | G34: =SUMIFS(物件データ!$M$5:$M$180,物件データ!$L$5:$L$180,1,物件データ!$B$5:$B$180,$A34,物件データ!$J$5:$J$180,G$33) -> 25000000 | H34: =SUMIFS(物件データ!$M$5:$M$180,物件データ!$L$5:$L$180,1,物件データ!$B$5:$B$180,$A34,物件データ!$J$5:$J$180,"?*") -> 475665000
A35: 条件なし土地 | B35: =SUMIFS(物件データ!$M$5:$M$180,物件データ!$L$5:$L$180,1,物件データ!$B$5:$B$180,$A35,物件データ!$J$5:$J$180,B$33) -> 28786000 | C35: =SUMIFS(物件データ!$M$5:$M$180,物件データ!$L$5:$L$180,1,物件データ!$B$5:$B$180,$A35,物件データ!$J$5:$J$180,C$33) -> 17200000 | D35: =SUMIFS(物件データ!$M$5:$M$180,物件データ!$L$5:$L$180,1,物件データ!$B$5:$B$180,$A35,物件データ!$J$5:$J$180,D$33) -> 0 | E35: =SUMIFS(物件データ!$M$5:$M$180,物件データ!$L$5:$L$180,1,物件データ!$B$5:$B$180,$A35,物件データ!$J$5:$J$180,E$33) -> 52461000 | F35: =SUMIFS(物件データ!$M$5:$M$180,物件データ!$L$5:$L$180,1,物件データ!$B$5:$B$180,$A35,物件データ!$J$5:$J$180,F$33) -> 251950000 | G35: =SUMIFS(物件データ!$M$5:$M$180,物件データ!$L$5:$L$180,1,物件データ!$B$5:$B$180,$A35,物件データ!$J$5:$J$180,G$33) -> -10216000 | H35: =SUMIFS(物件データ!$M$5:$M$180,物件データ!$L$5:$L$180,1,物件データ!$B$5:$B$180,$A35,物件データ!$J$5:$J$180,"?*") -> 340181000
A36: MSリフォーム再販 | B36: =SUMIFS(物件データ!$M$5:$M$180,物件データ!$L$5:$L$180,1,物件データ!$B$5:$B$180,$A36,物件データ!$J$5:$J$180,B$33) -> 0 | C36: =SUMIFS(物件データ!$M$5:$M$180,物件データ!$L$5:$L$180,1,物件データ!$B$5:$B$180,$A36,物件データ!$J$5:$J$180,C$33) -> 12260000 | D36: =SUMIFS(物件データ!$M$5:$M$180,物件データ!$L$5:$L$180,1,物件データ!$B$5:$B$180,$A36,物件データ!$J$5:$J$180,D$33) -> 0 | E36: =SUMIFS(物件データ!$M$5:$M$180,物件データ!$L$5:$L$180,1,物件データ!$B$5:$B$180,$A36,物件データ!$J$5:$J$180,E$33) -> -8750000 | F36: =SUMIFS(物件データ!$M$5:$M$180,物件データ!$L$5:$L$180,1,物件データ!$B$5:$B$180,$A36,物件データ!$J$5:$J$180,F$33) -> 24000000 | G36: =SUMIFS(物件データ!$M$5:$M$180,物件データ!$L$5:$L$180,1,物件データ!$B$5:$B$180,$A36,物件データ!$J$5:$J$180,G$33) -> 8690000 | H36: =SUMIFS(物件データ!$M$5:$M$180,物件データ!$L$5:$L$180,1,物件データ!$B$5:$B$180,$A36,物件データ!$J$5:$J$180,"?*") -> 36200000
A37: 戸建リフォーム再販 | B37: =SUMIFS(物件データ!$M$5:$M$180,物件データ!$L$5:$L$180,1,物件データ!$B$5:$B$180,$A37,物件データ!$J$5:$J$180,B$33) -> 10342000 | C37: =SUMIFS(物件データ!$M$5:$M$180,物件データ!$L$5:$L$180,1,物件データ!$B$5:$B$180,$A37,物件データ!$J$5:$J$180,C$33) -> 23500000 | D37: =SUMIFS(物件データ!$M$5:$M$180,物件データ!$L$5:$L$180,1,物件データ!$B$5:$B$180,$A37,物件データ!$J$5:$J$180,D$33) -> 13000000 | E37: =SUMIFS(物件データ!$M$5:$M$180,物件データ!$L$5:$L$180,1,物件データ!$B$5:$B$180,$A37,物件データ!$J$5:$J$180,E$33) -> 18600000 | F37: =SUMIFS(物件データ!$M$5:$M$180,物件データ!$L$5:$L$180,1,物件データ!$B$5:$B$180,$A37,物件データ!$J$5:$J$180,F$33) -> 36400000 | G37: =SUMIFS(物件データ!$M$5:$M$180,物件データ!$L$5:$L$180,1,物件データ!$B$5:$B$180,$A37,物件データ!$J$5:$J$180,G$33) -> 0 | H37: =SUMIFS(物件データ!$M$5:$M$180,物件データ!$L$5:$L$180,1,物件データ!$B$5:$B$180,$A37,物件データ!$J$5:$J$180,"?*") -> 101842000
A38: 条件付き土地 | B38: =SUMIFS(物件データ!$M$5:$M$180,物件データ!$L$5:$L$180,1,物件データ!$B$5:$B$180,$A38,物件データ!$J$5:$J$180,B$33) -> 9033600 | C38: =SUMIFS(物件データ!$M$5:$M$180,物件データ!$L$5:$L$180,1,物件データ!$B$5:$B$180,$A38,物件データ!$J$5:$J$180,C$33) -> 10950000 | D38: =SUMIFS(物件データ!$M$5:$M$180,物件データ!$L$5:$L$180,1,物件データ!$B$5:$B$180,$A38,物件データ!$J$5:$J$180,D$33) -> 0 | E38: =SUMIFS(物件データ!$M$5:$M$180,物件データ!$L$5:$L$180,1,物件データ!$B$5:$B$180,$A38,物件データ!$J$5:$J$180,E$33) -> 41850000 | F38: =SUMIFS(物件データ!$M$5:$M$180,物件データ!$L$5:$L$180,1,物件データ!$B$5:$B$180,$A38,物件データ!$J$5:$J$180,F$33) -> 0 | G38: =SUMIFS(物件データ!$M$5:$M$180,物件データ!$L$5:$L$180,1,物件データ!$B$5:$B$180,$A38,物件データ!$J$5:$J$180,G$33) -> 0 | H38: =SUMIFS(物件データ!$M$5:$M$180,物件データ!$L$5:$L$180,1,物件データ!$B$5:$B$180,$A38,物件データ!$J$5:$J$180,"?*") -> 61833600
A39: 立ち退き後転売土地 | B39: =SUMIFS(物件データ!$M$5:$M$180,物件データ!$L$5:$L$180,1,物件データ!$B$5:$B$180,$A39,物件データ!$J$5:$J$180,B$33) -> 0 | C39: =SUMIFS(物件データ!$M$5:$M$180,物件データ!$L$5:$L$180,1,物件データ!$B$5:$B$180,$A39,物件データ!$J$5:$J$180,C$33) -> 0 | D39: =SUMIFS(物件データ!$M$5:$M$180,物件データ!$L$5:$L$180,1,物件データ!$B$5:$B$180,$A39,物件データ!$J$5:$J$180,D$33) -> 25200000 | E39: =SUMIFS(物件データ!$M$5:$M$180,物件データ!$L$5:$L$180,1,物件データ!$B$5:$B$180,$A39,物件データ!$J$5:$J$180,E$33) -> 19230000 | F39: =SUMIFS(物件データ!$M$5:$M$180,物件データ!$L$5:$L$180,1,物件データ!$B$5:$B$180,$A39,物件データ!$J$5:$J$180,F$33) -> 13606090 | G39: =SUMIFS(物件データ!$M$5:$M$180,物件データ!$L$5:$L$180,1,物件データ!$B$5:$B$180,$A39,物件データ!$J$5:$J$180,G$33) -> 0 | H39: =SUMIFS(物件データ!$M$5:$M$180,物件データ!$L$5:$L$180,1,物件データ!$B$5:$B$180,$A39,物件データ!$J$5:$J$180,"?*") -> 58036090
A40: 一棟収益天端 | B40: =SUMIFS(物件データ!$M$5:$M$180,物件データ!$L$5:$L$180,1,物件データ!$B$5:$B$180,$A40,物件データ!$J$5:$J$180,B$33) -> 0 | C40: =SUMIFS(物件データ!$M$5:$M$180,物件データ!$L$5:$L$180,1,物件データ!$B$5:$B$180,$A40,物件データ!$J$5:$J$180,C$33) -> 33500000 | D40: =SUMIFS(物件データ!$M$5:$M$180,物件データ!$L$5:$L$180,1,物件データ!$B$5:$B$180,$A40,物件データ!$J$5:$J$180,D$33) -> 0 | E40: =SUMIFS(物件データ!$M$5:$M$180,物件データ!$L$5:$L$180,1,物件データ!$B$5:$B$180,$A40,物件データ!$J$5:$J$180,E$33) -> 9800000 | F40: =SUMIFS(物件データ!$M$5:$M$180,物件データ!$L$5:$L$180,1,物件データ!$B$5:$B$180,$A40,物件データ!$J$5:$J$180,F$33) -> 17000000 | G40: =SUMIFS(物件データ!$M$5:$M$180,物件データ!$L$5:$L$180,1,物件データ!$B$5:$B$180,$A40,物件データ!$J$5:$J$180,G$33) -> 0 | H40: =SUMIFS(物件データ!$M$5:$M$180,物件データ!$L$5:$L$180,1,物件データ!$B$5:$B$180,$A40,物件データ!$J$5:$J$180,"?*") -> 60300000
A41: OC転売 | B41: =SUMIFS(物件データ!$M$5:$M$180,物件データ!$L$5:$L$180,1,物件データ!$B$5:$B$180,$A41,物件データ!$J$5:$J$180,B$33) -> 0 | C41: =SUMIFS(物件データ!$M$5:$M$180,物件データ!$L$5:$L$180,1,物件データ!$B$5:$B$180,$A41,物件データ!$J$5:$J$180,C$33) -> 0 | D41: =SUMIFS(物件データ!$M$5:$M$180,物件データ!$L$5:$L$180,1,物件データ!$B$5:$B$180,$A41,物件データ!$J$5:$J$180,D$33) -> 0 | E41: =SUMIFS(物件データ!$M$5:$M$180,物件データ!$L$5:$L$180,1,物件データ!$B$5:$B$180,$A41,物件データ!$J$5:$J$180,E$33) -> 13300000 | F41: =SUMIFS(物件データ!$M$5:$M$180,物件データ!$L$5:$L$180,1,物件データ!$B$5:$B$180,$A41,物件データ!$J$5:$J$180,F$33) -> 0 | G41: =SUMIFS(物件データ!$M$5:$M$180,物件データ!$L$5:$L$180,1,物件データ!$B$5:$B$180,$A41,物件データ!$J$5:$J$180,G$33) -> 0 | H41: =SUMIFS(物件データ!$M$5:$M$180,物件データ!$L$5:$L$180,1,物件データ!$B$5:$B$180,$A41,物件データ!$J$5:$J$180,"?*") -> 13300000
A42: JT | B42: =SUMIFS(物件データ!$M$5:$M$180,物件データ!$L$5:$L$180,1,物件データ!$B$5:$B$180,$A42,物件データ!$J$5:$J$180,B$33) -> 0 | C42: =SUMIFS(物件データ!$M$5:$M$180,物件データ!$L$5:$L$180,1,物件データ!$B$5:$B$180,$A42,物件データ!$J$5:$J$180,C$33) -> 0 | D42: =SUMIFS(物件データ!$M$5:$M$180,物件データ!$L$5:$L$180,1,物件データ!$B$5:$B$180,$A42,物件データ!$J$5:$J$180,D$33) -> 0 | E42: =SUMIFS(物件データ!$M$5:$M$180,物件データ!$L$5:$L$180,1,物件データ!$B$5:$B$180,$A42,物件データ!$J$5:$J$180,E$33) -> 77750000 | F42: =SUMIFS(物件データ!$M$5:$M$180,物件データ!$L$5:$L$180,1,物件データ!$B$5:$B$180,$A42,物件データ!$J$5:$J$180,F$33) -> 0 | G42: =SUMIFS(物件データ!$M$5:$M$180,物件データ!$L$5:$L$180,1,物件データ!$B$5:$B$180,$A42,物件データ!$J$5:$J$180,G$33) -> 0 | H42: =SUMIFS(物件データ!$M$5:$M$180,物件データ!$L$5:$L$180,1,物件データ!$B$5:$B$180,$A42,物件データ!$J$5:$J$180,"?*") -> 77750000
A43: たちのき後転売MS | B43: =SUMIFS(物件データ!$M$5:$M$180,物件データ!$L$5:$L$180,1,物件データ!$B$5:$B$180,$A43,物件データ!$J$5:$J$180,B$33) -> 0 | C43: =SUMIFS(物件データ!$M$5:$M$180,物件データ!$L$5:$L$180,1,物件データ!$B$5:$B$180,$A43,物件データ!$J$5:$J$180,C$33) -> 0 | D43: =SUMIFS(物件データ!$M$5:$M$180,物件データ!$L$5:$L$180,1,物件データ!$B$5:$B$180,$A43,物件データ!$J$5:$J$180,D$33) -> 0 | E43: =SUMIFS(物件データ!$M$5:$M$180,物件データ!$L$5:$L$180,1,物件データ!$B$5:$B$180,$A43,物件データ!$J$5:$J$180,E$33) -> 0 | F43: =SUMIFS(物件データ!$M$5:$M$180,物件データ!$L$5:$L$180,1,物件データ!$B$5:$B$180,$A43,物件データ!$J$5:$J$180,F$33) -> 5600000 | G43: =SUMIFS(物件データ!$M$5:$M$180,物件データ!$L$5:$L$180,1,物件データ!$B$5:$B$180,$A43,物件データ!$J$5:$J$180,G$33) -> 0 | H43: =SUMIFS(物件データ!$M$5:$M$180,物件データ!$L$5:$L$180,1,物件データ!$B$5:$B$180,$A43,物件データ!$J$5:$J$180,"?*") -> 5600000
A44: 合計 | B44: =SUM(B34:B43) -> 48161600 | C44: =SUM(C34:C43) -> 280420000 | D44: =SUM(D34:D43) -> 71870000 | E44: =SUM(E34:E43) -> 299441000 | F44: =SUM(F34:F43) -> 507341090 | G44: =SUM(G34:G43) -> 23474000 | H44: =SUM(H34:H43) -> 1230707690
A46: 粗利率 ※原価入力済のみ
A47: 物件種別 | B47: 10期 | C47: 11期 | D47: 12期 | E47: 13期 | F47: 14期 | G47: 15期 | H47: 合計
A48: 新築戸建 | B48: =IFERROR(SUMIFS(物件データ!$M$5:$M$180,物件データ!$L$5:$L$180,1,物件データ!$B$5:$B$180,$A48,物件データ!$J$5:$J$180,B$47,物件データ!$H$5:$H$180,">0")/SUMIFS(物件データ!$G$5:$G$180,物件データ!$L$5:$L$180,1,物件データ!$B$5:$B$180,$A48,物件データ!$J$5:$J$180,B$47,物件データ!$H$5:$H$180,">0"),"") | C48: =IFERROR(SUMIFS(物件データ!$M$5:$M$180,物件データ!$L$5:$L$180,1,物件データ!$B$5:$B$180,$A48,物件データ!$J$5:$J$180,C$47,物件データ!$H$5:$H$180,">0")/SUMIFS(物件データ!$G$5:$G$180,物件データ!$L$5:$L$180,1,物件データ!$B$5:$B$180,$A48,物件データ!$J$5:$J$180,C$47,物件データ!$H$5:$H$180,">0"),"") -> 0.15763135 | D48: =IFERROR(SUMIFS(物件データ!$M$5:$M$180,物件データ!$L$5:$L$180,1,物件データ!$B$5:$B$180,$A48,物件データ!$J$5:$J$180,D$47,物件データ!$H$5:$H$180,">0")/SUMIFS(物件データ!$G$5:$G$180,物件データ!$L$5:$L$180,1,物件データ!$B$5:$B$180,$A48,物件データ!$J$5:$J$180,D$47,物件データ!$H$5:$H$180,">0"),"") -> 0.13549296 | E48: =IFERROR(SUMIFS(物件データ!$M$5:$M$180,物件データ!$L$5:$L$180,1,物件データ!$B$5:$B$180,$A48,物件データ!$J$5:$J$180,E$47,物件データ!$H$5:$H$180,">0")/SUMIFS(物件データ!$G$5:$G$180,物件データ!$L$5:$L$180,1,物件データ!$B$5:$B$180,$A48,物件データ!$J$5:$J$180,E$47,物件データ!$H$5:$H$180,">0"),"") -> 0.12419488 | F48: =IFERROR(SUMIFS(物件データ!$M$5:$M$180,物件データ!$L$5:$L$180,1,物件データ!$B$5:$B$180,$A48,物件データ!$J$5:$J$180,F$47,物件データ!$H$5:$H$180,">0")/SUMIFS(物件データ!$G$5:$G$180,物件データ!$L$5:$L$180,1,物件データ!$B$5:$B$180,$A48,物件データ!$J$5:$J$180,F$47,物件データ!$H$5:$H$180,">0"),"") -> 0.20010712 | G48: =IFERROR(SUMIFS(物件データ!$M$5:$M$180,物件データ!$L$5:$L$180,1,物件データ!$B$5:$B$180,$A48,物件データ!$J$5:$J$180,G$47,物件データ!$H$5:$H$180,">0")/SUMIFS(物件データ!$G$5:$G$180,物件データ!$L$5:$L$180,1,物件データ!$B$5:$B$180,$A48,物件データ!$J$5:$J$180,G$47,物件データ!$H$5:$H$180,">0"),"") -> 0.166334 | H48: =IFERROR(SUMIFS(物件データ!$M$5:$M$180,物件データ!$L$5:$L$180,1,物件データ!$B$5:$B$180,$A48,物件データ!$J$5:$J$180,"?*",物件データ!$H$5:$H$180,">0")/SUMIFS(物件データ!$G$5:$G$180,物件データ!$L$5:$L$180,1,物件データ!$B$5:$B$180,$A48,物件データ!$J$5:$J$180,"?*",物件データ!$H$5:$H$180,">0"),"") -> 0.16076281
A49: 条件なし土地 | B49: =IFERROR(SUMIFS(物件データ!$M$5:$M$180,物件データ!$L$5:$L$180,1,物件データ!$B$5:$B$180,$A49,物件データ!$J$5:$J$180,B$47,物件データ!$H$5:$H$180,">0")/SUMIFS(物件データ!$G$5:$G$180,物件データ!$L$5:$L$180,1,物件データ!$B$5:$B$180,$A49,物件データ!$J$5:$J$180,B$47,物件データ!$H$5:$H$180,">0"),"") -> 0.2085942 | C49: =IFERROR(SUMIFS(物件データ!$M$5:$M$180,物件データ!$L$5:$L$180,1,物件データ!$B$5:$B$180,$A49,物件データ!$J$5:$J$180,C$47,物件データ!$H$5:$H$180,">0")/SUMIFS(物件データ!$G$5:$G$180,物件データ!$L$5:$L$180,1,物件データ!$B$5:$B$180,$A49,物件データ!$J$5:$J$180,C$47,物件データ!$H$5:$H$180,">0"),"") -> 0.13292117 | D49: =IFERROR(SUMIFS(物件データ!$M$5:$M$180,物件データ!$L$5:$L$180,1,物件データ!$B$5:$B$180,$A49,物件データ!$J$5:$J$180,D$47,物件データ!$H$5:$H$180,">0")/SUMIFS(物件データ!$G$5:$G$180,物件データ!$L$5:$L$180,1,物件データ!$B$5:$B$180,$A49,物件データ!$J$5:$J$180,D$47,物件データ!$H$5:$H$180,">0"),"") | E49: =IFERROR(SUMIFS(物件データ!$M$5:$M$180,物件データ!$L$5:$L$180,1,物件データ!$B$5:$B$180,$A49,物件データ!$J$5:$J$180,E$47,物件データ!$H$5:$H$180,">0")/SUMIFS(物件データ!$G$5:$G$180,物件データ!$L$5:$L$180,1,物件データ!$B$5:$B$180,$A49,物件データ!$J$5:$J$180,E$47,物件データ!$H$5:$H$180,">0"),"") -> 0.20115414 | F49: =IFERROR(SUMIFS(物件データ!$M$5:$M$180,物件データ!$L$5:$L$180,1,物件データ!$B$5:$B$180,$A49,物件データ!$J$5:$J$180,F$47,物件データ!$H$5:$H$180,">0")/SUMIFS(物件データ!$G$5:$G$180,物件データ!$L$5:$L$180,1,物件データ!$B$5:$B$180,$A49,物件データ!$J$5:$J$180,F$47,物件データ!$H$5:$H$180,">0"),"") -> 0.20787954 | G49: =IFERROR(SUMIFS(物件データ!$M$5:$M$180,物件データ!$L$5:$L$180,1,物件データ!$B$5:$B$180,$A49,物件データ!$J$5:$J$180,G$47,物件データ!$H$5:$H$180,">0")/SUMIFS(物件データ!$G$5:$G$180,物件データ!$L$5:$L$180,1,物件データ!$B$5:$B$180,$A49,物件データ!$J$5:$J$180,G$47,物件データ!$H$5:$H$180,">0"),"") -> -0.040896717 | H49: =IFERROR(SUMIFS(物件データ!$M$5:$M$180,物件データ!$L$5:$L$180,1,物件データ!$B$5:$B$180,$A49,物件データ!$J$5:$J$180,"?*",物件データ!$H$5:$H$180,">0")/SUMIFS(物件データ!$G$5:$G$180,物件データ!$L$5:$L$180,1,物件データ!$B$5:$B$180,$A49,物件データ!$J$5:$J$180,"?*",物件データ!$H$5:$H$180,">0"),"") -> 0.17094523
A50: MSリフォーム再販 | B50: =IFERROR(SUMIFS(物件データ!$M$5:$M$180,物件データ!$L$5:$L$180,1,物件データ!$B$5:$B$180,$A50,物件データ!$J$5:$J$180,B$47,物件データ!$H$5:$H$180,">0")/SUMIFS(物件データ!$G$5:$G$180,物件データ!$L$5:$L$180,1,物件データ!$B$5:$B$180,$A50,物件データ!$J$5:$J$180,B$47,物件データ!$H$5:$H$180,">0"),"") | C50: =IFERROR(SUMIFS(物件データ!$M$5:$M$180,物件データ!$L$5:$L$180,1,物件データ!$B$5:$B$180,$A50,物件データ!$J$5:$J$180,C$47,物件データ!$H$5:$H$180,">0")/SUMIFS(物件データ!$G$5:$G$180,物件データ!$L$5:$L$180,1,物件データ!$B$5:$B$180,$A50,物件データ!$J$5:$J$180,C$47,物件データ!$H$5:$H$180,">0"),"") -> 0.062280925 | D50: =IFERROR(SUMIFS(物件データ!$M$5:$M$180,物件データ!$L$5:$L$180,1,物件データ!$B$5:$B$180,$A50,物件データ!$J$5:$J$180,D$47,物件データ!$H$5:$H$180,">0")/SUMIFS(物件データ!$G$5:$G$180,物件データ!$L$5:$L$180,1,物件データ!$B$5:$B$180,$A50,物件データ!$J$5:$J$180,D$47,物件データ!$H$5:$H$180,">0"),"") | E50: =IFERROR(SUMIFS(物件データ!$M$5:$M$180,物件データ!$L$5:$L$180,1,物件データ!$B$5:$B$180,$A50,物件データ!$J$5:$J$180,E$47,物件データ!$H$5:$H$180,">0")/SUMIFS(物件データ!$G$5:$G$180,物件データ!$L$5:$L$180,1,物件データ!$B$5:$B$180,$A50,物件データ!$J$5:$J$180,E$47,物件データ!$H$5:$H$180,">0"),"") -> -0.098536036 | F50: =IFERROR(SUMIFS(物件データ!$M$5:$M$180,物件データ!$L$5:$L$180,1,物件データ!$B$5:$B$180,$A50,物件データ!$J$5:$J$180,F$47,物件データ!$H$5:$H$180,">0")/SUMIFS(物件データ!$G$5:$G$180,物件データ!$L$5:$L$180,1,物件データ!$B$5:$B$180,$A50,物件データ!$J$5:$J$180,F$47,物件データ!$H$5:$H$180,">0"),"") -> 0.18320611 | G50: =IFERROR(SUMIFS(物件データ!$M$5:$M$180,物件データ!$L$5:$L$180,1,物件データ!$B$5:$B$180,$A50,物件データ!$J$5:$J$180,G$47,物件データ!$H$5:$H$180,">0")/SUMIFS(物件データ!$G$5:$G$180,物件データ!$L$5:$L$180,1,物件データ!$B$5:$B$180,$A50,物件データ!$J$5:$J$180,G$47,物件データ!$H$5:$H$180,">0"),"") -> 0.29161074 | H50: =IFERROR(SUMIFS(物件データ!$M$5:$M$180,物件データ!$L$5:$L$180,1,物件データ!$B$5:$B$180,$A50,物件データ!$J$5:$J$180,"?*",物件データ!$H$5:$H$180,">0")/SUMIFS(物件データ!$G$5:$G$180,物件データ!$L$5:$L$180,1,物件データ!$B$5:$B$180,$A50,物件データ!$J$5:$J$180,"?*",物件データ!$H$5:$H$180,">0"),"") -> 0.081084108
A51: 戸建リフォーム再販 | B51: =IFERROR(SUMIFS(物件データ!$M$5:$M$180,物件データ!$L$5:$L$180,1,物件データ!$B$5:$B$180,$A51,物件データ!$J$5:$J$180,B$47,物件データ!$H$5:$H$180,">0")/SUMIFS(物件データ!$G$5:$G$180,物件データ!$L$5:$L$180,1,物件データ!$B$5:$B$180,$A51,物件データ!$J$5:$J$180,B$47,物件データ!$H$5:$H$180,">0"),"") -> 0.12341289 | C51: =IFERROR(SUMIFS(物件データ!$M$5:$M$180,物件データ!$L$5:$L$180,1,物件データ!$B$5:$B$180,$A51,物件データ!$J$5:$J$180,C$47,物件データ!$H$5:$H$180,">0")/SUMIFS(物件データ!$G$5:$G$180,物件データ!$L$5:$L$180,1,物件データ!$B$5:$B$180,$A51,物件データ!$J$5:$J$180,C$47,物件データ!$H$5:$H$180,">0"),"") -> 0.14434889 | D51: =IFERROR(SUMIFS(物件データ!$M$5:$M$180,物件データ!$L$5:$L$180,1,物件データ!$B$5:$B$180,$A51,物件データ!$J$5:$J$180,D$47,物件データ!$H$5:$H$180,">0")/SUMIFS(物件データ!$G$5:$G$180,物件データ!$L$5:$L$180,1,物件データ!$B$5:$B$180,$A51,物件データ!$J$5:$J$180,D$47,物件データ!$H$5:$H$180,">0"),"") -> 0.17379679 | E51: =IFERROR(SUMIFS(物件データ!$M$5:$M$180,物件データ!$L$5:$L$180,1,物件データ!$B$5:$B$180,$A51,物件データ!$J$5:$J$180,E$47,物件データ!$H$5:$H$180,">0")/SUMIFS(物件データ!$G$5:$G$180,物件データ!$L$5:$L$180,1,物件データ!$B$5:$B$180,$A51,物件データ!$J$5:$J$180,E$47,物件データ!$H$5:$H$180,">0"),"") -> 0.13342898 | F51: =IFERROR(SUMIFS(物件データ!$M$5:$M$180,物件データ!$L$5:$L$180,1,物件データ!$B$5:$B$180,$A51,物件データ!$J$5:$J$180,F$47,物件データ!$H$5:$H$180,">0")/SUMIFS(物件データ!$G$5:$G$180,物件データ!$L$5:$L$180,1,物件データ!$B$5:$B$180,$A51,物件データ!$J$5:$J$180,F$47,物件データ!$H$5:$H$180,">0"),"") -> 0.11715481 | G51: =IFERROR(SUMIFS(物件データ!$M$5:$M$180,物件データ!$L$5:$L$180,1,物件データ!$B$5:$B$180,$A51,物件データ!$J$5:$J$180,G$47,物件データ!$H$5:$H$180,">0")/SUMIFS(物件データ!$G$5:$G$180,物件データ!$L$5:$L$180,1,物件データ!$B$5:$B$180,$A51,物件データ!$J$5:$J$180,G$47,物件データ!$H$5:$H$180,">0"),"") | H51: =IFERROR(SUMIFS(物件データ!$M$5:$M$180,物件データ!$L$5:$L$180,1,物件データ!$B$5:$B$180,$A51,物件データ!$J$5:$J$180,"?*",物件データ!$H$5:$H$180,">0")/SUMIFS(物件データ!$G$5:$G$180,物件データ!$L$5:$L$180,1,物件データ!$B$5:$B$180,$A51,物件データ!$J$5:$J$180,"?*",物件データ!$H$5:$H$180,">0"),"") -> 0.13200518
A52: 条件付き土地 | B52: =IFERROR(SUMIFS(物件データ!$M$5:$M$180,物件データ!$L$5:$L$180,1,物件データ!$B$5:$B$180,$A52,物件データ!$J$5:$J$180,B$47,物件データ!$H$5:$H$180,">0")/SUMIFS(物件データ!$G$5:$G$180,物件データ!$L$5:$L$180,1,物件データ!$B$5:$B$180,$A52,物件データ!$J$5:$J$180,B$47,物件データ!$H$5:$H$180,">0"),"") -> 0.15081135 | C52: =IFERROR(SUMIFS(物件データ!$M$5:$M$180,物件データ!$L$5:$L$180,1,物件データ!$B$5:$B$180,$A52,物件データ!$J$5:$J$180,C$47,物件データ!$H$5:$H$180,">0")/SUMIFS(物件データ!$G$5:$G$180,物件データ!$L$5:$L$180,1,物件データ!$B$5:$B$180,$A52,物件データ!$J$5:$J$180,C$47,物件データ!$H$5:$H$180,">0"),"") -> 0.26385542 | D52: =IFERROR(SUMIFS(物件データ!$M$5:$M$180,物件データ!$L$5:$L$180,1,物件データ!$B$5:$B$180,$A52,物件データ!$J$5:$J$180,D$47,物件データ!$H$5:$H$180,">0")/SUMIFS(物件データ!$G$5:$G$180,物件データ!$L$5:$L$180,1,物件データ!$B$5:$B$180,$A52,物件データ!$J$5:$J$180,D$47,物件データ!$H$5:$H$180,">0"),"") | E52: =IFERROR(SUMIFS(物件データ!$M$5:$M$180,物件データ!$L$5:$L$180,1,物件データ!$B$5:$B$180,$A52,物件データ!$J$5:$J$180,E$47,物件データ!$H$5:$H$180,">0")/SUMIFS(物件データ!$G$5:$G$180,物件データ!$L$5:$L$180,1,物件データ!$B$5:$B$180,$A52,物件データ!$J$5:$J$180,E$47,物件データ!$H$5:$H$180,">0"),"") -> 0.22213376 | F52: =IFERROR(SUMIFS(物件データ!$M$5:$M$180,物件データ!$L$5:$L$180,1,物件データ!$B$5:$B$180,$A52,物件データ!$J$5:$J$180,F$47,物件データ!$H$5:$H$180,">0")/SUMIFS(物件データ!$G$5:$G$180,物件データ!$L$5:$L$180,1,物件データ!$B$5:$B$180,$A52,物件データ!$J$5:$J$180,F$47,物件データ!$H$5:$H$180,">0"),"") | G52: =IFERROR(SUMIFS(物件データ!$M$5:$M$180,物件データ!$L$5:$L$180,1,物件データ!$B$5:$B$180,$A52,物件データ!$J$5:$J$180,G$47,物件データ!$H$5:$H$180,">0")/SUMIFS(物件データ!$G$5:$G$180,物件データ!$L$5:$L$180,1,物件データ!$B$5:$B$180,$A52,物件データ!$J$5:$J$180,G$47,物件データ!$H$5:$H$180,">0"),"") | H52: =IFERROR(SUMIFS(物件データ!$M$5:$M$180,物件データ!$L$5:$L$180,1,物件データ!$B$5:$B$180,$A52,物件データ!$J$5:$J$180,"?*",物件データ!$H$5:$H$180,">0")/SUMIFS(物件データ!$G$5:$G$180,物件データ!$L$5:$L$180,1,物件データ!$B$5:$B$180,$A52,物件データ!$J$5:$J$180,"?*",物件データ!$H$5:$H$180,">0"),"") -> 0.21336646
A53: 立ち退き後転売土地 | B53: =IFERROR(SUMIFS(物件データ!$M$5:$M$180,物件データ!$L$5:$L$180,1,物件データ!$B$5:$B$180,$A53,物件データ!$J$5:$J$180,B$47,物件データ!$H$5:$H$180,">0")/SUMIFS(物件データ!$G$5:$G$180,物件データ!$L$5:$L$180,1,物件データ!$B$5:$B$180,$A53,物件データ!$J$5:$J$180,B$47,物件データ!$H$5:$H$180,">0"),"") | C53: =IFERROR(SUMIFS(物件データ!$M$5:$M$180,物件データ!$L$5:$L$180,1,物件データ!$B$5:$B$180,$A53,物件データ!$J$5:$J$180,C$47,物件データ!$H$5:$H$180,">0")/SUMIFS(物件データ!$G$5:$G$180,物件データ!$L$5:$L$180,1,物件データ!$B$5:$B$180,$A53,物件データ!$J$5:$J$180,C$47,物件データ!$H$5:$H$180,">0"),"") | D53: =IFERROR(SUMIFS(物件データ!$M$5:$M$180,物件データ!$L$5:$L$180,1,物件データ!$B$5:$B$180,$A53,物件データ!$J$5:$J$180,D$47,物件データ!$H$5:$H$180,">0")/SUMIFS(物件データ!$G$5:$G$180,物件データ!$L$5:$L$180,1,物件データ!$B$5:$B$180,$A53,物件データ!$J$5:$J$180,D$47,物件データ!$H$5:$H$180,">0"),"") -> 0.25250501 | E53: =IFERROR(SUMIFS(物件データ!$M$5:$M$180,物件データ!$L$5:$L$180,1,物件データ!$B$5:$B$180,$A53,物件データ!$J$5:$J$180,E$47,物件データ!$H$5:$H$180,">0")/SUMIFS(物件データ!$G$5:$G$180,物件データ!$L$5:$L$180,1,物件データ!$B$5:$B$180,$A53,物件データ!$J$5:$J$180,E$47,物件データ!$H$5:$H$180,">0"),"") -> 0.15058731 | F53: =IFERROR(SUMIFS(物件データ!$M$5:$M$180,物件データ!$L$5:$L$180,1,物件データ!$B$5:$B$180,$A53,物件データ!$J$5:$J$180,F$47,物件データ!$H$5:$H$180,">0")/SUMIFS(物件データ!$G$5:$G$180,物件データ!$L$5:$L$180,1,物件データ!$B$5:$B$180,$A53,物件データ!$J$5:$J$180,F$47,物件データ!$H$5:$H$180,">0"),"") -> 0.10629758 | G53: =IFERROR(SUMIFS(物件データ!$M$5:$M$180,物件データ!$L$5:$L$180,1,物件データ!$B$5:$B$180,$A53,物件データ!$J$5:$J$180,G$47,物件データ!$H$5:$H$180,">0")/SUMIFS(物件データ!$G$5:$G$180,物件データ!$L$5:$L$180,1,物件データ!$B$5:$B$180,$A53,物件データ!$J$5:$J$180,G$47,物件データ!$H$5:$H$180,">0"),"") | H53: =IFERROR(SUMIFS(物件データ!$M$5:$M$180,物件データ!$L$5:$L$180,1,物件データ!$B$5:$B$180,$A53,物件データ!$J$5:$J$180,"?*",物件データ!$H$5:$H$180,">0")/SUMIFS(物件データ!$G$5:$G$180,物件データ!$L$5:$L$180,1,物件データ!$B$5:$B$180,$A53,物件データ!$J$5:$J$180,"?*",物件データ!$H$5:$H$180,">0"),"") -> 0.16325201
A54: 一棟収益天端 | B54: =IFERROR(SUMIFS(物件データ!$M$5:$M$180,物件データ!$L$5:$L$180,1,物件データ!$B$5:$B$180,$A54,物件データ!$J$5:$J$180,B$47,物件データ!$H$5:$H$180,">0")/SUMIFS(物件データ!$G$5:$G$180,物件データ!$L$5:$L$180,1,物件データ!$B$5:$B$180,$A54,物件データ!$J$5:$J$180,B$47,物件データ!$H$5:$H$180,">0"),"") | C54: =IFERROR(SUMIFS(物件データ!$M$5:$M$180,物件データ!$L$5:$L$180,1,物件データ!$B$5:$B$180,$A54,物件データ!$J$5:$J$180,C$47,物件データ!$H$5:$H$180,">0")/SUMIFS(物件データ!$G$5:$G$180,物件データ!$L$5:$L$180,1,物件データ!$B$5:$B$180,$A54,物件データ!$J$5:$J$180,C$47,物件データ!$H$5:$H$180,">0"),"") -> 0.19308357 | D54: =IFERROR(SUMIFS(物件データ!$M$5:$M$180,物件データ!$L$5:$L$180,1,物件データ!$B$5:$B$180,$A54,物件データ!$J$5:$J$180,D$47,物件データ!$H$5:$H$180,">0")/SUMIFS(物件データ!$G$5:$G$180,物件データ!$L$5:$L$180,1,物件データ!$B$5:$B$180,$A54,物件データ!$J$5:$J$180,D$47,物件データ!$H$5:$H$180,">0"),"") | E54: =IFERROR(SUMIFS(物件データ!$M$5:$M$180,物件データ!$L$5:$L$180,1,物件データ!$B$5:$B$180,$A54,物件データ!$J$5:$J$180,E$47,物件データ!$H$5:$H$180,">0")/SUMIFS(物件データ!$G$5:$G$180,物件データ!$L$5:$L$180,1,物件データ!$B$5:$B$180,$A54,物件データ!$J$5:$J$180,E$47,物件データ!$H$5:$H$180,">0"),"") -> 0.089090909 | F54: =IFERROR(SUMIFS(物件データ!$M$5:$M$180,物件データ!$L$5:$L$180,1,物件データ!$B$5:$B$180,$A54,物件データ!$J$5:$J$180,F$47,物件データ!$H$5:$H$180,">0")/SUMIFS(物件データ!$G$5:$G$180,物件データ!$L$5:$L$180,1,物件データ!$B$5:$B$180,$A54,物件データ!$J$5:$J$180,F$47,物件データ!$H$5:$H$180,">0"),"") -> 0.073913043 | G54: =IFERROR(SUMIFS(物件データ!$M$5:$M$180,物件データ!$L$5:$L$180,1,物件データ!$B$5:$B$180,$A54,物件データ!$J$5:$J$180,G$47,物件データ!$H$5:$H$180,">0")/SUMIFS(物件データ!$G$5:$G$180,物件データ!$L$5:$L$180,1,物件データ!$B$5:$B$180,$A54,物件データ!$J$5:$J$180,G$47,物件データ!$H$5:$H$180,">0"),"") | H54: =IFERROR(SUMIFS(物件データ!$M$5:$M$180,物件データ!$L$5:$L$180,1,物件データ!$B$5:$B$180,$A54,物件データ!$J$5:$J$180,"?*",物件データ!$H$5:$H$180,">0")/SUMIFS(物件データ!$G$5:$G$180,物件データ!$L$5:$L$180,1,物件データ!$B$5:$B$180,$A54,物件データ!$J$5:$J$180,"?*",物件データ!$H$5:$H$180,">0"),"") -> 0.11742941
A55: OC転売 | B55: =IFERROR(SUMIFS(物件データ!$M$5:$M$180,物件データ!$L$5:$L$180,1,物件データ!$B$5:$B$180,$A55,物件データ!$J$5:$J$180,B$47,物件データ!$H$5:$H$180,">0")/SUMIFS(物件データ!$G$5:$G$180,物件データ!$L$5:$L$180,1,物件データ!$B$5:$B$180,$A55,物件データ!$J$5:$J$180,B$47,物件データ!$H$5:$H$180,">0"),"") | C55: =IFERROR(SUMIFS(物件データ!$M$5:$M$180,物件データ!$L$5:$L$180,1,物件データ!$B$5:$B$180,$A55,物件データ!$J$5:$J$180,C$47,物件データ!$H$5:$H$180,">0")/SUMIFS(物件データ!$G$5:$G$180,物件データ!$L$5:$L$180,1,物件データ!$B$5:$B$180,$A55,物件データ!$J$5:$J$180,C$47,物件データ!$H$5:$H$180,">0"),"") | D55: =IFERROR(SUMIFS(物件データ!$M$5:$M$180,物件データ!$L$5:$L$180,1,物件データ!$B$5:$B$180,$A55,物件データ!$J$5:$J$180,D$47,物件データ!$H$5:$H$180,">0")/SUMIFS(物件データ!$G$5:$G$180,物件データ!$L$5:$L$180,1,物件データ!$B$5:$B$180,$A55,物件データ!$J$5:$J$180,D$47,物件データ!$H$5:$H$180,">0"),"") | E55: =IFERROR(SUMIFS(物件データ!$M$5:$M$180,物件データ!$L$5:$L$180,1,物件データ!$B$5:$B$180,$A55,物件データ!$J$5:$J$180,E$47,物件データ!$H$5:$H$180,">0")/SUMIFS(物件データ!$G$5:$G$180,物件データ!$L$5:$L$180,1,物件データ!$B$5:$B$180,$A55,物件データ!$J$5:$J$180,E$47,物件データ!$H$5:$H$180,">0"),"") -> 0.13039216 | F55: =IFERROR(SUMIFS(物件データ!$M$5:$M$180,物件データ!$L$5:$L$180,1,物件データ!$B$5:$B$180,$A55,物件データ!$J$5:$J$180,F$47,物件データ!$H$5:$H$180,">0")/SUMIFS(物件データ!$G$5:$G$180,物件データ!$L$5:$L$180,1,物件データ!$B$5:$B$180,$A55,物件データ!$J$5:$J$180,F$47,物件データ!$H$5:$H$180,">0"),"") | G55: =IFERROR(SUMIFS(物件データ!$M$5:$M$180,物件データ!$L$5:$L$180,1,物件データ!$B$5:$B$180,$A55,物件データ!$J$5:$J$180,G$47,物件データ!$H$5:$H$180,">0")/SUMIFS(物件データ!$G$5:$G$180,物件データ!$L$5:$L$180,1,物件データ!$B$5:$B$180,$A55,物件データ!$J$5:$J$180,G$47,物件データ!$H$5:$H$180,">0"),"") | H55: =IFERROR(SUMIFS(物件データ!$M$5:$M$180,物件データ!$L$5:$L$180,1,物件データ!$B$5:$B$180,$A55,物件データ!$J$5:$J$180,"?*",物件データ!$H$5:$H$180,">0")/SUMIFS(物件データ!$G$5:$G$180,物件データ!$L$5:$L$180,1,物件データ!$B$5:$B$180,$A55,物件データ!$J$5:$J$180,"?*",物件データ!$H$5:$H$180,">0"),"") -> 0.13039216
A56: JT | B56: =IFERROR(SUMIFS(物件データ!$M$5:$M$180,物件データ!$L$5:$L$180,1,物件データ!$B$5:$B$180,$A56,物件データ!$J$5:$J$180,B$47,物件データ!$H$5:$H$180,">0")/SUMIFS(物件データ!$G$5:$G$180,物件データ!$L$5:$L$180,1,物件データ!$B$5:$B$180,$A56,物件データ!$J$5:$J$180,B$47,物件データ!$H$5:$H$180,">0"),"") | C56: =IFERROR(SUMIFS(物件データ!$M$5:$M$180,物件データ!$L$5:$L$180,1,物件データ!$B$5:$B$180,$A56,物件データ!$J$5:$J$180,C$47,物件データ!$H$5:$H$180,">0")/SUMIFS(物件データ!$G$5:$G$180,物件データ!$L$5:$L$180,1,物件データ!$B$5:$B$180,$A56,物件データ!$J$5:$J$180,C$47,物件データ!$H$5:$H$180,">0"),"") | D56: =IFERROR(SUMIFS(物件データ!$M$5:$M$180,物件データ!$L$5:$L$180,1,物件データ!$B$5:$B$180,$A56,物件データ!$J$5:$J$180,D$47,物件データ!$H$5:$H$180,">0")/SUMIFS(物件データ!$G$5:$G$180,物件データ!$L$5:$L$180,1,物件データ!$B$5:$B$180,$A56,物件データ!$J$5:$J$180,D$47,物件データ!$H$5:$H$180,">0"),"") | E56: =IFERROR(SUMIFS(物件データ!$M$5:$M$180,物件データ!$L$5:$L$180,1,物件データ!$B$5:$B$180,$A56,物件データ!$J$5:$J$180,E$47,物件データ!$H$5:$H$180,">0")/SUMIFS(物件データ!$G$5:$G$180,物件データ!$L$5:$L$180,1,物件データ!$B$5:$B$180,$A56,物件データ!$J$5:$J$180,E$47,物件データ!$H$5:$H$180,">0"),"") -> 0.24296875 | F56: =IFERROR(SUMIFS(物件データ!$M$5:$M$180,物件データ!$L$5:$L$180,1,物件データ!$B$5:$B$180,$A56,物件データ!$J$5:$J$180,F$47,物件データ!$H$5:$H$180,">0")/SUMIFS(物件データ!$G$5:$G$180,物件データ!$L$5:$L$180,1,物件データ!$B$5:$B$180,$A56,物件データ!$J$5:$J$180,F$47,物件データ!$H$5:$H$180,">0"),"") | G56: =IFERROR(SUMIFS(物件データ!$M$5:$M$180,物件データ!$L$5:$L$180,1,物件データ!$B$5:$B$180,$A56,物件データ!$J$5:$J$180,G$47,物件データ!$H$5:$H$180,">0")/SUMIFS(物件データ!$G$5:$G$180,物件データ!$L$5:$L$180,1,物件データ!$B$5:$B$180,$A56,物件データ!$J$5:$J$180,G$47,物件データ!$H$5:$H$180,">0"),"") | H56: =IFERROR(SUMIFS(物件データ!$M$5:$M$180,物件データ!$L$5:$L$180,1,物件データ!$B$5:$B$180,$A56,物件データ!$J$5:$J$180,"?*",物件データ!$H$5:$H$180,">0")/SUMIFS(物件データ!$G$5:$G$180,物件データ!$L$5:$L$180,1,物件データ!$B$5:$B$180,$A56,物件データ!$J$5:$J$180,"?*",物件データ!$H$5:$H$180,">0"),"") -> 0.24296875
A57: たちのき後転売MS | B57: =IFERROR(SUMIFS(物件データ!$M$5:$M$180,物件データ!$L$5:$L$180,1,物件データ!$B$5:$B$180,$A57,物件データ!$J$5:$J$180,B$47,物件データ!$H$5:$H$180,">0")/SUMIFS(物件データ!$G$5:$G$180,物件データ!$L$5:$L$180,1,物件データ!$B$5:$B$180,$A57,物件データ!$J$5:$J$180,B$47,物件データ!$H$5:$H$180,">0"),"") | C57: =IFERROR(SUMIFS(物件データ!$M$5:$M$180,物件データ!$L$5:$L$180,1,物件データ!$B$5:$B$180,$A57,物件データ!$J$5:$J$180,C$47,物件データ!$H$5:$H$180,">0")/SUMIFS(物件データ!$G$5:$G$180,物件データ!$L$5:$L$180,1,物件データ!$B$5:$B$180,$A57,物件データ!$J$5:$J$180,C$47,物件データ!$H$5:$H$180,">0"),"") | D57: =IFERROR(SUMIFS(物件データ!$M$5:$M$180,物件データ!$L$5:$L$180,1,物件データ!$B$5:$B$180,$A57,物件データ!$J$5:$J$180,D$47,物件データ!$H$5:$H$180,">0")/SUMIFS(物件データ!$G$5:$G$180,物件データ!$L$5:$L$180,1,物件データ!$B$5:$B$180,$A57,物件データ!$J$5:$J$180,D$47,物件データ!$H$5:$H$180,">0"),"") | E57: =IFERROR(SUMIFS(物件データ!$M$5:$M$180,物件データ!$L$5:$L$180,1,物件データ!$B$5:$B$180,$A57,物件データ!$J$5:$J$180,E$47,物件データ!$H$5:$H$180,">0")/SUMIFS(物件データ!$G$5:$G$180,物件データ!$L$5:$L$180,1,物件データ!$B$5:$B$180,$A57,物件データ!$J$5:$J$180,E$47,物件データ!$H$5:$H$180,">0"),"") | F57: =IFERROR(SUMIFS(物件データ!$M$5:$M$180,物件データ!$L$5:$L$180,1,物件データ!$B$5:$B$180,$A57,物件データ!$J$5:$J$180,F$47,物件データ!$H$5:$H$180,">0")/SUMIFS(物件データ!$G$5:$G$180,物件データ!$L$5:$L$180,1,物件データ!$B$5:$B$180,$A57,物件データ!$J$5:$J$180,F$47,物件データ!$H$5:$H$180,">0"),"") -> 0.15135135 | G57: =IFERROR(SUMIFS(物件データ!$M$5:$M$180,物件データ!$L$5:$L$180,1,物件データ!$B$5:$B$180,$A57,物件データ!$J$5:$J$180,G$47,物件データ!$H$5:$H$180,">0")/SUMIFS(物件データ!$G$5:$G$180,物件データ!$L$5:$L$180,1,物件データ!$B$5:$B$180,$A57,物件データ!$J$5:$J$180,G$47,物件データ!$H$5:$H$180,">0"),"") | H57: =IFERROR(SUMIFS(物件データ!$M$5:$M$180,物件データ!$L$5:$L$180,1,物件データ!$B$5:$B$180,$A57,物件データ!$J$5:$J$180,"?*",物件データ!$H$5:$H$180,">0")/SUMIFS(物件データ!$G$5:$G$180,物件データ!$L$5:$L$180,1,物件データ!$B$5:$B$180,$A57,物件データ!$J$5:$J$180,"?*",物件データ!$H$5:$H$180,">0"),"") -> 0.15135135
A58: 合計 | B58: =IFERROR(SUMIFS(物件データ!$M$5:$M$180,物件データ!$L$5:$L$180,1,物件データ!$J$5:$J$180,B$47,物件データ!$H$5:$H$180,">0")/SUMIFS(物件データ!$G$5:$G$180,物件データ!$L$5:$L$180,1,物件データ!$J$5:$J$180,B$47,物件データ!$H$5:$H$180,">0"),"") -> 0.1709677 | C58: =IFERROR(SUMIFS(物件データ!$M$5:$M$180,物件データ!$L$5:$L$180,1,物件データ!$J$5:$J$180,C$47,物件データ!$H$5:$H$180,">0")/SUMIFS(物件データ!$G$5:$G$180,物件データ!$L$5:$L$180,1,物件データ!$J$5:$J$180,C$47,物件データ!$H$5:$H$180,">0"),"") -> 0.15035522 | D58: =IFERROR(SUMIFS(物件データ!$M$5:$M$180,物件データ!$L$5:$L$180,1,物件データ!$J$5:$J$180,D$47,物件データ!$H$5:$H$180,">0")/SUMIFS(物件データ!$G$5:$G$180,物件データ!$L$5:$L$180,1,物件データ!$J$5:$J$180,D$47,物件データ!$H$5:$H$180,">0"),"") -> 0.16986528 | E58: =IFERROR(SUMIFS(物件データ!$M$5:$M$180,物件データ!$L$5:$L$180,1,物件データ!$J$5:$J$180,E$47,物件データ!$H$5:$H$180,">0")/SUMIFS(物件データ!$G$5:$G$180,物件データ!$L$5:$L$180,1,物件データ!$J$5:$J$180,E$47,物件データ!$H$5:$H$180,">0"),"") -> 0.15414445 | F58: =IFERROR(SUMIFS(物件データ!$M$5:$M$180,物件データ!$L$5:$L$180,1,物件データ!$J$5:$J$180,F$47,物件データ!$H$5:$H$180,">0")/SUMIFS(物件データ!$G$5:$G$180,物件データ!$L$5:$L$180,1,物件データ!$J$5:$J$180,F$47,物件データ!$H$5:$H$180,">0"),"") -> 0.17850295 | G58: =IFERROR(SUMIFS(物件データ!$M$5:$M$180,物件データ!$L$5:$L$180,1,物件データ!$J$5:$J$180,G$47,物件データ!$H$5:$H$180,">0")/SUMIFS(物件データ!$G$5:$G$180,物件データ!$L$5:$L$180,1,物件データ!$J$5:$J$180,G$47,物件データ!$H$5:$H$180,">0"),"") -> 0.054603396 | H58: =IFERROR(SUMIFS(物件データ!$M$5:$M$180,物件データ!$L$5:$L$180,1,物件データ!$J$5:$J$180,"?*",物件データ!$H$5:$H$180,">0")/SUMIFS(物件データ!$G$5:$G$180,物件データ!$L$5:$L$180,1,物件データ!$J$5:$J$180,"?*",物件データ!$H$5:$H$180,">0"),"") -> 0.15809619
A60: 平均保有日数（日）
A61: 物件種別 | B61: 10期 | C61: 11期 | D61: 12期 | E61: 13期 | F61: 14期 | G61: 15期 | H61: 合計
A62: 新築戸建 | B62: =IFERROR(AVERAGEIFS(物件データ!$O$5:$O$180,物件データ!$L$5:$L$180,1,物件データ!$B$5:$B$180,$A62,物件データ!$J$5:$J$180,B$61,物件データ!$O$5:$O$180,">=0"),"") -> 311.94118 | C62: =IFERROR(AVERAGEIFS(物件データ!$O$5:$O$180,物件データ!$L$5:$L$180,1,物件データ!$B$5:$B$180,$A62,物件データ!$J$5:$J$180,C$61,物件データ!$O$5:$O$180,">=0"),"") -> 342.47059 | D62: =IFERROR(AVERAGEIFS(物件データ!$O$5:$O$180,物件データ!$L$5:$L$180,1,物件データ!$B$5:$B$180,$A62,物件データ!$J$5:$J$180,D$61,物件データ!$O$5:$O$180,">=0"),"") -> 291.5 | E62: =IFERROR(AVERAGEIFS(物件データ!$O$5:$O$180,物件データ!$L$5:$L$180,1,物件データ!$B$5:$B$180,$A62,物件データ!$J$5:$J$180,E$61,物件データ!$O$5:$O$180,">=0"),"") -> 438.07692 | F62: =IFERROR(AVERAGEIFS(物件データ!$O$5:$O$180,物件データ!$L$5:$L$180,1,物件データ!$B$5:$B$180,$A62,物件データ!$J$5:$J$180,F$61,物件データ!$O$5:$O$180,">=0"),"") -> 410.28571 | G62: =IFERROR(AVERAGEIFS(物件データ!$O$5:$O$180,物件データ!$L$5:$L$180,1,物件データ!$B$5:$B$180,$A62,物件データ!$J$5:$J$180,G$61,物件データ!$O$5:$O$180,">=0"),"") -> 342 | H62: =IFERROR(AVERAGEIFS(物件データ!$O$5:$O$180,物件データ!$L$5:$L$180,1,物件データ!$B$5:$B$180,$A62,物件データ!$J$5:$J$180,"?*",物件データ!$O$5:$O$180,">=0"),"") -> 358.7541
A63: 条件なし土地 | B63: =IFERROR(AVERAGEIFS(物件データ!$O$5:$O$180,物件データ!$L$5:$L$180,1,物件データ!$B$5:$B$180,$A63,物件データ!$J$5:$J$180,B$61,物件データ!$O$5:$O$180,">=0"),"") -> 129 | C63: =IFERROR(AVERAGEIFS(物件データ!$O$5:$O$180,物件データ!$L$5:$L$180,1,物件データ!$B$5:$B$180,$A63,物件データ!$J$5:$J$180,C$61,物件データ!$O$5:$O$180,">=0"),"") -> 216.33333 | D63: =IFERROR(AVERAGEIFS(物件データ!$O$5:$O$180,物件データ!$L$5:$L$180,1,物件データ!$B$5:$B$180,$A63,物件データ!$J$5:$J$180,D$61,物件データ!$O$5:$O$180,">=0"),"") | E63: =IFERROR(AVERAGEIFS(物件データ!$O$5:$O$180,物件データ!$L$5:$L$180,1,物件データ!$B$5:$B$180,$A63,物件データ!$J$5:$J$180,E$61,物件データ!$O$5:$O$180,">=0"),"") -> 155.5 | F63: =IFERROR(AVERAGEIFS(物件データ!$O$5:$O$180,物件データ!$L$5:$L$180,1,物件データ!$B$5:$B$180,$A63,物件データ!$J$5:$J$180,F$61,物件データ!$O$5:$O$180,">=0"),"") -> 100.8 | G63: =IFERROR(AVERAGEIFS(物件データ!$O$5:$O$180,物件データ!$L$5:$L$180,1,物件データ!$B$5:$B$180,$A63,物件データ!$J$5:$J$180,G$61,物件データ!$O$5:$O$180,">=0"),"") -> 247 | H63: =IFERROR(AVERAGEIFS(物件データ!$O$5:$O$180,物件データ!$L$5:$L$180,1,物件データ!$B$5:$B$180,$A63,物件データ!$J$5:$J$180,"?*",物件データ!$O$5:$O$180,">=0"),"") -> 144.33333
A64: MSリフォーム再販 | B64: =IFERROR(AVERAGEIFS(物件データ!$O$5:$O$180,物件データ!$L$5:$L$180,1,物件データ!$B$5:$B$180,$A64,物件データ!$J$5:$J$180,B$61,物件データ!$O$5:$O$180,">=0"),"") -> 233.5 | C64: =IFERROR(AVERAGEIFS(物件データ!$O$5:$O$180,物件データ!$L$5:$L$180,1,物件データ!$B$5:$B$180,$A64,物件データ!$J$5:$J$180,C$61,物件データ!$O$5:$O$180,">=0"),"") -> 178.2 | D64: =IFERROR(AVERAGEIFS(物件データ!$O$5:$O$180,物件データ!$L$5:$L$180,1,物件データ!$B$5:$B$180,$A64,物件データ!$J$5:$J$180,D$61,物件データ!$O$5:$O$180,">=0"),"") | E64: =IFERROR(AVERAGEIFS(物件データ!$O$5:$O$180,物件データ!$L$5:$L$180,1,物件データ!$B$5:$B$180,$A64,物件データ!$J$5:$J$180,E$61,物件データ!$O$5:$O$180,">=0"),"") -> 406 | F64: =IFERROR(AVERAGEIFS(物件データ!$O$5:$O$180,物件データ!$L$5:$L$180,1,物件データ!$B$5:$B$180,$A64,物件データ!$J$5:$J$180,F$61,物件データ!$O$5:$O$180,">=0"),"") -> 148 | G64: =IFERROR(AVERAGEIFS(物件データ!$O$5:$O$180,物件データ!$L$5:$L$180,1,物件データ!$B$5:$B$180,$A64,物件データ!$J$5:$J$180,G$61,物件データ!$O$5:$O$180,">=0"),"") -> 122 | H64: =IFERROR(AVERAGEIFS(物件データ!$O$5:$O$180,物件データ!$L$5:$L$180,1,物件データ!$B$5:$B$180,$A64,物件データ!$J$5:$J$180,"?*",物件データ!$O$5:$O$180,">=0"),"") -> 231.27778
A65: 戸建リフォーム再販 | B65: =IFERROR(AVERAGEIFS(物件データ!$O$5:$O$180,物件データ!$L$5:$L$180,1,物件データ!$B$5:$B$180,$A65,物件データ!$J$5:$J$180,B$61,物件データ!$O$5:$O$180,">=0"),"") -> 176.75 | C65: =IFERROR(AVERAGEIFS(物件データ!$O$5:$O$180,物件データ!$L$5:$L$180,1,物件データ!$B$5:$B$180,$A65,物件データ!$J$5:$J$180,C$61,物件データ!$O$5:$O$180,">=0"),"") -> 234.66667 | D65: =IFERROR(AVERAGEIFS(物件データ!$O$5:$O$180,物件データ!$L$5:$L$180,1,物件データ!$B$5:$B$180,$A65,物件データ!$J$5:$J$180,D$61,物件データ!$O$5:$O$180,">=0"),"") -> 122 | E65: =IFERROR(AVERAGEIFS(物件データ!$O$5:$O$180,物件データ!$L$5:$L$180,1,物件データ!$B$5:$B$180,$A65,物件データ!$J$5:$J$180,E$61,物件データ!$O$5:$O$180,">=0"),"") -> 107.66667 | F65: =IFERROR(AVERAGEIFS(物件データ!$O$5:$O$180,物件データ!$L$5:$L$180,1,物件データ!$B$5:$B$180,$A65,物件データ!$J$5:$J$180,F$61,物件データ!$O$5:$O$180,">=0"),"") -> 248.66667 | G65: =IFERROR(AVERAGEIFS(物件データ!$O$5:$O$180,物件データ!$L$5:$L$180,1,物件データ!$B$5:$B$180,$A65,物件データ!$J$5:$J$180,G$61,物件データ!$O$5:$O$180,">=0"),"") | H65: =IFERROR(AVERAGEIFS(物件データ!$O$5:$O$180,物件データ!$L$5:$L$180,1,物件データ!$B$5:$B$180,$A65,物件データ!$J$5:$J$180,"?*",物件データ!$O$5:$O$180,">=0"),"") -> 185.85714
A66: 条件付き土地 | B66: =IFERROR(AVERAGEIFS(物件データ!$O$5:$O$180,物件データ!$L$5:$L$180,1,物件データ!$B$5:$B$180,$A66,物件データ!$J$5:$J$180,B$61,物件データ!$O$5:$O$180,">=0"),"") -> 214 | C66: =IFERROR(AVERAGEIFS(物件データ!$O$5:$O$180,物件データ!$L$5:$L$180,1,物件データ!$B$5:$B$180,$A66,物件データ!$J$5:$J$180,C$61,物件データ!$O$5:$O$180,">=0"),"") -> 427 | D66: =IFERROR(AVERAGEIFS(物件データ!$O$5:$O$180,物件データ!$L$5:$L$180,1,物件データ!$B$5:$B$180,$A66,物件データ!$J$5:$J$180,D$61,物件データ!$O$5:$O$180,">=0"),"") | E66: =IFERROR(AVERAGEIFS(物件データ!$O$5:$O$180,物件データ!$L$5:$L$180,1,物件データ!$B$5:$B$180,$A66,物件データ!$J$5:$J$180,E$61,物件データ!$O$5:$O$180,">=0"),"") -> 91.666667 | F66: =IFERROR(AVERAGEIFS(物件データ!$O$5:$O$180,物件データ!$L$5:$L$180,1,物件データ!$B$5:$B$180,$A66,物件データ!$J$5:$J$180,F$61,物件データ!$O$5:$O$180,">=0"),"") | G66: =IFERROR(AVERAGEIFS(物件データ!$O$5:$O$180,物件データ!$L$5:$L$180,1,物件データ!$B$5:$B$180,$A66,物件データ!$J$5:$J$180,G$61,物件データ!$O$5:$O$180,">=0"),"") | H66: =IFERROR(AVERAGEIFS(物件データ!$O$5:$O$180,物件データ!$L$5:$L$180,1,物件データ!$B$5:$B$180,$A66,物件データ!$J$5:$J$180,"?*",物件データ!$O$5:$O$180,">=0"),"") -> 188.33333
A67: 立ち退き後転売土地 | B67: =IFERROR(AVERAGEIFS(物件データ!$O$5:$O$180,物件データ!$L$5:$L$180,1,物件データ!$B$5:$B$180,$A67,物件データ!$J$5:$J$180,B$61,物件データ!$O$5:$O$180,">=0"),"") | C67: =IFERROR(AVERAGEIFS(物件データ!$O$5:$O$180,物件データ!$L$5:$L$180,1,物件データ!$B$5:$B$180,$A67,物件データ!$J$5:$J$180,C$61,物件データ!$O$5:$O$180,">=0"),"") | D67: =IFERROR(AVERAGEIFS(物件データ!$O$5:$O$180,物件データ!$L$5:$L$180,1,物件データ!$B$5:$B$180,$A67,物件データ!$J$5:$J$180,D$61,物件データ!$O$5:$O$180,">=0"),"") -> 253 | E67: =IFERROR(AVERAGEIFS(物件データ!$O$5:$O$180,物件データ!$L$5:$L$180,1,物件データ!$B$5:$B$180,$A67,物件データ!$J$5:$J$180,E$61,物件データ!$O$5:$O$180,">=0"),"") -> 281.66667 | F67: =IFERROR(AVERAGEIFS(物件データ!$O$5:$O$180,物件データ!$L$5:$L$180,1,物件データ!$B$5:$B$180,$A67,物件データ!$J$5:$J$180,F$61,物件データ!$O$5:$O$180,">=0"),"") -> 752 | G67: =IFERROR(AVERAGEIFS(物件データ!$O$5:$O$180,物件データ!$L$5:$L$180,1,物件データ!$B$5:$B$180,$A67,物件データ!$J$5:$J$180,G$61,物件データ!$O$5:$O$180,">=0"),"") | H67: =IFERROR(AVERAGEIFS(物件データ!$O$5:$O$180,物件データ!$L$5:$L$180,1,物件データ!$B$5:$B$180,$A67,物件データ!$J$5:$J$180,"?*",物件データ!$O$5:$O$180,">=0"),"") -> 370
A68: 一棟収益天端 | B68: =IFERROR(AVERAGEIFS(物件データ!$O$5:$O$180,物件データ!$L$5:$L$180,1,物件データ!$B$5:$B$180,$A68,物件データ!$J$5:$J$180,B$61,物件データ!$O$5:$O$180,">=0"),"") | C68: =IFERROR(AVERAGEIFS(物件データ!$O$5:$O$180,物件データ!$L$5:$L$180,1,物件データ!$B$5:$B$180,$A68,物件データ!$J$5:$J$180,C$61,物件データ!$O$5:$O$180,">=0"),"") -> 240 | D68: =IFERROR(AVERAGEIFS(物件データ!$O$5:$O$180,物件データ!$L$5:$L$180,1,物件データ!$B$5:$B$180,$A68,物件データ!$J$5:$J$180,D$61,物件データ!$O$5:$O$180,">=0"),"") | E68: =IFERROR(AVERAGEIFS(物件データ!$O$5:$O$180,物件データ!$L$5:$L$180,1,物件データ!$B$5:$B$180,$A68,物件データ!$J$5:$J$180,E$61,物件データ!$O$5:$O$180,">=0"),"") -> 0 | F68: =IFERROR(AVERAGEIFS(物件データ!$O$5:$O$180,物件データ!$L$5:$L$180,1,物件データ!$B$5:$B$180,$A68,物件データ!$J$5:$J$180,F$61,物件データ!$O$5:$O$180,">=0"),"") -> 422 | G68: =IFERROR(AVERAGEIFS(物件データ!$O$5:$O$180,物件データ!$L$5:$L$180,1,物件データ!$B$5:$B$180,$A68,物件データ!$J$5:$J$180,G$61,物件データ!$O$5:$O$180,">=0"),"") | H68: =IFERROR(AVERAGEIFS(物件データ!$O$5:$O$180,物件データ!$L$5:$L$180,1,物件データ!$B$5:$B$180,$A68,物件データ!$J$5:$J$180,"?*",物件データ!$O$5:$O$180,">=0"),"") -> 225.5
A69: OC転売 | B69: =IFERROR(AVERAGEIFS(物件データ!$O$5:$O$180,物件データ!$L$5:$L$180,1,物件データ!$B$5:$B$180,$A69,物件データ!$J$5:$J$180,B$61,物件データ!$O$5:$O$180,">=0"),"") | C69: =IFERROR(AVERAGEIFS(物件データ!$O$5:$O$180,物件データ!$L$5:$L$180,1,物件データ!$B$5:$B$180,$A69,物件データ!$J$5:$J$180,C$61,物件データ!$O$5:$O$180,">=0"),"") -> 472 | D69: =IFERROR(AVERAGEIFS(物件データ!$O$5:$O$180,物件データ!$L$5:$L$180,1,物件データ!$B$5:$B$180,$A69,物件データ!$J$5:$J$180,D$61,物件データ!$O$5:$O$180,">=0"),"") | E69: =IFERROR(AVERAGEIFS(物件データ!$O$5:$O$180,物件データ!$L$5:$L$180,1,物件データ!$B$5:$B$180,$A69,物件データ!$J$5:$J$180,E$61,物件データ!$O$5:$O$180,">=0"),"") -> 28 | F69: =IFERROR(AVERAGEIFS(物件データ!$O$5:$O$180,物件データ!$L$5:$L$180,1,物件データ!$B$5:$B$180,$A69,物件データ!$J$5:$J$180,F$61,物件データ!$O$5:$O$180,">=0"),"") | G69: =IFERROR(AVERAGEIFS(物件データ!$O$5:$O$180,物件データ!$L$5:$L$180,1,物件データ!$B$5:$B$180,$A69,物件データ!$J$5:$J$180,G$61,物件データ!$O$5:$O$180,">=0"),"") | H69: =IFERROR(AVERAGEIFS(物件データ!$O$5:$O$180,物件データ!$L$5:$L$180,1,物件データ!$B$5:$B$180,$A69,物件データ!$J$5:$J$180,"?*",物件データ!$O$5:$O$180,">=0"),"") -> 250
A70: JT | B70: =IFERROR(AVERAGEIFS(物件データ!$O$5:$O$180,物件データ!$L$5:$L$180,1,物件データ!$B$5:$B$180,$A70,物件データ!$J$5:$J$180,B$61,物件データ!$O$5:$O$180,">=0"),"") | C70: =IFERROR(AVERAGEIFS(物件データ!$O$5:$O$180,物件データ!$L$5:$L$180,1,物件データ!$B$5:$B$180,$A70,物件データ!$J$5:$J$180,C$61,物件データ!$O$5:$O$180,">=0"),"") | D70: =IFERROR(AVERAGEIFS(物件データ!$O$5:$O$180,物件データ!$L$5:$L$180,1,物件データ!$B$5:$B$180,$A70,物件データ!$J$5:$J$180,D$61,物件データ!$O$5:$O$180,">=0"),"") | E70: =IFERROR(AVERAGEIFS(物件データ!$O$5:$O$180,物件データ!$L$5:$L$180,1,物件データ!$B$5:$B$180,$A70,物件データ!$J$5:$J$180,E$61,物件データ!$O$5:$O$180,">=0"),"") -> 446 | F70: =IFERROR(AVERAGEIFS(物件データ!$O$5:$O$180,物件データ!$L$5:$L$180,1,物件データ!$B$5:$B$180,$A70,物件データ!$J$5:$J$180,F$61,物件データ!$O$5:$O$180,">=0"),"") | G70: =IFERROR(AVERAGEIFS(物件データ!$O$5:$O$180,物件データ!$L$5:$L$180,1,物件データ!$B$5:$B$180,$A70,物件データ!$J$5:$J$180,G$61,物件データ!$O$5:$O$180,">=0"),"") | H70: =IFERROR(AVERAGEIFS(物件データ!$O$5:$O$180,物件データ!$L$5:$L$180,1,物件データ!$B$5:$B$180,$A70,物件データ!$J$5:$J$180,"?*",物件データ!$O$5:$O$180,">=0"),"") -> 446
A71: たちのき後転売MS | B71: =IFERROR(AVERAGEIFS(物件データ!$O$5:$O$180,物件データ!$L$5:$L$180,1,物件データ!$B$5:$B$180,$A71,物件データ!$J$5:$J$180,B$61,物件データ!$O$5:$O$180,">=0"),"") | C71: =IFERROR(AVERAGEIFS(物件データ!$O$5:$O$180,物件データ!$L$5:$L$180,1,物件データ!$B$5:$B$180,$A71,物件データ!$J$5:$J$180,C$61,物件データ!$O$5:$O$180,">=0"),"") | D71: =IFERROR(AVERAGEIFS(物件データ!$O$5:$O$180,物件データ!$L$5:$L$180,1,物件データ!$B$5:$B$180,$A71,物件データ!$J$5:$J$180,D$61,物件データ!$O$5:$O$180,">=0"),"") | E71: =IFERROR(AVERAGEIFS(物件データ!$O$5:$O$180,物件データ!$L$5:$L$180,1,物件データ!$B$5:$B$180,$A71,物件データ!$J$5:$J$180,E$61,物件データ!$O$5:$O$180,">=0"),"") | F71: =IFERROR(AVERAGEIFS(物件データ!$O$5:$O$180,物件データ!$L$5:$L$180,1,物件データ!$B$5:$B$180,$A71,物件データ!$J$5:$J$180,F$61,物件データ!$O$5:$O$180,">=0"),"") -> 362 | G71: =IFERROR(AVERAGEIFS(物件データ!$O$5:$O$180,物件データ!$L$5:$L$180,1,物件データ!$B$5:$B$180,$A71,物件データ!$J$5:$J$180,G$61,物件データ!$O$5:$O$180,">=0"),"") | H71: =IFERROR(AVERAGEIFS(物件データ!$O$5:$O$180,物件データ!$L$5:$L$180,1,物件データ!$B$5:$B$180,$A71,物件データ!$J$5:$J$180,"?*",物件データ!$O$5:$O$180,">=0"),"") -> 362
A72: 合計 | B72: =IFERROR(AVERAGEIFS(物件データ!$O$5:$O$180,物件データ!$L$5:$L$180,1,物件データ!$J$5:$J$180,B$61,物件データ!$O$5:$O$180,">=0"),"") -> 263.10345 | C72: =IFERROR(AVERAGEIFS(物件データ!$O$5:$O$180,物件データ!$L$5:$L$180,1,物件データ!$J$5:$J$180,C$61,物件データ!$O$5:$O$180,">=0"),"") -> 295.15625 | D72: =IFERROR(AVERAGEIFS(物件データ!$O$5:$O$180,物件データ!$L$5:$L$180,1,物件データ!$J$5:$J$180,D$61,物件データ!$O$5:$O$180,">=0"),"") -> 256.83333 | E72: =IFERROR(AVERAGEIFS(物件データ!$O$5:$O$180,物件データ!$L$5:$L$180,1,物件データ!$J$5:$J$180,E$61,物件データ!$O$5:$O$180,">=0"),"") -> 298.72727 | F72: =IFERROR(AVERAGEIFS(物件データ!$O$5:$O$180,物件データ!$L$5:$L$180,1,物件データ!$J$5:$J$180,F$61,物件データ!$O$5:$O$180,">=0"),"") -> 250.14815 | G72: =IFERROR(AVERAGEIFS(物件データ!$O$5:$O$180,物件データ!$L$5:$L$180,1,物件データ!$J$5:$J$180,G$61,物件データ!$O$5:$O$180,">=0"),"") -> 273.66667 | H72: =IFERROR(AVERAGEIFS(物件データ!$O$5:$O$180,物件データ!$L$5:$L$180,1,物件データ!$J$5:$J$180,"?*",物件データ!$O$5:$O$180,">=0"),"") -> 277.21805
A74: 参考：原価未入力で粗利対象外の棟数
A75: 物件種別 | B75: 10期 | C75: 11期 | D75: 12期 | E75: 13期 | F75: 14期 | G75: 15期 | H75: 合計
A76: 新築戸建 | B76: =COUNTIFS(物件データ!$L$5:$L$180,1,物件データ!$B$5:$B$180,$A76,物件データ!$J$5:$J$180,B$75)-COUNTIFS(物件データ!$L$5:$L$180,1,物件データ!$B$5:$B$180,$A76,物件データ!$J$5:$J$180,B$75,物件データ!$H$5:$H$180,">0") -> 17 | C76: =COUNTIFS(物件データ!$L$5:$L$180,1,物件データ!$B$5:$B$180,$A76,物件データ!$J$5:$J$180,C$75)-COUNTIFS(物件データ!$L$5:$L$180,1,物件データ!$B$5:$B$180,$A76,物件データ!$J$5:$J$180,C$75,物件データ!$H$5:$H$180,">0") -> 2 | D76: =COUNTIFS(物件データ!$L$5:$L$180,1,物件データ!$B$5:$B$180,$A76,物件データ!$J$5:$J$180,D$75)-COUNTIFS(物件データ!$L$5:$L$180,1,物件データ!$B$5:$B$180,$A76,物件データ!$J$5:$J$180,D$75,物件データ!$H$5:$H$180,">0") -> 0 | E76: =COUNTIFS(物件データ!$L$5:$L$180,1,物件データ!$B$5:$B$180,$A76,物件データ!$J$5:$J$180,E$75)-COUNTIFS(物件データ!$L$5:$L$180,1,物件データ!$B$5:$B$180,$A76,物件データ!$J$5:$J$180,E$75,物件データ!$H$5:$H$180,">0") -> 1 | F76: =COUNTIFS(物件データ!$L$5:$L$180,1,物件データ!$B$5:$B$180,$A76,物件データ!$J$5:$J$180,F$75)-COUNTIFS(物件データ!$L$5:$L$180,1,物件データ!$B$5:$B$180,$A76,物件データ!$J$5:$J$180,F$75,物件データ!$H$5:$H$180,">0") -> 0 | G76: =COUNTIFS(物件データ!$L$5:$L$180,1,物件データ!$B$5:$B$180,$A76,物件データ!$J$5:$J$180,G$75)-COUNTIFS(物件データ!$L$5:$L$180,1,物件データ!$B$5:$B$180,$A76,物件データ!$J$5:$J$180,G$75,物件データ!$H$5:$H$180,">0") -> 0 | H76: =COUNTIFS(物件データ!$L$5:$L$180,1,物件データ!$B$5:$B$180,$A76,物件データ!$J$5:$J$180,"?*")-COUNTIFS(物件データ!$L$5:$L$180,1,物件データ!$B$5:$B$180,$A76,物件データ!$J$5:$J$180,"?*",物件データ!$H$5:$H$180,">0") -> 20
A77: 条件なし土地 | B77: =COUNTIFS(物件データ!$L$5:$L$180,1,物件データ!$B$5:$B$180,$A77,物件データ!$J$5:$J$180,B$75)-COUNTIFS(物件データ!$L$5:$L$180,1,物件データ!$B$5:$B$180,$A77,物件データ!$J$5:$J$180,B$75,物件データ!$H$5:$H$180,">0") -> 1 | C77: =COUNTIFS(物件データ!$L$5:$L$180,1,物件データ!$B$5:$B$180,$A77,物件データ!$J$5:$J$180,C$75)-COUNTIFS(物件データ!$L$5:$L$180,1,物件データ!$B$5:$B$180,$A77,物件データ!$J$5:$J$180,C$75,物件データ!$H$5:$H$180,">0") -> 1 | D77: =COUNTIFS(物件データ!$L$5:$L$180,1,物件データ!$B$5:$B$180,$A77,物件データ!$J$5:$J$180,D$75)-COUNTIFS(物件データ!$L$5:$L$180,1,物件データ!$B$5:$B$180,$A77,物件データ!$J$5:$J$180,D$75,物件データ!$H$5:$H$180,">0") -> 0 | E77: =COUNTIFS(物件データ!$L$5:$L$180,1,物件データ!$B$5:$B$180,$A77,物件データ!$J$5:$J$180,E$75)-COUNTIFS(物件データ!$L$5:$L$180,1,物件データ!$B$5:$B$180,$A77,物件データ!$J$5:$J$180,E$75,物件データ!$H$5:$H$180,">0") -> 0 | F77: =COUNTIFS(物件データ!$L$5:$L$180,1,物件データ!$B$5:$B$180,$A77,物件データ!$J$5:$J$180,F$75)-COUNTIFS(物件データ!$L$5:$L$180,1,物件データ!$B$5:$B$180,$A77,物件データ!$J$5:$J$180,F$75,物件データ!$H$5:$H$180,">0") -> 0 | G77: =COUNTIFS(物件データ!$L$5:$L$180,1,物件データ!$B$5:$B$180,$A77,物件データ!$J$5:$J$180,G$75)-COUNTIFS(物件データ!$L$5:$L$180,1,物件データ!$B$5:$B$180,$A77,物件データ!$J$5:$J$180,G$75,物件データ!$H$5:$H$180,">0") -> 0 | H77: =COUNTIFS(物件データ!$L$5:$L$180,1,物件データ!$B$5:$B$180,$A77,物件データ!$J$5:$J$180,"?*")-COUNTIFS(物件データ!$L$5:$L$180,1,物件データ!$B$5:$B$180,$A77,物件データ!$J$5:$J$180,"?*",物件データ!$H$5:$H$180,">0") -> 2
A78: MSリフォーム再販 | B78: =COUNTIFS(物件データ!$L$5:$L$180,1,物件データ!$B$5:$B$180,$A78,物件データ!$J$5:$J$180,B$75)-COUNTIFS(物件データ!$L$5:$L$180,1,物件データ!$B$5:$B$180,$A78,物件データ!$J$5:$J$180,B$75,物件データ!$H$5:$H$180,">0") -> 5 | C78: =COUNTIFS(物件データ!$L$5:$L$180,1,物件データ!$B$5:$B$180,$A78,物件データ!$J$5:$J$180,C$75)-COUNTIFS(物件データ!$L$5:$L$180,1,物件データ!$B$5:$B$180,$A78,物件データ!$J$5:$J$180,C$75,物件データ!$H$5:$H$180,">0") -> 0 | D78: =COUNTIFS(物件データ!$L$5:$L$180,1,物件データ!$B$5:$B$180,$A78,物件データ!$J$5:$J$180,D$75)-COUNTIFS(物件データ!$L$5:$L$180,1,物件データ!$B$5:$B$180,$A78,物件データ!$J$5:$J$180,D$75,物件データ!$H$5:$H$180,">0") -> 0 | E78: =COUNTIFS(物件データ!$L$5:$L$180,1,物件データ!$B$5:$B$180,$A78,物件データ!$J$5:$J$180,E$75)-COUNTIFS(物件データ!$L$5:$L$180,1,物件データ!$B$5:$B$180,$A78,物件データ!$J$5:$J$180,E$75,物件データ!$H$5:$H$180,">0") -> 1 | F78: =COUNTIFS(物件データ!$L$5:$L$180,1,物件データ!$B$5:$B$180,$A78,物件データ!$J$5:$J$180,F$75)-COUNTIFS(物件データ!$L$5:$L$180,1,物件データ!$B$5:$B$180,$A78,物件データ!$J$5:$J$180,F$75,物件データ!$H$5:$H$180,">0") -> 1 | G78: =COUNTIFS(物件データ!$L$5:$L$180,1,物件データ!$B$5:$B$180,$A78,物件データ!$J$5:$J$180,G$75)-COUNTIFS(物件データ!$L$5:$L$180,1,物件データ!$B$5:$B$180,$A78,物件データ!$J$5:$J$180,G$75,物件データ!$H$5:$H$180,">0") -> 0 | H78: =COUNTIFS(物件データ!$L$5:$L$180,1,物件データ!$B$5:$B$180,$A78,物件データ!$J$5:$J$180,"?*")-COUNTIFS(物件データ!$L$5:$L$180,1,物件データ!$B$5:$B$180,$A78,物件データ!$J$5:$J$180,"?*",物件データ!$H$5:$H$180,">0") -> 7
A79: 戸建リフォーム再販 | B79: =COUNTIFS(物件データ!$L$5:$L$180,1,物件データ!$B$5:$B$180,$A79,物件データ!$J$5:$J$180,B$75)-COUNTIFS(物件データ!$L$5:$L$180,1,物件データ!$B$5:$B$180,$A79,物件データ!$J$5:$J$180,B$75,物件データ!$H$5:$H$180,">0") -> 3 | C79: =COUNTIFS(物件データ!$L$5:$L$180,1,物件データ!$B$5:$B$180,$A79,物件データ!$J$5:$J$180,C$75)-COUNTIFS(物件データ!$L$5:$L$180,1,物件データ!$B$5:$B$180,$A79,物件データ!$J$5:$J$180,C$75,物件データ!$H$5:$H$180,">0") -> 0 | D79: =COUNTIFS(物件データ!$L$5:$L$180,1,物件データ!$B$5:$B$180,$A79,物件データ!$J$5:$J$180,D$75)-COUNTIFS(物件データ!$L$5:$L$180,1,物件データ!$B$5:$B$180,$A79,物件データ!$J$5:$J$180,D$75,物件データ!$H$5:$H$180,">0") -> 0 | E79: =COUNTIFS(物件データ!$L$5:$L$180,1,物件データ!$B$5:$B$180,$A79,物件データ!$J$5:$J$180,E$75)-COUNTIFS(物件データ!$L$5:$L$180,1,物件データ!$B$5:$B$180,$A79,物件データ!$J$5:$J$180,E$75,物件データ!$H$5:$H$180,">0") -> 0 | F79: =COUNTIFS(物件データ!$L$5:$L$180,1,物件データ!$B$5:$B$180,$A79,物件データ!$J$5:$J$180,F$75)-COUNTIFS(物件データ!$L$5:$L$180,1,物件データ!$B$5:$B$180,$A79,物件データ!$J$5:$J$180,F$75,物件データ!$H$5:$H$180,">0") -> 0 | G79: =COUNTIFS(物件データ!$L$5:$L$180,1,物件データ!$B$5:$B$180,$A79,物件データ!$J$5:$J$180,G$75)-COUNTIFS(物件データ!$L$5:$L$180,1,物件データ!$B$5:$B$180,$A79,物件データ!$J$5:$J$180,G$75,物件データ!$H$5:$H$180,">0") -> 0 | H79: =COUNTIFS(物件データ!$L$5:$L$180,1,物件データ!$B$5:$B$180,$A79,物件データ!$J$5:$J$180,"?*")-COUNTIFS(物件データ!$L$5:$L$180,1,物件データ!$B$5:$B$180,$A79,物件データ!$J$5:$J$180,"?*",物件データ!$H$5:$H$180,">0") -> 3
A80: 条件付き土地 | B80: =COUNTIFS(物件データ!$L$5:$L$180,1,物件データ!$B$5:$B$180,$A80,物件データ!$J$5:$J$180,B$75)-COUNTIFS(物件データ!$L$5:$L$180,1,物件データ!$B$5:$B$180,$A80,物件データ!$J$5:$J$180,B$75,物件データ!$H$5:$H$180,">0") -> 1 | C80: =COUNTIFS(物件データ!$L$5:$L$180,1,物件データ!$B$5:$B$180,$A80,物件データ!$J$5:$J$180,C$75)-COUNTIFS(物件データ!$L$5:$L$180,1,物件データ!$B$5:$B$180,$A80,物件データ!$J$5:$J$180,C$75,物件データ!$H$5:$H$180,">0") -> 0 | D80: =COUNTIFS(物件データ!$L$5:$L$180,1,物件データ!$B$5:$B$180,$A80,物件データ!$J$5:$J$180,D$75)-COUNTIFS(物件データ!$L$5:$L$180,1,物件データ!$B$5:$B$180,$A80,物件データ!$J$5:$J$180,D$75,物件データ!$H$5:$H$180,">0") -> 0 | E80: =COUNTIFS(物件データ!$L$5:$L$180,1,物件データ!$B$5:$B$180,$A80,物件データ!$J$5:$J$180,E$75)-COUNTIFS(物件データ!$L$5:$L$180,1,物件データ!$B$5:$B$180,$A80,物件データ!$J$5:$J$180,E$75,物件データ!$H$5:$H$180,">0") -> 0 | F80: =COUNTIFS(物件データ!$L$5:$L$180,1,物件データ!$B$5:$B$180,$A80,物件データ!$J$5:$J$180,F$75)-COUNTIFS(物件データ!$L$5:$L$180,1,物件データ!$B$5:$B$180,$A80,物件データ!$J$5:$J$180,F$75,物件データ!$H$5:$H$180,">0") -> 0 | G80: =COUNTIFS(物件データ!$L$5:$L$180,1,物件データ!$B$5:$B$180,$A80,物件データ!$J$5:$J$180,G$75)-COUNTIFS(物件データ!$L$5:$L$180,1,物件データ!$B$5:$B$180,$A80,物件データ!$J$5:$J$180,G$75,物件データ!$H$5:$H$180,">0") -> 0 | H80: =COUNTIFS(物件データ!$L$5:$L$180,1,物件データ!$B$5:$B$180,$A80,物件データ!$J$5:$J$180,"?*")-COUNTIFS(物件データ!$L$5:$L$180,1,物件データ!$B$5:$B$180,$A80,物件データ!$J$5:$J$180,"?*",物件データ!$H$5:$H$180,">0") -> 1
A81: 立ち退き後転売土地 | B81: =COUNTIFS(物件データ!$L$5:$L$180,1,物件データ!$B$5:$B$180,$A81,物件データ!$J$5:$J$180,B$75)-COUNTIFS(物件データ!$L$5:$L$180,1,物件データ!$B$5:$B$180,$A81,物件データ!$J$5:$J$180,B$75,物件データ!$H$5:$H$180,">0") -> 0 | C81: =COUNTIFS(物件データ!$L$5:$L$180,1,物件データ!$B$5:$B$180,$A81,物件データ!$J$5:$J$180,C$75)-COUNTIFS(物件データ!$L$5:$L$180,1,物件データ!$B$5:$B$180,$A81,物件データ!$J$5:$J$180,C$75,物件データ!$H$5:$H$180,">0") -> 0 | D81: =COUNTIFS(物件データ!$L$5:$L$180,1,物件データ!$B$5:$B$180,$A81,物件データ!$J$5:$J$180,D$75)-COUNTIFS(物件データ!$L$5:$L$180,1,物件データ!$B$5:$B$180,$A81,物件データ!$J$5:$J$180,D$75,物件データ!$H$5:$H$180,">0") -> 0 | E81: =COUNTIFS(物件データ!$L$5:$L$180,1,物件データ!$B$5:$B$180,$A81,物件データ!$J$5:$J$180,E$75)-COUNTIFS(物件データ!$L$5:$L$180,1,物件データ!$B$5:$B$180,$A81,物件データ!$J$5:$J$180,E$75,物件データ!$H$5:$H$180,">0") -> 0 | F81: =COUNTIFS(物件データ!$L$5:$L$180,1,物件データ!$B$5:$B$180,$A81,物件データ!$J$5:$J$180,F$75)-COUNTIFS(物件データ!$L$5:$L$180,1,物件データ!$B$5:$B$180,$A81,物件データ!$J$5:$J$180,F$75,物件データ!$H$5:$H$180,">0") -> 0 | G81: =COUNTIFS(物件データ!$L$5:$L$180,1,物件データ!$B$5:$B$180,$A81,物件データ!$J$5:$J$180,G$75)-COUNTIFS(物件データ!$L$5:$L$180,1,物件データ!$B$5:$B$180,$A81,物件データ!$J$5:$J$180,G$75,物件データ!$H$5:$H$180,">0") -> 0 | H81: =COUNTIFS(物件データ!$L$5:$L$180,1,物件データ!$B$5:$B$180,$A81,物件データ!$J$5:$J$180,"?*")-COUNTIFS(物件データ!$L$5:$L$180,1,物件データ!$B$5:$B$180,$A81,物件データ!$J$5:$J$180,"?*",物件データ!$H$5:$H$180,">0") -> 0
A82: 一棟収益天端 | B82: =COUNTIFS(物件データ!$L$5:$L$180,1,物件データ!$B$5:$B$180,$A82,物件データ!$J$5:$J$180,B$75)-COUNTIFS(物件データ!$L$5:$L$180,1,物件データ!$B$5:$B$180,$A82,物件データ!$J$5:$J$180,B$75,物件データ!$H$5:$H$180,">0") -> 0 | C82: =COUNTIFS(物件データ!$L$5:$L$180,1,物件データ!$B$5:$B$180,$A82,物件データ!$J$5:$J$180,C$75)-COUNTIFS(物件データ!$L$5:$L$180,1,物件データ!$B$5:$B$180,$A82,物件データ!$J$5:$J$180,C$75,物件データ!$H$5:$H$180,">0") -> 0 | D82: =COUNTIFS(物件データ!$L$5:$L$180,1,物件データ!$B$5:$B$180,$A82,物件データ!$J$5:$J$180,D$75)-COUNTIFS(物件データ!$L$5:$L$180,1,物件データ!$B$5:$B$180,$A82,物件データ!$J$5:$J$180,D$75,物件データ!$H$5:$H$180,">0") -> 0 | E82: =COUNTIFS(物件データ!$L$5:$L$180,1,物件データ!$B$5:$B$180,$A82,物件データ!$J$5:$J$180,E$75)-COUNTIFS(物件データ!$L$5:$L$180,1,物件データ!$B$5:$B$180,$A82,物件データ!$J$5:$J$180,E$75,物件データ!$H$5:$H$180,">0") -> 0 | F82: =COUNTIFS(物件データ!$L$5:$L$180,1,物件データ!$B$5:$B$180,$A82,物件データ!$J$5:$J$180,F$75)-COUNTIFS(物件データ!$L$5:$L$180,1,物件データ!$B$5:$B$180,$A82,物件データ!$J$5:$J$180,F$75,物件データ!$H$5:$H$180,">0") -> 0 | G82: =COUNTIFS(物件データ!$L$5:$L$180,1,物件データ!$B$5:$B$180,$A82,物件データ!$J$5:$J$180,G$75)-COUNTIFS(物件データ!$L$5:$L$180,1,物件データ!$B$5:$B$180,$A82,物件データ!$J$5:$J$180,G$75,物件データ!$H$5:$H$180,">0") -> 0 | H82: =COUNTIFS(物件データ!$L$5:$L$180,1,物件データ!$B$5:$B$180,$A82,物件データ!$J$5:$J$180,"?*")-COUNTIFS(物件データ!$L$5:$L$180,1,物件データ!$B$5:$B$180,$A82,物件データ!$J$5:$J$180,"?*",物件データ!$H$5:$H$180,">0") -> 0
A83: OC転売 | B83: =COUNTIFS(物件データ!$L$5:$L$180,1,物件データ!$B$5:$B$180,$A83,物件データ!$J$5:$J$180,B$75)-COUNTIFS(物件データ!$L$5:$L$180,1,物件データ!$B$5:$B$180,$A83,物件データ!$J$5:$J$180,B$75,物件データ!$H$5:$H$180,">0") -> 0 | C83: =COUNTIFS(物件データ!$L$5:$L$180,1,物件データ!$B$5:$B$180,$A83,物件データ!$J$5:$J$180,C$75)-COUNTIFS(物件データ!$L$5:$L$180,1,物件データ!$B$5:$B$180,$A83,物件データ!$J$5:$J$180,C$75,物件データ!$H$5:$H$180,">0") -> 1 | D83: =COUNTIFS(物件データ!$L$5:$L$180,1,物件データ!$B$5:$B$180,$A83,物件データ!$J$5:$J$180,D$75)-COUNTIFS(物件データ!$L$5:$L$180,1,物件データ!$B$5:$B$180,$A83,物件データ!$J$5:$J$180,D$75,物件データ!$H$5:$H$180,">0") -> 0 | E83: =COUNTIFS(物件データ!$L$5:$L$180,1,物件データ!$B$5:$B$180,$A83,物件データ!$J$5:$J$180,E$75)-COUNTIFS(物件データ!$L$5:$L$180,1,物件データ!$B$5:$B$180,$A83,物件データ!$J$5:$J$180,E$75,物件データ!$H$5:$H$180,">0") -> 0 | F83: =COUNTIFS(物件データ!$L$5:$L$180,1,物件データ!$B$5:$B$180,$A83,物件データ!$J$5:$J$180,F$75)-COUNTIFS(物件データ!$L$5:$L$180,1,物件データ!$B$5:$B$180,$A83,物件データ!$J$5:$J$180,F$75,物件データ!$H$5:$H$180,">0") -> 0 | G83: =COUNTIFS(物件データ!$L$5:$L$180,1,物件データ!$B$5:$B$180,$A83,物件データ!$J$5:$J$180,G$75)-COUNTIFS(物件データ!$L$5:$L$180,1,物件データ!$B$5:$B$180,$A83,物件データ!$J$5:$J$180,G$75,物件データ!$H$5:$H$180,">0") -> 0 | H83: =COUNTIFS(物件データ!$L$5:$L$180,1,物件データ!$B$5:$B$180,$A83,物件データ!$J$5:$J$180,"?*")-COUNTIFS(物件データ!$L$5:$L$180,1,物件データ!$B$5:$B$180,$A83,物件データ!$J$5:$J$180,"?*",物件データ!$H$5:$H$180,">0") -> 1
A84: JT | B84: =COUNTIFS(物件データ!$L$5:$L$180,1,物件データ!$B$5:$B$180,$A84,物件データ!$J$5:$J$180,B$75)-COUNTIFS(物件データ!$L$5:$L$180,1,物件データ!$B$5:$B$180,$A84,物件データ!$J$5:$J$180,B$75,物件データ!$H$5:$H$180,">0") -> 0 | C84: =COUNTIFS(物件データ!$L$5:$L$180,1,物件データ!$B$5:$B$180,$A84,物件データ!$J$5:$J$180,C$75)-COUNTIFS(物件データ!$L$5:$L$180,1,物件データ!$B$5:$B$180,$A84,物件データ!$J$5:$J$180,C$75,物件データ!$H$5:$H$180,">0") -> 0 | D84: =COUNTIFS(物件データ!$L$5:$L$180,1,物件データ!$B$5:$B$180,$A84,物件データ!$J$5:$J$180,D$75)-COUNTIFS(物件データ!$L$5:$L$180,1,物件データ!$B$5:$B$180,$A84,物件データ!$J$5:$J$180,D$75,物件データ!$H$5:$H$180,">0") -> 0 | E84: =COUNTIFS(物件データ!$L$5:$L$180,1,物件データ!$B$5:$B$180,$A84,物件データ!$J$5:$J$180,E$75)-COUNTIFS(物件データ!$L$5:$L$180,1,物件データ!$B$5:$B$180,$A84,物件データ!$J$5:$J$180,E$75,物件データ!$H$5:$H$180,">0") -> 0 | F84: =COUNTIFS(物件データ!$L$5:$L$180,1,物件データ!$B$5:$B$180,$A84,物件データ!$J$5:$J$180,F$75)-COUNTIFS(物件データ!$L$5:$L$180,1,物件データ!$B$5:$B$180,$A84,物件データ!$J$5:$J$180,F$75,物件データ!$H$5:$H$180,">0") -> 0 | G84: =COUNTIFS(物件データ!$L$5:$L$180,1,物件データ!$B$5:$B$180,$A84,物件データ!$J$5:$J$180,G$75)-COUNTIFS(物件データ!$L$5:$L$180,1,物件データ!$B$5:$B$180,$A84,物件データ!$J$5:$J$180,G$75,物件データ!$H$5:$H$180,">0") -> 0 | H84: =COUNTIFS(物件データ!$L$5:$L$180,1,物件データ!$B$5:$B$180,$A84,物件データ!$J$5:$J$180,"?*")-COUNTIFS(物件データ!$L$5:$L$180,1,物件データ!$B$5:$B$180,$A84,物件データ!$J$5:$J$180,"?*",物件データ!$H$5:$H$180,">0") -> 0
A85: たちのき後転売MS | B85: =COUNTIFS(物件データ!$L$5:$L$180,1,物件データ!$B$5:$B$180,$A85,物件データ!$J$5:$J$180,B$75)-COUNTIFS(物件データ!$L$5:$L$180,1,物件データ!$B$5:$B$180,$A85,物件データ!$J$5:$J$180,B$75,物件データ!$H$5:$H$180,">0") -> 0 | C85: =COUNTIFS(物件データ!$L$5:$L$180,1,物件データ!$B$5:$B$180,$A85,物件データ!$J$5:$J$180,C$75)-COUNTIFS(物件データ!$L$5:$L$180,1,物件データ!$B$5:$B$180,$A85,物件データ!$J$5:$J$180,C$75,物件データ!$H$5:$H$180,">0") -> 0 | D85: =COUNTIFS(物件データ!$L$5:$L$180,1,物件データ!$B$5:$B$180,$A85,物件データ!$J$5:$J$180,D$75)-COUNTIFS(物件データ!$L$5:$L$180,1,物件データ!$B$5:$B$180,$A85,物件データ!$J$5:$J$180,D$75,物件データ!$H$5:$H$180,">0") -> 0 | E85: =COUNTIFS(物件データ!$L$5:$L$180,1,物件データ!$B$5:$B$180,$A85,物件データ!$J$5:$J$180,E$75)-COUNTIFS(物件データ!$L$5:$L$180,1,物件データ!$B$5:$B$180,$A85,物件データ!$J$5:$J$180,E$75,物件データ!$H$5:$H$180,">0") -> 0 | F85: =COUNTIFS(物件データ!$L$5:$L$180,1,物件データ!$B$5:$B$180,$A85,物件データ!$J$5:$J$180,F$75)-COUNTIFS(物件データ!$L$5:$L$180,1,物件データ!$B$5:$B$180,$A85,物件データ!$J$5:$J$180,F$75,物件データ!$H$5:$H$180,">0") -> 0 | G85: =COUNTIFS(物件データ!$L$5:$L$180,1,物件データ!$B$5:$B$180,$A85,物件データ!$J$5:$J$180,G$75)-COUNTIFS(物件データ!$L$5:$L$180,1,物件データ!$B$5:$B$180,$A85,物件データ!$J$5:$J$180,G$75,物件データ!$H$5:$H$180,">0") -> 0 | H85: =COUNTIFS(物件データ!$L$5:$L$180,1,物件データ!$B$5:$B$180,$A85,物件データ!$J$5:$J$180,"?*")-COUNTIFS(物件データ!$L$5:$L$180,1,物件データ!$B$5:$B$180,$A85,物件データ!$J$5:$J$180,"?*",物件データ!$H$5:$H$180,">0") -> 0
A86: 合計 | B86: =SUM(B76:B85) -> 27 | C86: =SUM(C76:C85) -> 4 | D86: =SUM(D76:D85) -> 0 | E86: =SUM(E76:E85) -> 2 | F86: =SUM(F76:F85) -> 1 | G86: =SUM(G76:G85) -> 0 | H86: =SUM(H76:H85) -> 34

Sheet ③成約価格分布
A1: ③ 期ごとの平均成約価格と価格分布（5,000万円きざみ）
A2: =" 集計対象："&設定!B4&"／販売価格が空欄の物件は除外" -> 集計対象：全て／販売価格が空欄の物件は除外
A4: 指標 | B4: 10期 | C4: 11期 | D4: 12期 | E4: 13期 | F4: 14期 | G4: 15期 | H4: 全期
A5: 棟数（価格あり） | B5: =COUNTIFS(物件データ!$L$5:$L$180,1,物件データ!$J$5:$J$180,B$4,物件データ!$G$5:$G$180,">0") -> 30 | C5: =COUNTIFS(物件データ!$L$5:$L$180,1,物件データ!$J$5:$J$180,C$4,物件データ!$G$5:$G$180,">0") -> 32 | D5: =COUNTIFS(物件データ!$L$5:$L$180,1,物件データ!$J$5:$J$180,D$4,物件データ!$G$5:$G$180,">0") -> 6 | E5: =COUNTIFS(物件データ!$L$5:$L$180,1,物件データ!$J$5:$J$180,E$4,物件データ!$G$5:$G$180,">0") -> 33 | F5: =COUNTIFS(物件データ!$L$5:$L$180,1,物件データ!$J$5:$J$180,F$4,物件データ!$G$5:$G$180,">0") -> 27 | G5: =COUNTIFS(物件データ!$L$5:$L$180,1,物件データ!$J$5:$J$180,G$4,物件データ!$G$5:$G$180,">0") -> 6 | H5: =COUNTIFS(物件データ!$L$5:$L$180,1,物件データ!$J$5:$J$180,"?*",物件データ!$G$5:$G$180,">0") -> 134
A6: 平均成約価格（円） | B6: =IFERROR(AVERAGEIFS(物件データ!$G$5:$G$180,物件データ!$L$5:$L$180,1,物件データ!$J$5:$J$180,B$4,物件データ!$G$5:$G$180,">0"),"") -> 62316667 | C6: =IFERROR(AVERAGEIFS(物件データ!$G$5:$G$180,物件データ!$L$5:$L$180,1,物件データ!$J$5:$J$180,C$4,物件データ!$G$5:$G$180,">0"),"") -> 75364062 | D6: =IFERROR(AVERAGEIFS(物件データ!$G$5:$G$180,物件データ!$L$5:$L$180,1,物件データ!$J$5:$J$180,D$4,物件データ!$G$5:$G$180,">0"),"") -> 70516667 | E6: =IFERROR(AVERAGEIFS(物件データ!$G$5:$G$180,物件データ!$L$5:$L$180,1,物件データ!$J$5:$J$180,E$4,物件データ!$G$5:$G$180,">0"),"") -> 63806061 | F6: =IFERROR(AVERAGEIFS(物件データ!$G$5:$G$180,物件データ!$L$5:$L$180,1,物件データ!$J$5:$J$180,F$4,物件データ!$G$5:$G$180,">0"),"") -> 1.0648889e+08 | G6: =IFERROR(AVERAGEIFS(物件データ!$G$5:$G$180,物件データ!$L$5:$L$180,1,物件データ!$J$5:$J$180,G$4,物件データ!$G$5:$G$180,">0"),"") -> 71650000 | H6: =IFERROR(AVERAGEIFS(物件データ!$G$5:$G$180,物件データ!$L$5:$L$180,1,物件データ!$J$5:$J$180,"?*",物件データ!$G$5:$G$180,">0"),"") -> 75484701
A7: 最低価格（円） | B7: =IFERROR(1/(1/_xlfn.MINIFS(物件データ!$G$5:$G$180,物件データ!$L$5:$L$180,1,物件データ!$J$5:$J$180,B$4,物件データ!$G$5:$G$180,">0")),"") -> 25900000 | C7: =IFERROR(1/(1/_xlfn.MINIFS(物件データ!$G$5:$G$180,物件データ!$L$5:$L$180,1,物件データ!$J$5:$J$180,C$4,物件データ!$G$5:$G$180,">0")),"") -> 19500000 | D7: =IFERROR(1/(1/_xlfn.MINIFS(物件データ!$G$5:$G$180,物件データ!$L$5:$L$180,1,物件データ!$J$5:$J$180,D$4,物件データ!$G$5:$G$180,">0")),"") -> 44800000 | E7: =IFERROR(1/(1/_xlfn.MINIFS(物件データ!$G$5:$G$180,物件データ!$L$5:$L$180,1,物件データ!$J$5:$J$180,E$4,物件データ!$G$5:$G$180,">0")),"") -> 6800000 | F7: =IFERROR(1/(1/_xlfn.MINIFS(物件データ!$G$5:$G$180,物件データ!$L$5:$L$180,1,物件データ!$J$5:$J$180,F$4,物件データ!$G$5:$G$180,">0")),"") -> 12000000 | G7: =IFERROR(1/(1/_xlfn.MINIFS(物件データ!$G$5:$G$180,物件データ!$L$5:$L$180,1,物件データ!$J$5:$J$180,G$4,物件データ!$G$5:$G$180,">0")),"") -> 29800000 | H7: =IFERROR(1/(1/_xlfn.MINIFS(物件データ!$G$5:$G$180,物件データ!$L$5:$L$180,1,物件データ!$J$5:$J$180,"?*",物件データ!$G$5:$G$180,">0")),"") -> 6800000
A8: 最高価格（円） | B8: =IFERROR(1/(1/_xlfn.MAXIFS(物件データ!$G$5:$G$180,物件データ!$L$5:$L$180,1,物件データ!$J$5:$J$180,B$4,物件データ!$G$5:$G$180,">0")),"") -> 138000000 | C8: =IFERROR(1/(1/_xlfn.MAXIFS(物件データ!$G$5:$G$180,物件データ!$L$5:$L$180,1,物件データ!$J$5:$J$180,C$4,物件データ!$G$5:$G$180,">0")),"") -> 400000000 | D8: =IFERROR(1/(1/_xlfn.MAXIFS(物件データ!$G$5:$G$180,物件データ!$L$5:$L$180,1,物件データ!$J$5:$J$180,D$4,物件データ!$G$5:$G$180,">0")),"") -> 99800000 | E8: =IFERROR(1/(1/_xlfn.MAXIFS(物件データ!$G$5:$G$180,物件データ!$L$5:$L$180,1,物件データ!$J$5:$J$180,E$4,物件データ!$G$5:$G$180,">0")),"") -> 320000000 | F8: =IFERROR(1/(1/_xlfn.MAXIFS(物件データ!$G$5:$G$180,物件データ!$L$5:$L$180,1,物件データ!$J$5:$J$180,F$4,物件データ!$G$5:$G$180,">0")),"") -> 300000000 | G8: =IFERROR(1/(1/_xlfn.MAXIFS(物件データ!$G$5:$G$180,物件データ!$L$5:$L$180,1,物件データ!$J$5:$J$180,G$4,物件データ!$G$5:$G$180,">0")),"") -> 180000000 | H8: =IFERROR(1/(1/_xlfn.MAXIFS(物件データ!$G$5:$G$180,物件データ!$L$5:$L$180,1,物件データ!$J$5:$J$180,"?*",物件データ!$G$5:$G$180,">0")),"") -> 400000000
A9: 売上高合計（円） | B9: =SUMIFS(物件データ!$G$5:$G$180,物件データ!$L$5:$L$180,1,物件データ!$J$5:$J$180,B$4) -> 1869500000 | C9: =SUMIFS(物件データ!$G$5:$G$180,物件データ!$L$5:$L$180,1,物件データ!$J$5:$J$180,C$4) -> 2411650000 | D9: =SUMIFS(物件データ!$G$5:$G$180,物件データ!$L$5:$L$180,1,物件データ!$J$5:$J$180,D$4) -> 423100000 | E9: =SUMIFS(物件データ!$G$5:$G$180,物件データ!$L$5:$L$180,1,物件データ!$J$5:$J$180,E$4) -> 2105600000 | F9: =SUMIFS(物件データ!$G$5:$G$180,物件データ!$L$5:$L$180,1,物件データ!$J$5:$J$180,F$4) -> 2875200000 | G9: =SUMIFS(物件データ!$G$5:$G$180,物件データ!$L$5:$L$180,1,物件データ!$J$5:$J$180,G$4) -> 429900000 | H9: =SUMIFS(物件データ!$G$5:$G$180,物件データ!$L$5:$L$180,1,物件データ!$J$5:$J$180,"?*") -> 10114950000
A12: 価格帯別 棟数
A13: 価格帯 | B13: 10期 | C13: 11期 | D13: 12期 | E13: 13期 | F13: 14期 | G13: 15期 | H13: 全期 | I13: 下限(円) | J13: 上限(円)
A14: ="〜"&IF(J14>=100000000,TEXT(J14/100000000,"0.0")&"億",TEXT(J14/10000,"#,##0")&"万")&"未満" -> 〜5,000万未満 | B14: =COUNTIFS(物件データ!$L$5:$L$180,1,物件データ!$J$5:$J$180,B$4,物件データ!$G$5:$G$180,">0",物件データ!$G$5:$G$180,"<"&$J14) -> 13 | C14: =COUNTIFS(物件データ!$L$5:$L$180,1,物件データ!$J$5:$J$180,C$4,物件データ!$G$5:$G$180,">0",物件データ!$G$5:$G$180,"<"&$J14) -> 15 | D14: =COUNTIFS(物件データ!$L$5:$L$180,1,物件データ!$J$5:$J$180,D$4,物件データ!$G$5:$G$180,">0",物件データ!$G$5:$G$180,"<"&$J14) -> 2 | E14: =COUNTIFS(物件データ!$L$5:$L$180,1,物件データ!$J$5:$J$180,E$4,物件データ!$G$5:$G$180,">0",物件データ!$G$5:$G$180,"<"&$J14) -> 19 | F14: =COUNTIFS(物件データ!$L$5:$L$180,1,物件データ!$J$5:$J$180,F$4,物件データ!$G$5:$G$180,">0",物件データ!$G$5:$G$180,"<"&$J14) -> 6 | G14: =COUNTIFS(物件データ!$L$5:$L$180,1,物件データ!$J$5:$J$180,G$4,物件データ!$G$5:$G$180,">0",物件データ!$G$5:$G$180,"<"&$J14) -> 2 | H14: =COUNTIFS(物件データ!$L$5:$L$180,1,物件データ!$J$5:$J$180,"?*",物件データ!$G$5:$G$180,">0",物件データ!$G$5:$G$180,"<"&$J14) -> 57 | I14: =設定!$B$5*0 -> 0 | J14: =設定!$B$5*1 -> 50000000
A15: =IF(I15>=100000000,TEXT(I15/100000000,"0.0")&"億",TEXT(I15/10000,"#,##0")&"万")&"〜"&IF(J15>=100000000,TEXT(J15/100000000,"0.0")&"億",TEXT(J15/10000,"#,##0")&"万")&"未満" -> 5,000万〜1.0億未満 | B15: =COUNTIFS(物件データ!$L$5:$L$180,1,物件データ!$J$5:$J$180,B$4,物件データ!$G$5:$G$180,">="&$I15,物件データ!$G$5:$G$180,"<"&$J15) -> 14 | C15: =COUNTIFS(物件データ!$L$5:$L$180,1,物件データ!$J$5:$J$180,C$4,物件データ!$G$5:$G$180,">="&$I15,物件データ!$G$5:$G$180,"<"&$J15) -> 13 | D15: =COUNTIFS(物件データ!$L$5:$L$180,1,物件データ!$J$5:$J$180,D$4,物件データ!$G$5:$G$180,">="&$I15,物件データ!$G$5:$G$180,"<"&$J15) -> 4 | E15: =COUNTIFS(物件データ!$L$5:$L$180,1,物件データ!$J$5:$J$180,E$4,物件データ!$G$5:$G$180,">="&$I15,物件データ!$G$5:$G$180,"<"&$J15) -> 8 | F15: =COUNTIFS(物件データ!$L$5:$L$180,1,物件データ!$J$5:$J$180,F$4,物件データ!$G$5:$G$180,">="&$I15,物件データ!$G$5:$G$180,"<"&$J15) -> 11 | G15: =COUNTIFS(物件データ!$L$5:$L$180,1,物件データ!$J$5:$J$180,G$4,物件データ!$G$5:$G$180,">="&$I15,物件データ!$G$5:$G$180,"<"&$J15) -> 3 | H15: =COUNTIFS(物件データ!$L$5:$L$180,1,物件データ!$J$5:$J$180,"?*",物件データ!$G$5:$G$180,">="&$I15,物件データ!$G$5:$G$180,"<"&$J15) -> 53 | I15: =設定!$B$5*1 -> 50000000 | J15: =設定!$B$5*2 -> 100000000
A16: =IF(I16>=100000000,TEXT(I16/100000000,"0.0")&"億",TEXT(I16/10000,"#,##0")&"万")&"〜"&IF(J16>=100000000,TEXT(J16/100000000,"0.0")&"億",TEXT(J16/10000,"#,##0")&"万")&"未満" -> 1.0億〜1.5億未満 | B16: =COUNTIFS(物件データ!$L$5:$L$180,1,物件データ!$J$5:$J$180,B$4,物件データ!$G$5:$G$180,">="&$I16,物件データ!$G$5:$G$180,"<"&$J16) -> 3 | C16: =COUNTIFS(物件データ!$L$5:$L$180,1,物件データ!$J$5:$J$180,C$4,物件データ!$G$5:$G$180,">="&$I16,物件データ!$G$5:$G$180,"<"&$J16) -> 1 | D16: =COUNTIFS(物件データ!$L$5:$L$180,1,物件データ!$J$5:$J$180,D$4,物件データ!$G$5:$G$180,">="&$I16,物件データ!$G$5:$G$180,"<"&$J16) -> 0 | E16: =COUNTIFS(物件データ!$L$5:$L$180,1,物件データ!$J$5:$J$180,E$4,物件データ!$G$5:$G$180,">="&$I16,物件データ!$G$5:$G$180,"<"&$J16) -> 5 | F16: =COUNTIFS(物件データ!$L$5:$L$180,1,物件データ!$J$5:$J$180,F$4,物件データ!$G$5:$G$180,">="&$I16,物件データ!$G$5:$G$180,"<"&$J16) -> 5 | G16: =COUNTIFS(物件データ!$L$5:$L$180,1,物件データ!$J$5:$J$180,G$4,物件データ!$G$5:$G$180,">="&$I16,物件データ!$G$5:$G$180,"<"&$J16) -> 0 | H16: =COUNTIFS(物件データ!$L$5:$L$180,1,物件データ!$J$5:$J$180,"?*",物件データ!$G$5:$G$180,">="&$I16,物件データ!$G$5:$G$180,"<"&$J16) -> 14 | I16: =設定!$B$5*2 -> 100000000 | J16: =設定!$B$5*3 -> 150000000
A17: =IF(I17>=100000000,TEXT(I17/100000000,"0.0")&"億",TEXT(I17/10000,"#,##0")&"万")&"〜"&IF(J17>=100000000,TEXT(J17/100000000,"0.0")&"億",TEXT(J17/10000,"#,##0")&"万")&"未満" -> 1.5億〜2.0億未満 | B17: =COUNTIFS(物件データ!$L$5:$L$180,1,物件データ!$J$5:$J$180,B$4,物件データ!$G$5:$G$180,">="&$I17,物件データ!$G$5:$G$180,"<"&$J17) -> 0 | C17: =COUNTIFS(物件データ!$L$5:$L$180,1,物件データ!$J$5:$J$180,C$4,物件データ!$G$5:$G$180,">="&$I17,物件データ!$G$5:$G$180,"<"&$J17) -> 0 | D17: =COUNTIFS(物件データ!$L$5:$L$180,1,物件データ!$J$5:$J$180,D$4,物件データ!$G$5:$G$180,">="&$I17,物件データ!$G$5:$G$180,"<"&$J17) -> 0 | E17: =COUNTIFS(物件データ!$L$5:$L$180,1,物件データ!$J$5:$J$180,E$4,物件データ!$G$5:$G$180,">="&$I17,物件データ!$G$5:$G$180,"<"&$J17) -> 0 | F17: =COUNTIFS(物件データ!$L$5:$L$180,1,物件データ!$J$5:$J$180,F$4,物件データ!$G$5:$G$180,">="&$I17,物件データ!$G$5:$G$180,"<"&$J17) -> 2 | G17: =COUNTIFS(物件データ!$L$5:$L$180,1,物件データ!$J$5:$J$180,G$4,物件データ!$G$5:$G$180,">="&$I17,物件データ!$G$5:$G$180,"<"&$J17) -> 1 | H17: =COUNTIFS(物件データ!$L$5:$L$180,1,物件データ!$J$5:$J$180,"?*",物件データ!$G$5:$G$180,">="&$I17,物件データ!$G$5:$G$180,"<"&$J17) -> 3 | I17: =設定!$B$5*3 -> 150000000 | J17: =設定!$B$5*4 -> 200000000
A18: =IF(I18>=100000000,TEXT(I18/100000000,"0.0")&"億",TEXT(I18/10000,"#,##0")&"万")&"〜"&IF(J18>=100000000,TEXT(J18/100000000,"0.0")&"億",TEXT(J18/10000,"#,##0")&"万")&"未満" -> 2.0億〜2.5億未満 | B18: =COUNTIFS(物件データ!$L$5:$L$180,1,物件データ!$J$5:$J$180,B$4,物件データ!$G$5:$G$180,">="&$I18,物件データ!$G$5:$G$180,"<"&$J18) -> 0 | C18: =COUNTIFS(物件データ!$L$5:$L$180,1,物件データ!$J$5:$J$180,C$4,物件データ!$G$5:$G$180,">="&$I18,物件データ!$G$5:$G$180,"<"&$J18) -> 2 | D18: =COUNTIFS(物件データ!$L$5:$L$180,1,物件データ!$J$5:$J$180,D$4,物件データ!$G$5:$G$180,">="&$I18,物件データ!$G$5:$G$180,"<"&$J18) -> 0 | E18: =COUNTIFS(物件データ!$L$5:$L$180,1,物件データ!$J$5:$J$180,E$4,物件データ!$G$5:$G$180,">="&$I18,物件データ!$G$5:$G$180,"<"&$J18) -> 0 | F18: =COUNTIFS(物件データ!$L$5:$L$180,1,物件データ!$J$5:$J$180,F$4,物件データ!$G$5:$G$180,">="&$I18,物件データ!$G$5:$G$180,"<"&$J18) -> 1 | G18: =COUNTIFS(物件データ!$L$5:$L$180,1,物件データ!$J$5:$J$180,G$4,物件データ!$G$5:$G$180,">="&$I18,物件データ!$G$5:$G$180,"<"&$J18) -> 0 | H18: =COUNTIFS(物件データ!$L$5:$L$180,1,物件データ!$J$5:$J$180,"?*",物件データ!$G$5:$G$180,">="&$I18,物件データ!$G$5:$G$180,"<"&$J18) -> 3 | I18: =設定!$B$5*4 -> 200000000 | J18: =設定!$B$5*5 -> 250000000
A19: =IF(I19>=100000000,TEXT(I19/100000000,"0.0")&"億",TEXT(I19/10000,"#,##0")&"万")&"〜"&IF(J19>=100000000,TEXT(J19/100000000,"0.0")&"億",TEXT(J19/10000,"#,##0")&"万")&"未満" -> 2.5億〜3.0億未満 | B19: =COUNTIFS(物件データ!$L$5:$L$180,1,物件データ!$J$5:$J$180,B$4,物件データ!$G$5:$G$180,">="&$I19,物件データ!$G$5:$G$180,"<"&$J19) -> 0 | C19: =COUNTIFS(物件データ!$L$5:$L$180,1,物件データ!$J$5:$J$180,C$4,物件データ!$G$5:$G$180,">="&$I19,物件データ!$G$5:$G$180,"<"&$J19) -> 0 | D19: =COUNTIFS(物件データ!$L$5:$L$180,1,物件データ!$J$5:$J$180,D$4,物件データ!$G$5:$G$180,">="&$I19,物件データ!$G$5:$G$180,"<"&$J19) -> 0 | E19: =COUNTIFS(物件データ!$L$5:$L$180,1,物件データ!$J$5:$J$180,E$4,物件データ!$G$5:$G$180,">="&$I19,物件データ!$G$5:$G$180,"<"&$J19) -> 0 | F19: =COUNTIFS(物件データ!$L$5:$L$180,1,物件データ!$J$5:$J$180,F$4,物件データ!$G$5:$G$180,">="&$I19,物件データ!$G$5:$G$180,"<"&$J19) -> 1 | G19: =COUNTIFS(物件データ!$L$5:$L$180,1,物件データ!$J$5:$J$180,G$4,物件データ!$G$5:$G$180,">="&$I19,物件データ!$G$5:$G$180,"<"&$J19) -> 0 | H19: =COUNTIFS(物件データ!$L$5:$L$180,1,物件データ!$J$5:$J$180,"?*",物件データ!$G$5:$G$180,">="&$I19,物件データ!$G$5:$G$180,"<"&$J19) -> 1 | I19: =設定!$B$5*5 -> 250000000 | J19: =設定!$B$5*6 -> 300000000
A20: =IF(I20>=100000000,TEXT(I20/100000000,"0.0")&"億",TEXT(I20/10000,"#,##0")&"万")&"〜"&IF(J20>=100000000,TEXT(J20/100000000,"0.0")&"億",TEXT(J20/10000,"#,##0")&"万")&"未満" -> 3.0億〜3.5億未満 | B20: =COUNTIFS(物件データ!$L$5:$L$180,1,物件データ!$J$5:$J$180,B$4,物件データ!$G$5:$G$180,">="&$I20,物件データ!$G$5:$G$180,"<"&$J20) -> 0 | C20: =COUNTIFS(物件データ!$L$5:$L$180,1,物件データ!$J$5:$J$180,C$4,物件データ!$G$5:$G$180,">="&$I20,物件データ!$G$5:$G$180,"<"&$J20) -> 0 | D20: =COUNTIFS(物件データ!$L$5:$L$180,1,物件データ!$J$5:$J$180,D$4,物件データ!$G$5:$G$180,">="&$I20,物件データ!$G$5:$G$180,"<"&$J20) -> 0 | E20: =COUNTIFS(物件データ!$L$5:$L$180,1,物件データ!$J$5:$J$180,E$4,物件データ!$G$5:$G$180,">="&$I20,物件データ!$G$5:$G$180,"<"&$J20) -> 1 | F20: =COUNTIFS(物件データ!$L$5:$L$180,1,物件データ!$J$5:$J$180,F$4,物件データ!$G$5:$G$180,">="&$I20,物件データ!$G$5:$G$180,"<"&$J20) -> 1 | G20: =COUNTIFS(物件データ!$L$5:$L$180,1,物件データ!$J$5:$J$180,G$4,物件データ!$G$5:$G$180,">="&$I20,物件データ!$G$5:$G$180,"<"&$J20) -> 0 | H20: =COUNTIFS(物件データ!$L$5:$L$180,1,物件データ!$J$5:$J$180,"?*",物件データ!$G$5:$G$180,">="&$I20,物件データ!$G$5:$G$180,"<"&$J20) -> 2 | I20: =設定!$B$5*6 -> 300000000 | J20: =設定!$B$5*7 -> 350000000
A21: =IF(I21>=100000000,TEXT(I21/100000000,"0.0")&"億",TEXT(I21/10000,"#,##0")&"万")&"〜"&IF(J21>=100000000,TEXT(J21/100000000,"0.0")&"億",TEXT(J21/10000,"#,##0")&"万")&"未満" -> 3.5億〜4.0億未満 | B21: =COUNTIFS(物件データ!$L$5:$L$180,1,物件データ!$J$5:$J$180,B$4,物件データ!$G$5:$G$180,">="&$I21,物件データ!$G$5:$G$180,"<"&$J21) -> 0 | C21: =COUNTIFS(物件データ!$L$5:$L$180,1,物件データ!$J$5:$J$180,C$4,物件データ!$G$5:$G$180,">="&$I21,物件データ!$G$5:$G$180,"<"&$J21) -> 0 | D21: =COUNTIFS(物件データ!$L$5:$L$180,1,物件データ!$J$5:$J$180,D$4,物件データ!$G$5:$G$180,">="&$I21,物件データ!$G$5:$G$180,"<"&$J21) -> 0 | E21: =COUNTIFS(物件データ!$L$5:$L$180,1,物件データ!$J$5:$J$180,E$4,物件データ!$G$5:$G$180,">="&$I21,物件データ!$G$5:$G$180,"<"&$J21) -> 0 | F21: =COUNTIFS(物件データ!$L$5:$L$180,1,物件データ!$J$5:$J$180,F$4,物件データ!$G$5:$G$180,">="&$I21,物件データ!$G$5:$G$180,"<"&$J21) -> 0 | G21: =COUNTIFS(物件データ!$L$5:$L$180,1,物件データ!$J$5:$J$180,G$4,物件データ!$G$5:$G$180,">="&$I21,物件データ!$G$5:$G$180,"<"&$J21) -> 0 | H21: =COUNTIFS(物件データ!$L$5:$L$180,1,物件データ!$J$5:$J$180,"?*",物件データ!$G$5:$G$180,">="&$I21,物件データ!$G$5:$G$180,"<"&$J21) -> 0 | I21: =設定!$B$5*7 -> 350000000 | J21: =設定!$B$5*8 -> 400000000
A22: =IF(I22>=100000000,TEXT(I22/100000000,"0.0")&"億",TEXT(I22/10000,"#,##0")&"万")&"〜"&IF(J22>=100000000,TEXT(J22/100000000,"0.0")&"億",TEXT(J22/10000,"#,##0")&"万")&"未満" -> 4.0億〜4.5億未満 | B22: =COUNTIFS(物件データ!$L$5:$L$180,1,物件データ!$J$5:$J$180,B$4,物件データ!$G$5:$G$180,">="&$I22,物件データ!$G$5:$G$180,"<"&$J22) -> 0 | C22: =COUNTIFS(物件データ!$L$5:$L$180,1,物件データ!$J$5:$J$180,C$4,物件データ!$G$5:$G$180,">="&$I22,物件データ!$G$5:$G$180,"<"&$J22) -> 1 | D22: =COUNTIFS(物件データ!$L$5:$L$180,1,物件データ!$J$5:$J$180,D$4,物件データ!$G$5:$G$180,">="&$I22,物件データ!$G$5:$G$180,"<"&$J22) -> 0 | E22: =COUNTIFS(物件データ!$L$5:$L$180,1,物件データ!$J$5:$J$180,E$4,物件データ!$G$5:$G$180,">="&$I22,物件データ!$G$5:$G$180,"<"&$J22) -> 0 | F22: =COUNTIFS(物件データ!$L$5:$L$180,1,物件データ!$J$5:$J$180,F$4,物件データ!$G$5:$G$180,">="&$I22,物件データ!$G$5:$G$180,"<"&$J22) -> 0 | G22: =COUNTIFS(物件データ!$L$5:$L$180,1,物件データ!$J$5:$J$180,G$4,物件データ!$G$5:$G$180,">="&$I22,物件データ!$G$5:$G$180,"<"&$J22) -> 0 | H22: =COUNTIFS(物件データ!$L$5:$L$180,1,物件データ!$J$5:$J$180,"?*",物件データ!$G$5:$G$180,">="&$I22,物件データ!$G$5:$G$180,"<"&$J22) -> 1 | I22: =設定!$B$5*8 -> 400000000 | J22: =設定!$B$5*9 -> 450000000
A23: 合計 | B23: =SUM(B14:B22) -> 30 | C23: =SUM(C14:C22) -> 32 | D23: =SUM(D14:D22) -> 6 | E23: =SUM(E14:E22) -> 33 | F23: =SUM(F14:F22) -> 27 | G23: =SUM(G14:G22) -> 6 | H23: =SUM(H14:H22) -> 134
A25: 価格帯別 構成比
A26: 価格帯 | B26: 10期 | C26: 11期 | D26: 12期 | E26: 13期 | F26: 14期 | G26: 15期 | H26: 全期
A27: =A14 -> 〜5,000万未満 | B27: =IF(B$23=0,"",B14/B$23) -> 0.43333333 | C27: =IF(C$23=0,"",C14/C$23) -> 0.46875 | D27: =IF(D$23=0,"",D14/D$23) -> 0.33333333 | E27: =IF(E$23=0,"",E14/E$23) -> 0.57575758 | F27: =IF(F$23=0,"",F14/F$23) -> 0.22222222 | G27: =IF(G$23=0,"",G14/G$23) -> 0.33333333 | H27: =IF(H$23=0,"",H14/H$23) -> 0.42537313
A28: =A15 -> 5,000万〜1.0億未満 | B28: =IF(B$23=0,"",B15/B$23) -> 0.46666667 | C28: =IF(C$23=0,"",C15/C$23) -> 0.40625 | D28: =IF(D$23=0,"",D15/D$23) -> 0.66666667 | E28: =IF(E$23=0,"",E15/E$23) -> 0.24242424 | F28: =IF(F$23=0,"",F15/F$23) -> 0.40740741 | G28: =IF(G$23=0,"",G15/G$23) -> 0.5 | H28: =IF(H$23=0,"",H15/H$23) -> 0.39552239
A29: =A16 -> 1.0億〜1.5億未満 | B29: =IF(B$23=0,"",B16/B$23) -> 0.1 | C29: =IF(C$23=0,"",C16/C$23) -> 0.03125 | D29: =IF(D$23=0,"",D16/D$23) -> 0 | E29: =IF(E$23=0,"",E16/E$23) -> 0.15151515 | F29: =IF(F$23=0,"",F16/F$23) -> 0.18518519 | G29: =IF(G$23=0,"",G16/G$23) -> 0 | H29: =IF(H$23=0,"",H16/H$23) -> 0.10447761
A30: =A17 -> 1.5億〜2.0億未満 | B30: =IF(B$23=0,"",B17/B$23) -> 0 | C30: =IF(C$23=0,"",C17/C$23) -> 0 | D30: =IF(D$23=0,"",D17/D$23) -> 0 | E30: =IF(E$23=0,"",E17/E$23) -> 0 | F30: =IF(F$23=0,"",F17/F$23) -> 0.074074074 | G30: =IF(G$23=0,"",G17/G$23) -> 0.16666667 | H30: =IF(H$23=0,"",H17/H$23) -> 0.02238806
A31: =A18 -> 2.0億〜2.5億未満 | B31: =IF(B$23=0,"",B18/B$23) -> 0 | C31: =IF(C$23=0,"",C18/C$23) -> 0.0625 | D31: =IF(D$23=0,"",D18/D$23) -> 0 | E31: =IF(E$23=0,"",E18/E$23) -> 0 | F31: =IF(F$23=0,"",F18/F$23) -> 0.037037037 | G31: =IF(G$23=0,"",G18/G$23) -> 0 | H31: =IF(H$23=0,"",H18/H$23) -> 0.02238806
A32: =A19 -> 2.5億〜3.0億未満 | B32: =IF(B$23=0,"",B19/B$23) -> 0 | C32: =IF(C$23=0,"",C19/C$23) -> 0 | D32: =IF(D$23=0,"",D19/D$23) -> 0 | E32: =IF(E$23=0,"",E19/E$23) -> 0 | F32: =IF(F$23=0,"",F19/F$23) -> 0.037037037 | G32: =IF(G$23=0,"",G19/G$23) -> 0 | H32: =IF(H$23=0,"",H19/H$23) -> 0.0074626866
A33: =A20 -> 3.0億〜3.5億未満 | B33: =IF(B$23=0,"",B20/B$23) -> 0 | C33: =IF(C$23=0,"",C20/C$23) -> 0 | D33: =IF(D$23=0,"",D20/D$23) -> 0 | E33: =IF(E$23=0,"",E20/E$23) -> 0.03030303 | F33: =IF(F$23=0,"",F20/F$23) -> 0.037037037 | G33: =IF(G$23=0,"",G20/G$23) -> 0 | H33: =IF(H$23=0,"",H20/H$23) -> 0.014925373
A34: =A21 -> 3.5億〜4.0億未満 | B34: =IF(B$23=0,"",B21/B$23) -> 0 | C34: =IF(C$23=0,"",C21/C$23) -> 0 | D34: =IF(D$23=0,"",D21/D$23) -> 0 | E34: =IF(E$23=0,"",E21/E$23) -> 0 | F34: =IF(F$23=0,"",F21/F$23) -> 0 | G34: =IF(G$23=0,"",G21/G$23) -> 0 | H34: =IF(H$23=0,"",H21/H$23) -> 0
A35: =A22 -> 4.0億〜4.5億未満 | B35: =IF(B$23=0,"",B22/B$23) -> 0 | C35: =IF(C$23=0,"",C22/C$23) -> 0.03125 | D35: =IF(D$23=0,"",D22/D$23) -> 0 | E35: =IF(E$23=0,"",E22/E$23) -> 0 | F35: =IF(F$23=0,"",F22/F$23) -> 0 | G35: =IF(G$23=0,"",G22/G$23) -> 0 | H35: =IF(H$23=0,"",H22/H$23) -> 0.0074626866

Sheet 設定
A1: 設定（黄色セルのみ編集）
A3: 基準日 | B3: 46294 | C3: これ以前の売却決済＝実績、以降＝予定
A4: 集計対象 | B4: 全て | C4: 「全て」＝実績＋予定 ／「実績のみ」＝基準日以前の決済分だけ
A5: 価格帯の刻み(円) | B5: 50000000
A7: 期 | B7: 開始日 | C7: 終了日 | D7: 備考
A8: 9期 | B8: 44378 | C8: 44742
A9: 10期 | B9: 44743 | C9: 45107
A10: 11期 | B10: 45108 | C10: 45473
A11: 12期 | B11: 45474 | C11: 45565 | D11: 決算期変更の3ヶ月変則
A12: 13期 | B12: 45566 | C12: 45930
A13: 14期 | B13: 45931 | C13: 46295
A14: 15期 | B14: 46296 | C14: 46660
A15: 16期 | B15: 46661 | C15: 47026
A17: 【前提】
A18: ・期は売却決済日（売上計上日）で判定。ビルド期数＝グループ期数−2（ビルド15期＝2026.10–2027.9）
A19: ・売上高＝販売価格（入力シートH列）。粗利＝販売価格−仕入原価−商品化原価（販売諸費用・支払利息は含めない＝会計上の粗利）
A20: ・仕入原価＝入力シートI〜M列、商品化原価＝P,R,T,…,AJ列（リフォーム・解体・立退・建物・その他①〜⑤）
A21: ・仕入原価が未入力の物件は粗利・粗利率の集計から除外（売上高・棟数には含む）
A22: ・保有日数＝売却決済日−仕入決済日
A23: ・出所：8a692c1c-BU__CF_-_______________9_4___________VER.xlsx「入力シート」 作成日 2026/09/29
